Workbook
Name Excel_BuiltIn_Print_Area_1: #REF!
Name Excel_BuiltIn_Print_Area_1: #REF!
Name Excel_BuiltIn_Print_Area_2: #REF!
Name Excel_BuiltIn_Print_Area_2: #REF!
Name Excel_BuiltIn_Print_Titles_1: #REF!
Name Excel_BuiltIn_Print_Titles_1: #REF!
Name Print_Titles: РДДС!$A:$B,РДДС!$2:$5

Sheet Вводные данные
B2: Вводные данные
A3: № | B3: Показатель | C3: 1 год | D3: 2 год | E3: 3 год
A4: 1 | B4: Инфляция | C4: 0 | D4: 0.15 | E4: 0.15
A5: 2 | B5: Потери при сбыте готовой продукции/ реализации товара | C5: 0 | D5: 0 | E5: 0
A6: 3 | B6: Размер обязательных взносов за ИП | C6: 53658 | D6: 57390 | E6: 61154
B8: Сезонность продаж
A9: № | B9: Месяц - начало продаж | C9: 45809 | D9: =EDATE(C9,1) -> 45839 | E9: =EDATE(D9,1) -> 45870 | F9: =EDATE(E9,1) -> 45901 | G9: =EDATE(F9,1) -> 45931 | H9: =EDATE(G9,1) -> 45962 | I9: =EDATE(H9,1) -> 45992 | J9: =EDATE(I9,1) -> 46023 | K9: =EDATE(J9,1) -> 46054 | ... N9: =EDATE(M9,1) -> 46143
A10: 1 | B10: Показатель | C10: 1 | D10: 0.9 | E10: 0.7 | F10: 0.7 | G10: 0.65 | H10: 0.65 | I10: 0.85 | J10: 0.65 | K10: 0.75 | L10: 0.7 | M10: 0.8 | N10: 0.9
B12: *Примечание: в шапке таблицы "Сезонность продаж" самостоятельно прописать месяц и год начала продаж в первом столбце. Во всем документе будет произведено автоматическое обновление дат!!!
B13: Месяц начала продаж должен идти после завершение всех этапов проекта!!!

Sheet РДДС
D2: Расчет движения денежных средств
A4: Код | B4: Наименование статьи | C4: Инвестиционный месяц | D4: 1 год | P4: Итого за 1 год | Q4: 2 год | AC4: Итого за 2 год | AD4: 3 год | AP4: Итого за 3 год | AQ4: Итого по проекту
D5: ='Вводные данные'!C9 -> 45809 | E5: ='Вводные данные'!D9 -> 45839 | F5: ='Вводные данные'!E9 -> 45870 | G5: ='Вводные данные'!F9 -> 45901 | H5: ='Вводные данные'!G9 -> 45931 | I5: ='Вводные данные'!H9 -> 45962 | J5: ='Вводные данные'!I9 -> 45992 | K5: ='Вводные данные'!J9 -> 46023 | ... O5: ='Вводные данные'!N9 -> 46143 | Q5: =EDATE(O5,1) -> 46174 | R5: =EDATE(Q5,1) -> 46204 | S5: =EDATE(R5,1) -> 46235 | T5: =EDATE(S5,1) -> 46266 | U5: =EDATE(T5,1) -> 46296 | V5: =EDATE(U5,1) -> 46327 | W5: =EDATE(V5,1) -> 46357 | X5: =EDATE(W5,1) -> 46388 | Y5: =EDATE(X5,1) -> 46419 | ... AB5: =EDATE(AA5,1) -> 46508 | AD5: =EDATE(AB5,1) -> 46539 | AE5: =EDATE(AD5,1) -> 46569 | AF5: =EDATE(AE5,1) -> 46600 | AG5: =EDATE(AF5,1) -> 46631 | AH5: =EDATE(AG5,1) -> 46661 | AI5: =EDATE(AH5,1) -> 46692 | AJ5: =EDATE(AI5,1) -> 46722 | AK5: =EDATE(AJ5,1) -> 46753 | AL5: =EDATE(AK5,1) -> 46784 | ... AO5: =EDATE(AN5,1) -> 46874
A6: 1 | B6: Доходы | D6: =Продажи!B31 -> 324000 | E6: =Продажи!C31 -> 79000 | F6: =Продажи!D31 -> 709000 | G6: =Продажи!E31 -> 264000 | H6: =Продажи!F31 -> 564000 | I6: =Продажи!G31 -> 714000 | J6: =Продажи!H31 -> 764000 | K6: =Продажи!I31 -> 791000 | ... O6: =Продажи!M31 -> 1191000 | P6: =SUM(D6:O6) -> 8458000 | Q6: =Продажи!O31 -> 1899800 | R6: =Продажи!P31 -> 2354050 | S6: =Продажи!Q31 -> 2256300 | T6: =Продажи!R31 -> 3042516.7 | U6: =Продажи!S31 -> 2657841.7 | V6: =Продажи!T31 -> 3132216.7 | W6: =Продажи!U31 -> 3068391.7 | X6: =Продажи!V31 -> 3850966.7 | ... AB6: =Продажи!Z31 -> 4636416.7 | AC6: =SUM(Q6:AB6) -> 38144350 | AD6: =Продажи!AB31 -> 5135267.5 | AE6: =Продажи!AC31 -> 5442087.5 | AF6: =Продажи!AD31 -> 5032112.5 | AG6: =Продажи!AE31 -> 5994892.5 | AH6: =Продажи!AF31 -> 5628560 | AI6: =Продажи!AG31 -> 6562245 | AJ6: =Продажи!AH31 -> 6280552.5 | AK6: =Продажи!AI31 -> 7216882.5 | ... AO6: =Продажи!AM31 -> 8356877.5 | AP6: =SUM(AD6:AO6) -> 77633395 | AQ6: =P6+AC6+AP6 -> 1.2423574e+08
A7: 2 | B7: Фонд оплаты труда (трудовые договора) | D7: =Персонал!B46 -> 520000 | E7: =Персонал!C46 -> 520000 | F7: =Персонал!D46 -> 520000 | G7: =Персонал!E46 -> 520000 | H7: =Персонал!F46 -> 520000 | I7: =Персонал!G46 -> 520000 | J7: =Персонал!H46 -> 520000 | K7: =Персонал!I46 -> 520000 | ... O7: =Персонал!M46 -> 520000 | P7: =SUM(D7:O7) -> 6240000 | Q7: =Персонал!O46 -> 1058000 | R7: =Персонал!P46 -> 1058000 | S7: =Персонал!Q46 -> 1058000 | T7: =Персонал!R46 -> 1058000 | U7: =Персонал!S46 -> 1058000 | V7: =Персонал!T46 -> 1058000 | W7: =Персонал!U46 -> 1058000 | X7: =Персонал!V46 -> 1058000 | ... AB7: =Персонал!Z46 -> 1058000 | AC7: =SUM(Q7:AB7) -> 12696000 | AD7: =Персонал!AB46 -> 1216700 | AE7: =Персонал!AC46 -> 1216700 | AF7: =Персонал!AD46 -> 1216700 | AG7: =Персонал!AE46 -> 1216700 | AH7: =Персонал!AF46 -> 1216700 | AI7: =Персонал!AG46 -> 1216700 | AJ7: =Персонал!AH46 -> 1216700 | AK7: =Персонал!AI46 -> 1216700 | ... AO7: =Персонал!AM46 -> 1216700 | AP7: =SUM(AD7:AO7) -> 14600400 | AQ7: =P7+AC7+AP7 -> 33536400
A8: 2.1 | B8: НДФЛ (ФОТ 13%) | D8: =D7*13% -> 67600 | E8: =E7*13% -> 67600 | F8: =F7*13% -> 67600 | G8: =G7*13% -> 67600 | H8: =H7*13% -> 67600 | I8: =I7*13% -> 67600 | J8: =J7*13% -> 67600 | K8: =K7*13% -> 67600 | ... O8: =O7*13% -> 67600 | P8: =SUM(D8:O8) -> 811200 | Q8: =Q7*13% -> 137540 | R8: =R7*13% -> 137540 | S8: =S7*13% -> 137540 | T8: =T7*13% -> 137540 | U8: =U7*13% -> 137540 | V8: =V7*13% -> 137540 | W8: =W7*13% -> 137540 | X8: =X7*13% -> 137540 | ... AB8: =AB7*13% -> 137540 | AC8: =SUM(Q8:AB8) -> 1650480 | AD8: =AD7*13% -> 158171 | AE8: =AE7*13% -> 158171 | AF8: =AF7*13% -> 158171 | AG8: =AG7*13% -> 158171 | AH8: =AH7*13% -> 158171 | AI8: =AI7*13% -> 158171 | AJ8: =AJ7*13% -> 158171 | AK8: =AK7*13% -> 158171 | ... AO8: =AO7*13% -> 158171 | AP8: =SUM(AD8:AO8) -> 1898052 | AQ8: =P8+AC8+AP8 -> 4359732
A9: 3 | B9: Взносы (ФОТ) | D9: =SUM(D10:D12) -> 157040 | E9: =SUM(E10:E12) -> 157040 | F9: =SUM(F10:F12) -> 157040 | G9: =SUM(G10:G12) -> 157040 | H9: =SUM(H10:H12) -> 157040 | I9: =SUM(I10:I12) -> 157040 | J9: =SUM(J10:J12) -> 157040 | K9: =SUM(K10:K12) -> 157040 | ... O9: =SUM(O10:O12) -> 157040 | P9: =SUM(D9:O9) -> 1884480 | Q9: =SUM(Q10:Q12) -> 319516 | R9: =SUM(R10:R12) -> 319516 | S9: =SUM(S10:S12) -> 319516 | T9: =SUM(T10:T12) -> 319516 | U9: =SUM(U10:U12) -> 319516 | V9: =SUM(V10:V12) -> 319516 | W9: =SUM(W10:W12) -> 319516 | X9: =SUM(X10:X12) -> 319516 | ... AB9: =SUM(AB10:AB12) -> 319516 | AC9: =SUM(Q9:AB9) -> 3834192 | AD9: =SUM(AD10:AD12) -> 367443.4 | AE9: =SUM(AE10:AE12) -> 367443.4 | AF9: =SUM(AF10:AF12) -> 367443.4 | AG9: =SUM(AG10:AG12) -> 367443.4 | AH9: =SUM(AH10:AH12) -> 367443.4 | AI9: =SUM(AI10:AI12) -> 367443.4 | AJ9: =SUM(AJ10:AJ12) -> 367443.4 | AK9: =SUM(AK10:AK12) -> 367443.4 | ... AO9: =SUM(AO10:AO12) -> 367443.4 | AP9: =SUM(AD9:AO9) -> 4409320.8 | AQ9: =P9+AC9+AP9 -> 10127993
A10: 3.1 | B10: Пенсионный фонд (ФОТ 22%) | D10: =D7*22% -> 114400 | E10: =E7*22% -> 114400 | F10: =F7*22% -> 114400 | G10: =G7*22% -> 114400 | H10: =H7*22% -> 114400 | I10: =I7*22% -> 114400 | J10: =J7*22% -> 114400 | K10: =K7*22% -> 114400 | ... O10: =O7*22% -> 114400 | P10: =SUM(D10:O10) -> 1372800 | Q10: =Q7*22% -> 232760 | R10: =R7*22% -> 232760 | S10: =S7*22% -> 232760 | T10: =T7*22% -> 232760 | U10: =U7*22% -> 232760 | V10: =V7*22% -> 232760 | W10: =W7*22% -> 232760 | X10: =X7*22% -> 232760 | ... AB10: =AB7*22% -> 232760 | AC10: =SUM(Q10:AB10) -> 2793120 | AD10: =AD7*22% -> 267674 | AE10: =AE7*22% -> 267674 | AF10: =AF7*22% -> 267674 | AG10: =AG7*22% -> 267674 | AH10: =AH7*22% -> 267674 | AI10: =AI7*22% -> 267674 | AJ10: =AJ7*22% -> 267674 | AK10: =AK7*22% -> 267674 | ... AO10: =AO7*22% -> 267674 | AP10: =SUM(AD10:AO10) -> 3212088 | AQ10: =P10+AC10+AP10 -> 7378008
A11: 3.2 | B11: ФФОМС, ТФОМС (ФОТ 5,1%) | D11: =D7*5.1% -> 26520 | E11: =E7*5.1% -> 26520 | F11: =F7*5.1% -> 26520 | G11: =G7*5.1% -> 26520 | H11: =H7*5.1% -> 26520 | I11: =I7*5.1% -> 26520 | J11: =J7*5.1% -> 26520 | K11: =K7*5.1% -> 26520 | ... O11: =O7*5.1% -> 26520 | P11: =SUM(D11:O11) -> 318240 | Q11: =Q7*5.1% -> 53958 | R11: =R7*5.1% -> 53958 | S11: =S7*5.1% -> 53958 | T11: =T7*5.1% -> 53958 | U11: =U7*5.1% -> 53958 | V11: =V7*5.1% -> 53958 | W11: =W7*5.1% -> 53958 | X11: =X7*5.1% -> 53958 | ... AB11: =AB7*5.1% -> 53958 | AC11: =SUM(Q11:AB11) -> 647496 | AD11: =AD7*5.1% -> 62051.7 | AE11: =AE7*5.1% -> 62051.7 | AF11: =AF7*5.1% -> 62051.7 | AG11: =AG7*5.1% -> 62051.7 | AH11: =AH7*5.1% -> 62051.7 | AI11: =AI7*5.1% -> 62051.7 | AJ11: =AJ7*5.1% -> 62051.7 | AK11: =AK7*5.1% -> 62051.7 | ... AO11: =AO7*5.1% -> 62051.7 | AP11: =SUM(AD11:AO11) -> 744620.4 | AQ11: =P11+AC11+AP11 -> 1710356.4
A12: 3.3 | B12: ФСС (ФОТ 0,2%+2,9%) | D12: =D7*3.1% -> 16120 | E12: =E7*3.1% -> 16120 | F12: =F7*3.1% -> 16120 | G12: =G7*3.1% -> 16120 | H12: =H7*3.1% -> 16120 | I12: =I7*3.1% -> 16120 | J12: =J7*3.1% -> 16120 | K12: =K7*3.1% -> 16120 | ... O12: =O7*3.1% -> 16120 | P12: =SUM(D12:O12) -> 193440 | Q12: =Q7*3.1% -> 32798 | R12: =R7*3.1% -> 32798 | S12: =S7*3.1% -> 32798 | T12: =T7*3.1% -> 32798 | U12: =U7*3.1% -> 32798 | V12: =V7*3.1% -> 32798 | W12: =W7*3.1% -> 32798 | X12: =X7*3.1% -> 32798 | ... AB12: =AB7*3.1% -> 32798 | AC12: =SUM(Q12:AB12) -> 393576 | AD12: =AD7*3.1% -> 37717.7 | AE12: =AE7*3.1% -> 37717.7 | AF12: =AF7*3.1% -> 37717.7 | AG12: =AG7*3.1% -> 37717.7 | AH12: =AH7*3.1% -> 37717.7 | AI12: =AI7*3.1% -> 37717.7 | AJ12: =AJ7*3.1% -> 37717.7 | AK12: =AK7*3.1% -> 37717.7 | ... AO12: =AO7*3.1% -> 37717.7 | AP12: =SUM(AD12:AO12) -> 452612.4 | AQ12: =P12+AC12+AP12 -> 1039628.4
A13: 4 | B13: Cдельная оплата труда | D13: ='Сдельная оплата труда'!C266 -> 300 | E13: ='Сдельная оплата труда'!D266 -> 200 | F13: ='Сдельная оплата труда'!E266 -> 500 | G13: ='Сдельная оплата труда'!F266 -> 600 | H13: ='Сдельная оплата труда'!G266 -> 800 | I13: ='Сдельная оплата труда'!H266 -> 1100 | J13: ='Сдельная оплата труда'!I266 -> 1300 | K13: ='Сдельная оплата труда'!J266 -> 1400 | ... O13: ='Сдельная оплата труда'!N266 -> 2400 | P13: =SUM(D13:O13) -> 14600 | Q13: ='Сдельная оплата труда'!P266 -> 4050 | R13: ='Сдельная оплата труда'!Q266 -> 4650 | S13: ='Сдельная оплата труда'!R266 -> 5250 | T13: ='Сдельная оплата труда'!S266 -> 6050 | U13: ='Сдельная оплата труда'!T266 -> 6575 | V13: ='Сдельная оплата труда'!U266 -> 7250 | W13: ='Сдельная оплата труда'!V266 -> 7775 | X13: ='Сдельная оплата труда'!W266 -> 8600 | ... AB13: ='Сдельная оплата труда'!AA266 -> 11150 | AC13: =SUM(Q13:AB13) -> 90600 | AD13: ='Сдельная оплата труда'!AC266 -> 1200 | AE13: ='Сдельная оплата труда'!AD266 -> 1200 | AF13: ='Сдельная оплата труда'!AE266 -> 1200 | AG13: ='Сдельная оплата труда'!AF266 -> 1200 | AH13: ='Сдельная оплата труда'!AG266 -> 1200 | AI13: ='Сдельная оплата труда'!AH266 -> 1200 | AJ13: ='Сдельная оплата труда'!AI266 -> 1400 | AK13: ='Сдельная оплата труда'!AJ266 -> 1400 | ... AO13: ='Сдельная оплата труда'!AN266 -> 1400 | AP13: =SUM(AD13:AO13) -> 15600 | AQ13: =P13+AC13+AP13 -> 120800
A14: 4.1 | B14: НДФЛ (Сдельная оплата труда 13%) | D14: =D13*13% -> 39 | E14: =E13*13% -> 26 | F14: =F13*13% -> 65 | G14: =G13*13% -> 78 | H14: =H13*13% -> 104 | I14: =I13*13% -> 143 | J14: =J13*13% -> 169 | K14: =K13*13% -> 182 | ... O14: =O13*13% -> 312 | P14: =SUM(D14:O14) -> 1898 | Q14: =Q13*13% -> 526.5 | R14: =R13*13% -> 604.5 | S14: =S13*13% -> 682.5 | T14: =T13*13% -> 786.5 | U14: =U13*13% -> 854.75 | V14: =V13*13% -> 942.5 | W14: =W13*13% -> 1010.75 | X14: =X13*13% -> 1118 | ... AB14: =AB13*13% -> 1449.5 | AC14: =SUM(Q14:AB14) -> 11778 | AD14: =AD13*13% -> 156 | AE14: =AE13*13% -> 156 | AF14: =AF13*13% -> 156 | AG14: =AG13*13% -> 156 | AH14: =AH13*13% -> 156 | AI14: =AI13*13% -> 156 | AJ14: =AJ13*13% -> 182 | AK14: =AK13*13% -> 182 | ... AO14: =AO13*13% -> 182 | AP14: =SUM(AD14:AO14) -> 2028 | AQ14: =P14+AC14+AP14 -> 15704
A15: 5 | B15: Взносы (сдельная оплата труда) | D15: =SUM(D16:D18) -> 90.6 | E15: =SUM(E16:E18) -> 60.4 | F15: =SUM(F16:F18) -> 151 | G15: =SUM(G16:G18) -> 181.2 | H15: =SUM(H16:H18) -> 241.6 | I15: =SUM(I16:I18) -> 332.2 | J15: =SUM(J16:J18) -> 392.6 | K15: =SUM(K16:K18) -> 422.8 | ... O15: =SUM(O16:O18) -> 724.8 | P15: =SUM(D15:O15) -> 4409.2 | Q15: =SUM(Q16:Q18) -> 1223.1 | R15: =SUM(R16:R18) -> 1404.3 | S15: =SUM(S16:S18) -> 1585.5 | T15: =SUM(T16:T18) -> 1827.1 | U15: =SUM(U16:U18) -> 1985.65 | V15: =SUM(V16:V18) -> 2189.5 | W15: =SUM(W16:W18) -> 2348.05 | X15: =SUM(X16:X18) -> 2597.2 | ... AB15: =SUM(AB16:AB18) -> 3367.3 | AC15: =SUM(Q15:AB15) -> 27361.2 | AD15: =SUM(AD16:AD18) -> 362.4 | AE15: =SUM(AE16:AE18) -> 362.4 | AF15: =SUM(AF16:AF18) -> 362.4 | AG15: =SUM(AG16:AG18) -> 362.4 | AH15: =SUM(AH16:AH18) -> 362.4 | AI15: =SUM(AI16:AI18) -> 362.4 | AJ15: =SUM(AJ16:AJ18) -> 422.8 | AK15: =SUM(AK16:AK18) -> 422.8 | ... AO15: =SUM(AO16:AO18) -> 422.8 | AP15: =SUM(AD15:AO15) -> 4711.2 | AQ15: =P15+AC15+AP15 -> 36481.6
A16: 5.1 | B16: Пенсионный фонд (22%) | D16: =D13*22% -> 66 | E16: =E13*22% -> 44 | F16: =F13*22% -> 110 | G16: =G13*22% -> 132 | H16: =H13*22% -> 176 | I16: =I13*22% -> 242 | J16: =J13*22% -> 286 | K16: =K13*22% -> 308 | ... O16: =O13*22% -> 528 | P16: =SUM(D16:O16) -> 3212 | Q16: =Q13*22% -> 891 | R16: =R13*22% -> 1023 | S16: =S13*22% -> 1155 | T16: =T13*22% -> 1331 | U16: =U13*22% -> 1446.5 | V16: =V13*22% -> 1595 | W16: =W13*22% -> 1710.5 | X16: =X13*22% -> 1892 | ... AB16: =AB13*22% -> 2453 | AC16: =SUM(Q16:AB16) -> 19932 | AD16: =AD13*22% -> 264 | AE16: =AE13*22% -> 264 | AF16: =AF13*22% -> 264 | AG16: =AG13*22% -> 264 | AH16: =AH13*22% -> 264 | AI16: =AI13*22% -> 264 | AJ16: =AJ13*22% -> 308 | AK16: =AK13*22% -> 308 | ... AO16: =AO13*22% -> 308 | AP16: =SUM(AD16:AO16) -> 3432 | AQ16: =P16+AC16+AP16 -> 26576
A17: 5.2 | B17: ФФОМС, ТФОМС (5,1%) | D17: =D13*5.1% -> 15.3 | E17: =E13*5.1% -> 10.2 | F17: =F13*5.1% -> 25.5 | G17: =G13*5.1% -> 30.6 | H17: =H13*5.1% -> 40.8 | I17: =I13*5.1% -> 56.1 | J17: =J13*5.1% -> 66.3 | K17: =K13*5.1% -> 71.4 | ... O17: =O13*5.1% -> 122.4 | P17: =SUM(D17:O17) -> 744.6 | Q17: =Q13*5.1% -> 206.55 | R17: =R13*5.1% -> 237.15 | S17: =S13*5.1% -> 267.75 | T17: =T13*5.1% -> 308.55 | U17: =U13*5.1% -> 335.325 | V17: =V13*5.1% -> 369.75 | W17: =W13*5.1% -> 396.525 | X17: =X13*5.1% -> 438.6 | ... AB17: =AB13*5.1% -> 568.65 | AC17: =SUM(Q17:AB17) -> 4620.6 | AD17: =AD13*5.1% -> 61.2 | AE17: =AE13*5.1% -> 61.2 | AF17: =AF13*5.1% -> 61.2 | AG17: =AG13*5.1% -> 61.2 | AH17: =AH13*5.1% -> 61.2 | AI17: =AI13*5.1% -> 61.2 | AJ17: =AJ13*5.1% -> 71.4 | AK17: =AK13*5.1% -> 71.4 | ... AO17: =AO13*5.1% -> 71.4 | AP17: =SUM(AD17:AO17) -> 795.6 | AQ17: =P17+AC17+AP17 -> 6160.8
A18: 5.3 | B18: ФСС (0,2%+2,9%) | D18: =D13*3.1% -> 9.3 | E18: =E13*3.1% -> 6.2 | F18: =F13*3.1% -> 15.5 | G18: =G13*3.1% -> 18.6 | H18: =H13*3.1% -> 24.8 | I18: =I13*3.1% -> 34.1 | J18: =J13*3.1% -> 40.3 | K18: =K13*3.1% -> 43.4 | ... O18: =O13*3.1% -> 74.4 | P18: =SUM(D18:O18) -> 452.6 | Q18: =Q13*3.1% -> 125.55 | R18: =R13*3.1% -> 144.15 | S18: =S13*3.1% -> 162.75 | T18: =T13*3.1% -> 187.55 | U18: =U13*3.1% -> 203.825 | V18: =V13*3.1% -> 224.75 | W18: =W13*3.1% -> 241.025 | X18: =X13*3.1% -> 266.6 | ... AB18: =AB13*3.1% -> 345.65 | AC18: =SUM(Q18:AB18) -> 2808.6 | AD18: =AD13*3.1% -> 37.2 | AE18: =AE13*3.1% -> 37.2 | AF18: =AF13*3.1% -> 37.2 | AG18: =AG13*3.1% -> 37.2 | AH18: =AH13*3.1% -> 37.2 | AI18: =AI13*3.1% -> 37.2 | AJ18: =AJ13*3.1% -> 43.4 | AK18: =AK13*3.1% -> 43.4 | ... AO18: =AO13*3.1% -> 43.4 | AP18: =SUM(AD18:AO18) -> 483.6 | AQ18: =P18+AC18+AP18 -> 3744.8
A19: 6 | B19: Налог | D19: =SUM(D20:D21) -> 30709.833 | E19: =SUM(E20:E21) -> 16009.833 | F19: =SUM(F20:F21) -> 53809.833 | G19: =SUM(G20:G21) -> 27109.833 | H19: =SUM(H20:H21) -> 45109.833 | I19: =SUM(I20:I21) -> 54109.833 | J19: =SUM(J20:J21) -> 57109.833 | K19: =SUM(K20:K21) -> 58729.833 | ... O19: =SUM(O20:O21) -> 82729.833 | P19: =SUM(D19:O19) -> 642718 | Q19: =SUM(Q20:Q21) -> 150307.46 | R19: =SUM(R20:R21) -> 177562.46 | S19: =SUM(S20:S21) -> 171697.46 | T19: =SUM(T20:T21) -> 218870.46 | U19: =SUM(U20:U21) -> 195789.96 | V19: =SUM(V20:V21) -> 224252.46 | W19: =SUM(W20:W21) -> 220422.96 | X19: =SUM(X20:X21) -> 267377.46 | ... AB19: =SUM(AB20:AB21) -> 314504.46 | AC19: =SUM(Q19:AB19) -> 2724494.5 | AD19: =SUM(AD20:AD21) -> 377656.71 | AE19: =SUM(AE20:AE21) -> 396065.91 | AF19: =SUM(AF20:AF21) -> 371467.41 | AG19: =SUM(AG20:AG21) -> 429234.21 | AH19: =SUM(AH20:AH21) -> 407254.26 | AI19: =SUM(AI20:AI21) -> 463275.36 | AJ19: =SUM(AJ20:AJ21) -> 446373.81 | AK19: =SUM(AK20:AK21) -> 502553.61 | ... AO19: =SUM(AO20:AO21) -> 570953.31 | AP19: =SUM(AD19:AO19) -> 5492491.7 | AQ19: =P19+AC19+AP19 -> 8859704.1
A20: 6.1 | B20: Налог УСН 6% (например) | D20: =D6*6% -> 19440 | E20: =E6*6% -> 4740 | F20: =F6*6% -> 42540 | G20: =G6*6% -> 15840 | H20: =H6*6% -> 33840 | I20: =I6*6% -> 42840 | J20: =J6*6% -> 45840 | K20: =K6*6% -> 47460 | ... O20: =O6*6% -> 71460 | P20: =SUM(D20:O20) -> 507480 | Q20: =Q6*6% -> 113988 | R20: =R6*6% -> 141243 | S20: =S6*6% -> 135378 | T20: =T6*6% -> 182551 | U20: =U6*6% -> 159470.5 | V20: =V6*6% -> 187933 | W20: =W6*6% -> 184103.5 | X20: =X6*6% -> 231058 | ... AB20: =AB6*6% -> 278185 | AC20: =SUM(Q20:AB20) -> 2288661 | AD20: =AD6*6% -> 308116.05 | AE20: =AE6*6% -> 326525.25 | AF20: =AF6*6% -> 301926.75 | AG20: =AG6*6% -> 359693.55 | AH20: =AH6*6% -> 337713.6 | AI20: =AI6*6% -> 393734.7 | AJ20: =AJ6*6% -> 376833.15 | AK20: =AK6*6% -> 433012.95 | ... AO20: =AO6*6% -> 501412.65 | AP20: =SUM(AD20:AO20) -> 4658003.7 | AQ20: =P20+AC20+AP20 -> 7454144.7
A21: 6.2 | B21: Взнос ИП фиксированный | D21: ='Вводные данные'!$C$6/12+(($P$6-300000)*1%/12) -> 11269.833 | E21: ='Вводные данные'!$C$6/12+(($P$6-300000)*1%/12) -> 11269.833 | F21: ='Вводные данные'!$C$6/12+(($P$6-300000)*1%/12) -> 11269.833 | G21: ='Вводные данные'!$C$6/12+(($P$6-300000)*1%/12) -> 11269.833 | H21: ='Вводные данные'!$C$6/12+(($P$6-300000)*1%/12) -> 11269.833 | I21: ='Вводные данные'!$C$6/12+(($P$6-300000)*1%/12) -> 11269.833 | J21: ='Вводные данные'!$C$6/12+(($P$6-300000)*1%/12) -> 11269.833 | K21: ='Вводные данные'!$C$6/12+(($P$6-300000)*1%/12) -> 11269.833 | ... O21: ='Вводные данные'!$C$6/12+(($P$6-300000)*1%/12) -> 11269.833 | P21: =SUM(D21:O21) -> 135238 | Q21: =('Вводные данные'!$D$6/12+(($AC$6-300000)*1%/12)) -> 36319.458 | R21: =('Вводные данные'!$D$6/12+(($AC$6-300000)*1%/12)) -> 36319.458 | S21: =('Вводные данные'!$D$6/12+(($AC$6-300000)*1%/12)) -> 36319.458 | T21: =('Вводные данные'!$D$6/12+(($AC$6-300000)*1%/12)) -> 36319.458 | U21: =('Вводные данные'!$D$6/12+(($AC$6-300000)*1%/12)) -> 36319.458 | V21: =('Вводные данные'!$D$6/12+(($AC$6-300000)*1%/12)) -> 36319.458 | W21: =('Вводные данные'!$D$6/12+(($AC$6-300000)*1%/12)) -> 36319.458 | X21: =('Вводные данные'!$D$6/12+(($AC$6-300000)*1%/12)) -> 36319.458 | ... AB21: =('Вводные данные'!$D$6/12+(($AC$6-300000)*1%/12)) -> 36319.458 | AC21: =SUM(Q21:AB21) -> 435833.5 | AD21: =('Вводные данные'!$E$6/12+(($AP$6-300000)*1%/12)) -> 69540.663 | AE21: =('Вводные данные'!$E$6/12+(($AP$6-300000)*1%/12)) -> 69540.663 | AF21: =('Вводные данные'!$E$6/12+(($AP$6-300000)*1%/12)) -> 69540.663 | AG21: =('Вводные данные'!$E$6/12+(($AP$6-300000)*1%/12)) -> 69540.663 | AH21: =('Вводные данные'!$E$6/12+(($AP$6-300000)*1%/12)) -> 69540.663 | AI21: =('Вводные данные'!$E$6/12+(($AP$6-300000)*1%/12)) -> 69540.663 | AJ21: =('Вводные данные'!$E$6/12+(($AP$6-300000)*1%/12)) -> 69540.663 | AK21: =('Вводные данные'!$E$6/12+(($AP$6-300000)*1%/12)) -> 69540.663 | ... AO21: =('Вводные данные'!$E$6/12+(($AP$6-300000)*1%/12)) -> 69540.663 | AP21: =SUM(AD21:AO21) -> 834487.95 | AQ21: =P21+AC21+AP21 -> 1405559.4
A22: 7 | B22: Маркетинговые расходы | D22: =Маркетинг!B12 -> 61500 | E22: =Маркетинг!C12 -> 61500 | F22: =Маркетинг!D12 -> 61500 | G22: =Маркетинг!E12 -> 61500 | H22: =Маркетинг!F12 -> 61500 | I22: =Маркетинг!G12 -> 61500 | J22: =Маркетинг!H12 -> 61500 | K22: =Маркетинг!I12 -> 61500 | ... O22: =Маркетинг!M12 -> 61500 | P22: =SUM(D22:O22) -> 738000 | Q22: =Маркетинг!O12 -> 70725 | R22: =Маркетинг!P12 -> 70725 | S22: =Маркетинг!Q12 -> 70725 | T22: =Маркетинг!R12 -> 70725 | U22: =Маркетинг!S12 -> 70725 | V22: =Маркетинг!T12 -> 70725 | W22: =Маркетинг!U12 -> 70725 | X22: =Маркетинг!V12 -> 70725 | ... AB22: =Маркетинг!Z12 -> 70725 | AC22: =SUM(Q22:AB22) -> 848700 | AD22: =Маркетинг!AB12 -> 81333.75 | AE22: =Маркетинг!AC12 -> 81333.75 | AF22: =Маркетинг!AD12 -> 81333.75 | AG22: =Маркетинг!AE12 -> 81333.75 | AH22: =Маркетинг!AF12 -> 81333.75 | AI22: =Маркетинг!AG12 -> 81333.75 | AJ22: =Маркетинг!AH12 -> 81333.75 | AK22: =Маркетинг!AI12 -> 81333.75 | ... AO22: =Маркетинг!AM12 -> 81333.75 | AP22: =SUM(AD22:AO22) -> 976005 | AQ22: =P22+AC22+AP22 -> 2562705
A23: 8 | B23: Административно-хозяйственные и производственные расходы | D23: =SUM(D24:D39) -> 142800 | E23: =SUM(E24:E39) -> 97400 | F23: =SUM(F24:F39) -> 202100 | G23: =SUM(G24:G39) -> 117000 | H23: =SUM(H24:H39) -> 167600 | I23: =SUM(I24:I39) -> 183900 | J23: =SUM(J24:J39) -> 189500 | K23: =SUM(K24:K39) -> 205400 | ... O23: =SUM(O24:O39) -> 249200 | P23: =SUM(D23:O23) -> 2246000 | Q23: =SUM(Q24:Q39) -> 367655 | R23: =SUM(R24:R39) -> 438610 | S23: =SUM(S24:S39) -> 407905 | T23: =SUM(T24:T39) -> 550275 | U23: =SUM(U24:U39) -> 468510 | V23: =SUM(V24:V39) -> 541535 | W23: =SUM(W24:W39) -> 514395 | X23: =SUM(X24:X39) -> 656075 | ... AB23: =SUM(AB24:AB39) -> 760380 | AC23: =SUM(Q23:AB23) -> 6546835 | AD23: =SUM(AD24:AD39) -> 910673.5 | AE23: =SUM(AE24:AE39) -> 963705.75 | AF23: =SUM(AF24:AF39) -> 874040.25 | AG23: =SUM(AG24:AG39) -> 1039969.9 | AH23: =SUM(AH24:AH39) -> 964256.79 | AI23: =SUM(AI24:AI39) -> 1125403.4 | AJ23: =SUM(AJ24:AJ39) -> 1057757.5 | AK23: =SUM(AK24:AK39) -> 1217449.4 | ... AO23: =SUM(AO24:AO39) -> 1385406.9 | AP23: =SUM(AD23:AO23) -> 13199476 | AQ23: =P23+AC23+AP23 -> 21992311
A24: 8.1 | B24: Производственные расходы | D24: ='Переменные затраты'!H126 -> 53800 | E24: ='Переменные затраты'!I126 -> 8400 | F24: ='Переменные затраты'!J126 -> 113100 | G24: ='Переменные затраты'!K126 -> 28000 | H24: ='Переменные затраты'!L126 -> 78600 | I24: ='Переменные затраты'!M126 -> 94900 | J24: ='Переменные затраты'!N126 -> 100500 | K24: ='Переменные затраты'!O126 -> 116400 | ... O24: ='Переменные затраты'!S126 -> 160200 | P24: =SUM(D24:O24) -> 1178000 | Q24: ='Переменные затраты'!U126 -> 265305 | R24: ='Переменные затраты'!V126 -> 336260 | S24: ='Переменные затраты'!W126 -> 305555 | T24: ='Переменные затраты'!X126 -> 447925 | U24: ='Переменные затраты'!Y126 -> 366160 | V24: ='Переменные затраты'!Z126 -> 439185 | W24: ='Переменные затраты'!AA126 -> 412045 | X24: ='Переменные затраты'!AB126 -> 553725 | ... AB24: ='Переменные затраты'!AF126 -> 658030 | AC24: =SUM(Q24:AB24) -> 5318635 | AD24: ='Переменные затраты'!AH126 -> 792971 | AE24: ='Переменные затраты'!AI126 -> 846003.25 | AF24: ='Переменные затраты'!AJ126 -> 756337.75 | AG24: ='Переменные затраты'!AK126 -> 922267.42 | AH24: ='Переменные затраты'!AL126 -> 846554.29 | AI24: ='Переменные затраты'!AM126 -> 1007700.9 | AJ24: ='Переменные затраты'!AN126 -> 940055.04 | AK24: ='Переменные затраты'!AO126 -> 1099746.9 | ... AO24: ='Переменные затраты'!AS126 -> 1267704.4 | AP24: =SUM(AD24:AO24) -> 11787046 | AQ24: =P24+AC24+AP24 -> 18283681
A25: 8.2 | B25: ='Постоянные затраты'!A5 -> Бухгалтерия | D25: ='Постоянные затраты'!B5 -> 10000 | E25: ='Постоянные затраты'!C5 -> 10000 | F25: ='Постоянные затраты'!D5 -> 10000 | G25: ='Постоянные затраты'!E5 -> 10000 | H25: ='Постоянные затраты'!F5 -> 10000 | I25: ='Постоянные затраты'!G5 -> 10000 | J25: ='Постоянные затраты'!H5 -> 10000 | K25: ='Постоянные затраты'!I5 -> 10000 | ... O25: ='Постоянные затраты'!M5 -> 10000 | P25: =SUM(D25:O25) -> 120000 | Q25: ='Постоянные затраты'!O5 -> 11500 | R25: ='Постоянные затраты'!P5 -> 11500 | S25: ='Постоянные затраты'!Q5 -> 11500 | T25: ='Постоянные затраты'!R5 -> 11500 | U25: ='Постоянные затраты'!S5 -> 11500 | V25: ='Постоянные затраты'!T5 -> 11500 | W25: ='Постоянные затраты'!U5 -> 11500 | X25: ='Постоянные затраты'!V5 -> 11500 | ... AB25: ='Постоянные затраты'!Z5 -> 11500 | AC25: =SUM(Q25:AB25) -> 138000 | AD25: ='Постоянные затраты'!AB5 -> 13225 | AE25: ='Постоянные затраты'!AC5 -> 13225 | AF25: ='Постоянные затраты'!AD5 -> 13225 | AG25: ='Постоянные затраты'!AE5 -> 13225 | AH25: ='Постоянные затраты'!AF5 -> 13225 | AI25: ='Постоянные затраты'!AG5 -> 13225 | AJ25: ='Постоянные затраты'!AH5 -> 13225 | AK25: ='Постоянные затраты'!AI5 -> 13225 | ... AO25: ='Постоянные затраты'!AM5 -> 13225 | AP25: =SUM(AD25:AO25) -> 158700 | AQ25: =P25+AC25+AP25 -> 416700
A26: 8.3 | B26: ='Постоянные затраты'!A6 -> Юридические | D26: ='Постоянные затраты'!B6 -> 10000 | E26: ='Постоянные затраты'!C6 -> 10000 | F26: ='Постоянные затраты'!D6 -> 10000 | G26: ='Постоянные затраты'!E6 -> 10000 | H26: ='Постоянные затраты'!F6 -> 10000 | I26: ='Постоянные затраты'!G6 -> 10000 | J26: ='Постоянные затраты'!H6 -> 10000 | K26: ='Постоянные затраты'!I6 -> 10000 | ... O26: ='Постоянные затраты'!M6 -> 10000 | P26: =SUM(D26:O26) -> 120000 | Q26: ='Постоянные затраты'!O6 -> 11500 | R26: ='Постоянные затраты'!P6 -> 11500 | S26: ='Постоянные затраты'!Q6 -> 11500 | T26: ='Постоянные затраты'!R6 -> 11500 | U26: ='Постоянные затраты'!S6 -> 11500 | V26: ='Постоянные затраты'!T6 -> 11500 | W26: ='Постоянные затраты'!U6 -> 11500 | X26: ='Постоянные затраты'!V6 -> 11500 | ... AB26: ='Постоянные затраты'!Z6 -> 11500 | AC26: =SUM(Q26:AB26) -> 138000 | AD26: ='Постоянные затраты'!AB6 -> 13225 | AE26: ='Постоянные затраты'!AC6 -> 13225 | AF26: ='Постоянные затраты'!AD6 -> 13225 | AG26: ='Постоянные затраты'!AE6 -> 13225 | AH26: ='Постоянные затраты'!AF6 -> 13225 | AI26: ='Постоянные затраты'!AG6 -> 13225 | AJ26: ='Постоянные затраты'!AH6 -> 13225 | AK26: ='Постоянные затраты'!AI6 -> 13225 | ... AO26: ='Постоянные затраты'!AM6 -> 13225 | AP26: =SUM(AD26:AO26) -> 158700 | AQ26: =P26+AC26+AP26 -> 416700
A27: 8.4 | B27: ='Постоянные затраты'!A7 -> 0 | D27: ='Постоянные затраты'!B7 -> 0 | E27: ='Постоянные затраты'!C7 -> 0 | F27: ='Постоянные затраты'!D7 -> 0 | G27: ='Постоянные затраты'!E7 -> 0 | H27: ='Постоянные затраты'!F7 -> 0 | I27: ='Постоянные затраты'!G7 -> 0 | J27: ='Постоянные затраты'!H7 -> 0 | K27: ='Постоянные затраты'!I7 -> 0 | ... O27: ='Постоянные затраты'!M7 -> 0 | P27: =SUM(D27:O27) -> 0 | Q27: ='Постоянные затраты'!O7 -> 0 | R27: ='Постоянные затраты'!P7 -> 0 | S27: ='Постоянные затраты'!Q7 -> 0 | T27: ='Постоянные затраты'!R7 -> 0 | U27: ='Постоянные затраты'!S7 -> 0 | V27: ='Постоянные затраты'!T7 -> 0 | W27: ='Постоянные затраты'!U7 -> 0 | X27: ='Постоянные затраты'!V7 -> 0 | ... AB27: ='Постоянные затраты'!Z7 -> 0 | AC27: =SUM(Q27:AB27) -> 0 | AD27: ='Постоянные затраты'!AB7 -> 0 | AE27: ='Постоянные затраты'!AC7 -> 0 | AF27: ='Постоянные затраты'!AD7 -> 0 | AG27: ='Постоянные затраты'!AE7 -> 0 | AH27: ='Постоянные затраты'!AF7 -> 0 | AI27: ='Постоянные затраты'!AG7 -> 0 | AJ27: ='Постоянные затраты'!AH7 -> 0 | AK27: ='Постоянные затраты'!AI7 -> 0 | ... AO27: ='Постоянные затраты'!AM7 -> 0 | AP27: =SUM(AD27:AO27) -> 0 | AQ27: =P27+AC27+AP27 -> 0
A28: 8.5 | B28: ='Постоянные затраты'!A8 -> Офис аренда | D28: ='Постоянные затраты'!B8 -> 30000 | E28: ='Постоянные затраты'!C8 -> 30000 | F28: ='Постоянные затраты'!D8 -> 30000 | G28: ='Постоянные затраты'!E8 -> 30000 | H28: ='Постоянные затраты'!F8 -> 30000 | I28: ='Постоянные затраты'!G8 -> 30000 | J28: ='Постоянные затраты'!H8 -> 30000 | K28: ='Постоянные затраты'!I8 -> 30000 | ... O28: ='Постоянные затраты'!M8 -> 30000 | P28: =SUM(D28:O28) -> 360000 | Q28: ='Постоянные затраты'!O8 -> 34500 | R28: ='Постоянные затраты'!P8 -> 34500 | S28: ='Постоянные затраты'!Q8 -> 34500 | T28: ='Постоянные затраты'!R8 -> 34500 | U28: ='Постоянные затраты'!S8 -> 34500 | V28: ='Постоянные затраты'!T8 -> 34500 | W28: ='Постоянные затраты'!U8 -> 34500 | X28: ='Постоянные затраты'!V8 -> 34500 | ... AB28: ='Постоянные затраты'!Z8 -> 34500 | AC28: =SUM(Q28:AB28) -> 414000 | AD28: ='Постоянные затраты'!AB8 -> 39675 | AE28: ='Постоянные затраты'!AC8 -> 39675 | AF28: ='Постоянные затраты'!AD8 -> 39675 | AG28: ='Постоянные затраты'!AE8 -> 39675 | AH28: ='Постоянные затраты'!AF8 -> 39675 | AI28: ='Постоянные затраты'!AG8 -> 39675 | AJ28: ='Постоянные затраты'!AH8 -> 39675 | AK28: ='Постоянные затраты'!AI8 -> 39675 | ... AO28: ='Постоянные затраты'!AM8 -> 39675 | AP28: =SUM(AD28:AO28) -> 476100 | AQ28: =P28+AC28+AP28 -> 1250100
A29: 8.6 | B29: ='Постоянные затраты'!A9 -> Прочее (связь, интернет, канцелярия) | D29: ='Постоянные затраты'!B9 -> 4000 | E29: ='Постоянные затраты'!C9 -> 4000 | F29: ='Постоянные затраты'!D9 -> 4000 | G29: ='Постоянные затраты'!E9 -> 4000 | H29: ='Постоянные затраты'!F9 -> 4000 | I29: ='Постоянные затраты'!G9 -> 4000 | J29: ='Постоянные затраты'!H9 -> 4000 | K29: ='Постоянные затраты'!I9 -> 4000 | ... O29: ='Постоянные затраты'!M9 -> 4000 | P29: =SUM(D29:O29) -> 48000 | Q29: ='Постоянные затраты'!O9 -> 4600 | R29: ='Постоянные затраты'!P9 -> 4600 | S29: ='Постоянные затраты'!Q9 -> 4600 | T29: ='Постоянные затраты'!R9 -> 4600 | U29: ='Постоянные затраты'!S9 -> 4600 | V29: ='Постоянные затраты'!T9 -> 4600 | W29: ='Постоянные затраты'!U9 -> 4600 | X29: ='Постоянные затраты'!V9 -> 4600 | ... AB29: ='Постоянные затраты'!Z9 -> 4600 | AC29: =SUM(Q29:AB29) -> 55200 | AD29: ='Постоянные затраты'!AB9 -> 5290 | AE29: ='Постоянные затраты'!AC9 -> 5290 | AF29: ='Постоянные затраты'!AD9 -> 5290 | AG29: ='Постоянные затраты'!AE9 -> 5290 | AH29: ='Постоянные затраты'!AF9 -> 5290 | AI29: ='Постоянные затраты'!AG9 -> 5290 | AJ29: ='Постоянные затраты'!AH9 -> 5290 | AK29: ='Постоянные затраты'!AI9 -> 5290 | ... AO29: ='Постоянные затраты'!AM9 -> 5290 | AP29: =SUM(AD29:AO29) -> 63480 | AQ29: =P29+AC29+AP29 -> 166680
A30: 8.7 | B30: ='Постоянные затраты'!A10 -> Хостинг и облака | D30: ='Постоянные затраты'!B10 -> 15000 | E30: ='Постоянные затраты'!C10 -> 15000 | F30: ='Постоянные затраты'!D10 -> 15000 | G30: ='Постоянные затраты'!E10 -> 15000 | H30: ='Постоянные затраты'!F10 -> 15000 | I30: ='Постоянные затраты'!G10 -> 15000 | J30: ='Постоянные затраты'!H10 -> 15000 | K30: ='Постоянные затраты'!I10 -> 15000 | ... O30: ='Постоянные затраты'!M10 -> 15000 | P30: =SUM(D30:O30) -> 180000 | Q30: ='Постоянные затраты'!O10 -> 17250 | R30: ='Постоянные затраты'!P10 -> 17250 | S30: ='Постоянные затраты'!Q10 -> 17250 | T30: ='Постоянные затраты'!R10 -> 17250 | U30: ='Постоянные затраты'!S10 -> 17250 | V30: ='Постоянные затраты'!T10 -> 17250 | W30: ='Постоянные затраты'!U10 -> 17250 | X30: ='Постоянные затраты'!V10 -> 17250 | ... AB30: ='Постоянные затраты'!Z10 -> 17250 | AC30: =SUM(Q30:AB30) -> 207000 | AD30: ='Постоянные затраты'!AB10 -> 19837.5 | AE30: ='Постоянные затраты'!AC10 -> 19837.5 | AF30: ='Постоянные затраты'!AD10 -> 19837.5 | AG30: ='Постоянные затраты'!AE10 -> 19837.5 | AH30: ='Постоянные затраты'!AF10 -> 19837.5 | AI30: ='Постоянные затраты'!AG10 -> 19837.5 | AJ30: ='Постоянные затраты'!AH10 -> 19837.5 | AK30: ='Постоянные затраты'!AI10 -> 19837.5 | ... AO30: ='Постоянные затраты'!AM10 -> 19837.5 | AP30: =SUM(AD30:AO30) -> 238050 | AQ30: =P30+AC30+AP30 -> 625050
A31: 8.8 | B31: ='Постоянные затраты'!A11 -> Домены, SSL, почта | D31: ='Постоянные затраты'!B11 -> 5000 | E31: ='Постоянные затраты'!C11 -> 5000 | F31: ='Постоянные затраты'!D11 -> 5000 | G31: ='Постоянные затраты'!E11 -> 5000 | H31: ='Постоянные затраты'!F11 -> 5000 | I31: ='Постоянные затраты'!G11 -> 5000 | J31: ='Постоянные затраты'!H11 -> 5000 | K31: ='Постоянные затраты'!I11 -> 5000 | ... O31: ='Постоянные затраты'!M11 -> 5000 | P31: =SUM(D31:O31) -> 60000 | Q31: ='Постоянные затраты'!O11 -> 5750 | R31: ='Постоянные затраты'!P11 -> 5750 | S31: ='Постоянные затраты'!Q11 -> 5750 | T31: ='Постоянные затраты'!R11 -> 5750 | U31: ='Постоянные затраты'!S11 -> 5750 | V31: ='Постоянные затраты'!T11 -> 5750 | W31: ='Постоянные затраты'!U11 -> 5750 | X31: ='Постоянные затраты'!V11 -> 5750 | ... AB31: ='Постоянные затраты'!Z11 -> 5750 | AC31: =SUM(Q31:AB31) -> 69000 | AD31: ='Постоянные затраты'!AB11 -> 6612.5 | AE31: ='Постоянные затраты'!AC11 -> 6612.5 | AF31: ='Постоянные затраты'!AD11 -> 6612.5 | AG31: ='Постоянные затраты'!AE11 -> 6612.5 | AH31: ='Постоянные затраты'!AF11 -> 6612.5 | AI31: ='Постоянные затраты'!AG11 -> 6612.5 | AJ31: ='Постоянные затраты'!AH11 -> 6612.5 | AK31: ='Постоянные затраты'!AI11 -> 6612.5 | ... AO31: ='Постоянные затраты'!AM11 -> 6612.5 | AP31: =SUM(AD31:AO31) -> 79350 | AQ31: =P31+AC31+AP31 -> 208350
A32: 8.9 | B32: ='Постоянные затраты'!A12 -> SaaS-сервисы | D32: ='Постоянные затраты'!B12 -> 10000 | E32: ='Постоянные затраты'!C12 -> 10000 | F32: ='Постоянные затраты'!D12 -> 10000 | G32: ='Постоянные затраты'!E12 -> 10000 | H32: ='Постоянные затраты'!F12 -> 10000 | I32: ='Постоянные затраты'!G12 -> 10000 | J32: ='Постоянные затраты'!H12 -> 10000 | K32: ='Постоянные затраты'!I12 -> 10000 | ... O32: ='Постоянные затраты'!M12 -> 10000 | P32: =SUM(D32:O32) -> 120000 | Q32: ='Постоянные затраты'!O12 -> 11500 | R32: ='Постоянные затраты'!P12 -> 11500 | S32: ='Постоянные затраты'!Q12 -> 11500 | T32: ='Постоянные затраты'!R12 -> 11500 | U32: ='Постоянные затраты'!S12 -> 11500 | V32: ='Постоянные затраты'!T12 -> 11500 | W32: ='Постоянные затраты'!U12 -> 11500 | X32: ='Постоянные затраты'!V12 -> 11500 | ... AB32: ='Постоянные затраты'!Z12 -> 11500 | AC32: =SUM(Q32:AB32) -> 138000 | AD32: ='Постоянные затраты'!AB12 -> 13225 | AE32: ='Постоянные затраты'!AC12 -> 13225 | AF32: ='Постоянные затраты'!AD12 -> 13225 | AG32: ='Постоянные затраты'!AE12 -> 13225 | AH32: ='Постоянные затраты'!AF12 -> 13225 | AI32: ='Постоянные затраты'!AG12 -> 13225 | AJ32: ='Постоянные затраты'!AH12 -> 13225 | AK32: ='Постоянные затраты'!AI12 -> 13225 | ... AO32: ='Постоянные затраты'!AM12 -> 13225 | AP32: =SUM(AD32:AO32) -> 158700 | AQ32: =P32+AC32+AP32 -> 416700
A33: 8.10 | B33: ='Постоянные затраты'!A13 -> Мониторинг и аналитика | D33: ='Постоянные затраты'!B13 -> 5000 | E33: ='Постоянные затраты'!C13 -> 5000 | F33: ='Постоянные затраты'!D13 -> 5000 | G33: ='Постоянные затраты'!E13 -> 5000 | H33: ='Постоянные затраты'!F13 -> 5000 | I33: ='Постоянные затраты'!G13 -> 5000 | J33: ='Постоянные затраты'!H13 -> 5000 | K33: ='Постоянные затраты'!I13 -> 5000 | ... O33: ='Постоянные затраты'!M13 -> 5000 | P33: =SUM(D33:O33) -> 60000 | Q33: ='Постоянные затраты'!O13 -> 5750 | R33: ='Постоянные затраты'!P13 -> 5750 | S33: ='Постоянные затраты'!Q13 -> 5750 | T33: ='Постоянные затраты'!R13 -> 5750 | U33: ='Постоянные затраты'!S13 -> 5750 | V33: ='Постоянные затраты'!T13 -> 5750 | W33: ='Постоянные затраты'!U13 -> 5750 | X33: ='Постоянные затраты'!V13 -> 5750 | ... AB33: ='Постоянные затраты'!Z13 -> 5750 | AC33: =SUM(Q33:AB33) -> 69000 | AD33: ='Постоянные затраты'!AB13 -> 6612.5 | AE33: ='Постоянные затраты'!AC13 -> 6612.5 | AF33: ='Постоянные затраты'!AD13 -> 6612.5 | AG33: ='Постоянные затраты'!AE13 -> 6612.5 | AH33: ='Постоянные затраты'!AF13 -> 6612.5 | AI33: ='Постоянные затраты'!AG13 -> 6612.5 | AJ33: ='Постоянные затраты'!AH13 -> 6612.5 | AK33: ='Постоянные затраты'!AI13 -> 6612.5 | ... AO33: ='Постоянные затраты'!AM13 -> 6612.5 | AP33: =SUM(AD33:AO33) -> 79350 | AQ33: =P33+AC33+AP33 -> 208350
A34: 8.11 | B34: ='Постоянные затраты'!A14 -> Расходы 10 | D34: ='Постоянные затраты'!B14 -> 0 | E34: ='Постоянные затраты'!C14 -> 0 | F34: ='Постоянные затраты'!D14 -> 0 | G34: ='Постоянные затраты'!E14 -> 0 | H34: ='Постоянные затраты'!F14 -> 0 | I34: ='Постоянные затраты'!G14 -> 0 | J34: ='Постоянные затраты'!H14 -> 0 | K34: ='Постоянные затраты'!I14 -> 0 | ... O34: ='Постоянные затраты'!M14 -> 0 | P34: =SUM(D34:O34) -> 0 | Q34: ='Постоянные затраты'!O14 -> 0 | R34: ='Постоянные затраты'!P14 -> 0 | S34: ='Постоянные затраты'!Q14 -> 0 | T34: ='Постоянные затраты'!R14 -> 0 | U34: ='Постоянные затраты'!S14 -> 0 | V34: ='Постоянные затраты'!T14 -> 0 | W34: ='Постоянные затраты'!U14 -> 0 | X34: ='Постоянные затраты'!V14 -> 0 | ... AB34: ='Постоянные затраты'!Z14 -> 0 | AC34: =SUM(Q34:AB34) -> 0 | AD34: ='Постоянные затраты'!AB14 -> 0 | AE34: ='Постоянные затраты'!AC14 -> 0 | AF34: ='Постоянные затраты'!AD14 -> 0 | AG34: ='Постоянные затраты'!AE14 -> 0 | AH34: ='Постоянные затраты'!AF14 -> 0 | AI34: ='Постоянные затраты'!AG14 -> 0 | AJ34: ='Постоянные затраты'!AH14 -> 0 | AK34: ='Постоянные затраты'!AI14 -> 0 | ... AO34: ='Постоянные затраты'!AM14 -> 0 | AP34: =SUM(AD34:AO34) -> 0 | AQ34: =P34+AC34+AP34 -> 0
A35: 8.12 | B35: ='Постоянные затраты'!A15 -> Расходы 11 | D35: ='Постоянные затраты'!B15 -> 0 | E35: ='Постоянные затраты'!C15 -> 0 | F35: ='Постоянные затраты'!D15 -> 0 | G35: ='Постоянные затраты'!E15 -> 0 | H35: ='Постоянные затраты'!F15 -> 0 | I35: ='Постоянные затраты'!G15 -> 0 | J35: ='Постоянные затраты'!H15 -> 0 | K35: ='Постоянные затраты'!I15 -> 0 | ... O35: ='Постоянные затраты'!M15 -> 0 | P35: =SUM(D35:O35) -> 0 | Q35: ='Постоянные затраты'!O15 -> 0 | R35: ='Постоянные затраты'!P15 -> 0 | S35: ='Постоянные затраты'!Q15 -> 0 | T35: ='Постоянные затраты'!R15 -> 0 | U35: ='Постоянные затраты'!S15 -> 0 | V35: ='Постоянные затраты'!T15 -> 0 | W35: ='Постоянные затраты'!U15 -> 0 | X35: ='Постоянные затраты'!V15 -> 0 | ... AB35: ='Постоянные затраты'!Z15 -> 0 | AC35: =SUM(Q35:AB35) -> 0 | AD35: ='Постоянные затраты'!AB15 -> 0 | AE35: ='Постоянные затраты'!AC15 -> 0 | AF35: ='Постоянные затраты'!AD15 -> 0 | AG35: ='Постоянные затраты'!AE15 -> 0 | AH35: ='Постоянные затраты'!AF15 -> 0 | AI35: ='Постоянные затраты'!AG15 -> 0 | AJ35: ='Постоянные затраты'!AH15 -> 0 | AK35: ='Постоянные затраты'!AI15 -> 0 | ... AO35: ='Постоянные затраты'!AM15 -> 0 | AP35: =SUM(AD35:AO35) -> 0 | AQ35: =P35+AC35+AP35 -> 0
A36: 8.13 | B36: ='Постоянные затраты'!A16 -> Расходы 12 | D36: ='Постоянные затраты'!B16 -> 0 | E36: ='Постоянные затраты'!C16 -> 0 | F36: ='Постоянные затраты'!D16 -> 0 | G36: ='Постоянные затраты'!E16 -> 0 | H36: ='Постоянные затраты'!F16 -> 0 | I36: ='Постоянные затраты'!G16 -> 0 | J36: ='Постоянные затраты'!H16 -> 0 | K36: ='Постоянные затраты'!I16 -> 0 | ... O36: ='Постоянные затраты'!M16 -> 0 | P36: =SUM(D36:O36) -> 0 | Q36: ='Постоянные затраты'!O16 -> 0 | R36: ='Постоянные затраты'!P16 -> 0 | S36: ='Постоянные затраты'!Q16 -> 0 | T36: ='Постоянные затраты'!R16 -> 0 | U36: ='Постоянные затраты'!S16 -> 0 | V36: ='Постоянные затраты'!T16 -> 0 | W36: ='Постоянные затраты'!U16 -> 0 | X36: ='Постоянные затраты'!V16 -> 0 | ... AB36: ='Постоянные затраты'!Z16 -> 0 | AC36: =SUM(Q36:AB36) -> 0 | AD36: ='Постоянные затраты'!AB16 -> 0 | AE36: ='Постоянные затраты'!AC16 -> 0 | AF36: ='Постоянные затраты'!AD16 -> 0 | AG36: ='Постоянные затраты'!AE16 -> 0 | AH36: ='Постоянные затраты'!AF16 -> 0 | AI36: ='Постоянные затраты'!AG16 -> 0 | AJ36: ='Постоянные затраты'!AH16 -> 0 | AK36: ='Постоянные затраты'!AI16 -> 0 | ... AO36: ='Постоянные затраты'!AM16 -> 0 | AP36: =SUM(AD36:AO36) -> 0 | AQ36: =P36+AC36+AP36 -> 0
... A39: 8.16 | B39: ='Постоянные затраты'!A19 -> Расходы 15 | D39: ='Постоянные затраты'!B19 -> 0 | E39: ='Постоянные затраты'!C19 -> 0 | F39: ='Постоянные затраты'!D19 -> 0 | G39: ='Постоянные затраты'!E19 -> 0 | H39: ='Постоянные затраты'!F19 -> 0 | I39: ='Постоянные затраты'!G19 -> 0 | J39: ='Постоянные затраты'!H19 -> 0 | K39: ='Постоянные затраты'!I19 -> 0 | ... O39: ='Постоянные затраты'!M19 -> 0 | P39: =SUM(D39:O39) -> 0 | Q39: ='Постоянные затраты'!O19 -> 0 | R39: ='Постоянные затраты'!P19 -> 0 | S39: ='Постоянные затраты'!Q19 -> 0 | T39: ='Постоянные затраты'!R19 -> 0 | U39: ='Постоянные затраты'!S19 -> 0 | V39: ='Постоянные затраты'!T19 -> 0 | W39: ='Постоянные затраты'!U19 -> 0 | X39: ='Постоянные затраты'!V19 -> 0 | ... AB39: ='Постоянные затраты'!Z19 -> 0 | AC39: =SUM(Q39:AB39) -> 0 | AD39: ='Постоянные затраты'!AB19 -> 0 | AE39: ='Постоянные затраты'!AC19 -> 0 | AF39: ='Постоянные затраты'!AD19 -> 0 | AG39: ='Постоянные затраты'!AE19 -> 0 | AH39: ='Постоянные затраты'!AF19 -> 0 | AI39: ='Постоянные затраты'!AG19 -> 0 | AJ39: ='Постоянные затраты'!AH19 -> 0 | AK39: ='Постоянные затраты'!AI19 -> 0 | ... AO39: ='Постоянные затраты'!AM19 -> 0 | AP39: =SUM(AD39:AO39) -> 0 | AQ39: =P39+AC39+AP39 -> 0
A40: 8.17 | B40: Непредвиденные расходы (5%) | D40: =D6*5% -> 16200 | E40: =E6*5% -> 3950 | F40: =F6*5% -> 35450 | G40: =G6*5% -> 13200 | H40: =H6*5% -> 28200 | I40: =I6*5% -> 35700 | J40: =J6*5% -> 38200 | K40: =K6*5% -> 39550 | ... O40: =O6*5% -> 59550 | P40: =SUM(D40:O40) -> 422900 | Q40: =Q6*5% -> 94990 | R40: =R6*5% -> 117702.5 | S40: =S6*5% -> 112815 | T40: =T6*5% -> 152125.83 | U40: =U6*5% -> 132892.08 | V40: =V6*5% -> 156610.83 | W40: =W6*5% -> 153419.58 | X40: =X6*5% -> 192548.33 | ... AB40: =AB6*5% -> 231820.83 | AC40: =SUM(Q40:AB40) -> 1907217.5 | AD40: =AD6*5% -> 256763.38 | AE40: =AE6*5% -> 272104.38 | AF40: =AF6*5% -> 251605.62 | AG40: =AG6*5% -> 299744.62 | AH40: =AH6*5% -> 281428 | AI40: =AI6*5% -> 328112.25 | AJ40: =AJ6*5% -> 314027.62 | AK40: =AK6*5% -> 360844.12 | ... AO40: =AO6*5% -> 417843.88 | AP40: =SUM(AD40:AO40) -> 3881669.8 | AQ40: =P40+AC40+AP40 -> 6211787.2
A41: 9 | B41: Себестоимость без учета налога на прибыль: | D41: =D7+D9+D13+D15+D22+D23+D40 -> 897930.6 | E41: =E7+E9+E13+E15+E22+E23+E40 -> 840150.4 | F41: =F7+F9+F13+F15+F22+F23+F40 -> 976741 | G41: =G7+G9+G13+G15+G22+G23+G40 -> 869521.2 | H41: =H7+H9+H13+H15+H22+H23+H40 -> 935381.6 | I41: =I7+I9+I13+I15+I22+I23+I40 -> 959572.2 | J41: =J7+J9+J13+J15+J22+J23+J40 -> 967932.6 | K41: =K7+K9+K13+K15+K22+K23+K40 -> 985312.8 | ... O41: =O7+O9+O13+O15+O22+O23+O40 -> 1050414.8 | P41: =SUM(D41:O41) -> 11550389 | Q41: =Q7+Q9+Q13+Q15+Q22+Q23+Q40 -> 1916159.1 | R41: =R7+R9+R13+R15+R22+R23+R40 -> 2010607.8 | S41: =S7+S9+S13+S15+S22+S23+S40 -> 1975796.5 | T41: =T7+T9+T13+T15+T22+T23+T40 -> 2158518.9 | U41: =U7+U9+U13+U15+U22+U23+U40 -> 2058203.7 | V41: =V7+V9+V13+V15+V22+V23+V40 -> 2155826.3 | W41: =W7+W9+W13+W15+W22+W23+W40 -> 2126178.6 | X41: =X7+X9+X13+X15+X22+X23+X40 -> 2308061.5 | ... AB41: =AB7+AB9+AB13+AB15+AB22+AB23+AB40 -> 2454959.1 | AC41: =SUM(Q41:AB41) -> 25950906 | AD41: =AD7+AD9+AD13+AD15+AD22+AD23+AD40 -> 2834476.4 | AE41: =AE7+AE9+AE13+AE15+AE22+AE23+AE40 -> 2902849.7 | AF41: =AF7+AF9+AF13+AF15+AF22+AF23+AF40 -> 2792685.4 | AG41: =AG7+AG9+AG13+AG15+AG22+AG23+AG40 -> 3006754.1 | AH41: =AH7+AH9+AH13+AH15+AH22+AH23+AH40 -> 2912724.3 | AI41: =AI7+AI9+AI13+AI15+AI22+AI23+AI40 -> 3120555.2 | AJ41: =AJ7+AJ9+AJ13+AJ15+AJ22+AJ23+AJ40 -> 3039085.1 | AK41: =AK7+AK9+AK13+AK15+AK22+AK23+AK40 -> 3245593.5 | ... AO41: =AO7+AO9+AO13+AO15+AO22+AO23+AO40 -> 3470550.7 | AP41: =SUM(AD41:AO41) -> 37087182 | AQ41: =P41+AC41+AP41 -> 74588477
A42: 10 | B42: Итого себестоимость: | D42: =D41+D19 -> 928640.43 | E42: =E41+E19 -> 856160.23 | F42: =F41+F19 -> 1030550.8 | G42: =G41+G19 -> 896631.03 | H42: =H41+H19 -> 980491.43 | I42: =I41+I19 -> 1013682 | J42: =J41+J19 -> 1025042.4 | K42: =K41+K19 -> 1044042.6 | ... O42: =O41+O19 -> 1133144.6 | P42: =SUM(D42:O42) -> 12193107 | Q42: =Q41+Q19 -> 2066466.6 | R42: =R41+R19 -> 2188170.3 | S42: =S41+S19 -> 2147494 | T42: =T41+T19 -> 2377389.4 | U42: =U41+U19 -> 2253993.7 | V42: =V41+V19 -> 2380078.8 | W42: =W41+W19 -> 2346601.6 | X42: =X41+X19 -> 2575439 | ... AB42: =AB41+AB19 -> 2769463.6 | AC42: =SUM(Q42:AB42) -> 28675400 | AD42: =AD41+AD19 -> 3212133.1 | AE42: =AE41+AE19 -> 3298915.6 | AF42: =AF41+AF19 -> 3164152.8 | AG42: =AG41+AG19 -> 3435988.3 | AH42: =AH41+AH19 -> 3319978.6 | AI42: =AI41+AI19 -> 3583830.6 | AJ42: =AJ41+AJ19 -> 3485458.9 | AK42: =AK41+AK19 -> 3748147.1 | ... AO42: =AO41+AO19 -> 4041504.1 | AP42: =SUM(AD42:AO42) -> 42579674 | AQ42: =P42+AC42+AP42 -> 83448182
A43: 11 | B43: Рентабельность продаж | D43: =D54/D6 -> -1.8661742 | E43: =E54/E6 -> -9.8374713 | F43: =F54/F6 -> -0.45352727 | G43: =G54/G6 -> -2.3963297 | H43: =H54/H6 -> -0.73845999 | I43: =I54/I6 -> -0.41972274 | J43: =J54/J6 -> -0.34167858 | K43: =K54/K6 -> -0.31990219 | ... AQ43: =AQ54/AQ6 -> 0.32830779
A44: 12 | B44: Денежный поток от операционной деятельности | D44: =D6-D42 -> -604640.43 | E44: =E6-E42 -> -777160.23 | F44: =F6-F42 -> -321550.83 | G44: =G6-G42 -> -632631.03 | H44: =H6-H42 -> -416491.43 | I44: =I6-I42 -> -299682.03 | J44: =J6-J42 -> -261042.43 | K44: =K6-K42 -> -253042.63 | ... O44: =O6-O42 -> 57855.367 | P44: =D44+E44+F44+G44+H44+I44+J44+K44+L44+M44+N44+O44 -> -3735107.2 | Q44: =Q6-Q42 -> -166666.56 | R44: =R6-R42 -> 165879.74 | S44: =S6-S42 -> 108806.04 | T44: =T6-T42 -> 665127.27 | U44: =U6-U42 -> 403847.97 | V44: =V6-V42 -> 752137.87 | W44: =W6-W42 -> 721790.07 | X44: =X6-X42 -> 1275527.7 | ... AB44: =AB6-AB42 -> 1866953.1 | AC44: =SUM(Q44:AB44) -> 9468949.8 | AD44: =AD6-AD42 -> 1923134.4 | AE44: =AE6-AE42 -> 2143171.9 | AF44: =AF6-AF42 -> 1867959.7 | AG44: =AG6-AG42 -> 2558904.2 | AH44: =AH6-AH42 -> 2308581.4 | AI44: =AI6-AI42 -> 2978414.4 | AJ44: =AJ6-AJ42 -> 2795093.6 | AK44: =AK6-AK42 -> 3468735.4 | ... AO44: =AO6-AO42 -> 4315373.4 | AP44: =SUM(AD44:AO44) -> 35053721 | AQ44: =P44+AC44+AP44 -> 40787563
A45: 13 | B45: Инвестиционные расходы | C45: =SUM(C46:C46) -> 2480000 | D45: =SUM(D46) -> 0 | E45: =SUM(E46) -> 0 | F45: =SUM(F46) -> 0 | G45: =SUM(G46) -> 0 | H45: =SUM(H46) -> 0 | I45: =SUM(I46) -> 0 | J45: =SUM(J46) -> 0 | K45: =SUM(K46) -> 0 | ... AQ45: =SUM(AQ46) -> 0
A46: 13.1 | B46: Расходы на подготовку проекта | C46: ='План-график'!F19 -> 2480000 | D46: 0 | E46: 0 | F46: 0 | G46: 0 | H46: 0 | I46: 0 | J46: 0 | K46: 0 | L46: 0 | M46: 0 | N46: 0 | O46: 0 | P46: =SUM(D46:O46) -> 0 | Q46: 0 | R46: 0 | S46: 0 | T46: 0 | U46: 0 | V46: 0 | W46: 0 | X46: 0 | Y46: 0 | Z46: 0 | AA46: 0 | AB46: 0 | AC46: =SUM(Q46:AB46) -> 0 | AD46: 0 | AE46: 0 | AF46: 0 | AG46: 0 | AH46: 0 | AI46: 0 | AJ46: 0 | AK46: 0 | AL46: 0 | AM46: 0 | AN46: 0 | AO46: 0 | AP46: =SUM(AD46:AO46) -> 0 | AQ46: =P46+AC46+AP46 -> 0
A47: 14 | B47: Денежный поток от финансовой деятельности | C47: =SUM(C48:C50) -> 500000 | D47: =SUM(D48:D50)-D51-D52-D53 -> 0 | E47: =SUM(E48:E50)-E51-E52-E53 -> 0 | F47: =SUM(F48:F50)-F51-F52-F53 -> 0 | G47: =SUM(G48:G50)-G51-G52-G53 -> 0 | H47: =SUM(H48:H50)-H51-H52-H53 -> 0 | I47: =SUM(I48:I50)-I51-I52-I53 -> 0 | J47: =SUM(J48:J50)-J51-J52-J53 -> 0 | K47: =SUM(K48:K50)-K51-K52-K53 -> 0 | ... AP47: =SUM(AP48:AP50)-AP51-AP52-AP53 -> 0 | AQ47: =P47+AC47+AP47 -> 0
A48: 14.1 | B48: Собственный капитал | C48: 500000 | D48: 0 | E48: 0 | F48: 0 | G48: 0 | H48: 0 | I48: 0 | J48: 0 | K48: 0 | L48: 0 | M48: 0 | N48: 0 | O48: 0 | P48: =SUM(D48:O48) -> 0 | Q48: 0 | R48: 0 | S48: 0 | T48: 0 | U48: 0 | V48: 0 | W48: 0 | X48: 0 | Y48: 0 | Z48: 0 | AA48: 0 | AB48: 0 | AC48: =SUM(Q48:AB48) -> 0 | AD48: 0 | AE48: 0 | AF48: 0 | AG48: 0 | AH48: 0 | AI48: 0 | AJ48: 0 | AK48: 0 | AL48: 0 | AM48: 0 | AN48: 0 | AO48: 0 | AP48: =SUM(AD48:AO48) -> 0 | AQ48: =P48+AC48+AP48 -> 0
A49: 14.2 | B49: Заемный капитал | D49: 0 | E49: 0 | F49: 0 | G49: 0 | H49: 0 | I49: 0 | J49: 0 | K49: 0 | L49: 0 | M49: 0 | N49: 0 | O49: 0 | P49: =SUM(D49:O49) -> 0 | Q49: 0 | R49: 0 | S49: 0 | T49: 0 | U49: 0 | V49: 0 | W49: 0 | X49: 0 | Y49: 0 | Z49: 0 | AA49: 0 | AB49: 0 | AC49: =SUM(Q49:AB49) -> 0 | AD49: 0 | AE49: 0 | AF49: 0 | AG49: 0 | AH49: 0 | AI49: 0 | AJ49: 0 | AK49: 0 | AL49: 0 | AM49: 0 | AN49: 0 | AO49: 0 | AP49: =SUM(AD49:AO49) -> 0 | AQ49: =P49+AC49+AP49 -> 0
A50: 14.3 | B50: Невозвратное финансирование (гранты, пожертвование) | C50: 0 | D50: 0 | E50: 0 | F50: 0 | G50: 0 | H50: 0 | I50: 0 | J50: 0 | K50: 0 | L50: 0 | M50: 0 | N50: 0 | O50: 0 | P50: =SUM(D50:O50) -> 0 | Q50: 0 | R50: 0 | S50: 0 | T50: 0 | U50: 0 | V50: 0 | W50: 0 | X50: 0 | Y50: 0 | Z50: 0 | AA50: 0 | AB50: 0 | AC50: =SUM(Q50:AB50) -> 0 | AD50: 0 | AE50: 0 | AF50: 0 | AG50: 0 | AH50: 0 | AI50: 0 | AJ50: 0 | AK50: 0 | AL50: 0 | AM50: 0 | AN50: 0 | AO50: 0 | AP50: =SUM(AD50:AO50) -> 0 | AQ50: =P50+AC50+AP50 -> 0
A51: 14.4 | B51: Погашение основного долга | D51: =Кредит!B14 -> 0 | E51: =Кредит!B15 -> 0 | F51: =Кредит!B16 -> 0 | G51: =Кредит!B17 -> 0 | H51: =Кредит!B18 -> 0 | I51: =Кредит!B19 -> 0 | J51: =Кредит!B20 -> 0 | K51: =Кредит!B21 -> 0 | L51: =Кредит!B22 -> 0 | M51: =Кредит!B23 -> 0 | N51: =Кредит!B24 -> 0 | O51: =Кредит!B25 -> 0 | P51: =SUM(D51:O51) -> 0 | Q51: =Кредит!B26 -> 0 | R51: =Кредит!B27 -> 0 | S51: =Кредит!B28 -> 0 | T51: =Кредит!B29 -> 0 | U51: =Кредит!B30 -> 0 | V51: =Кредит!B31 -> 0 | W51: =Кредит!B32 -> 0 | X51: =Кредит!B33 -> 0 | Y51: =Кредит!B34 -> 0 | Z51: =Кредит!B35 -> 0 | AA51: =Кредит!B36 -> 0 | AB51: =Кредит!B37 -> 0 | AC51: =SUM(Q51:AB51) -> 0 | AD51: =Кредит!B38 -> 0 | AE51: =Кредит!B39 -> 0 | AF51: =Кредит!B40 -> 0 | AG51: =Кредит!B41 -> 0 | AH51: =Кредит!B42 -> 0 | AI51: =Кредит!B43 -> 0 | AJ51: =Кредит!B44 -> 0 | AK51: =Кредит!B45 -> 0 | AL51: =Кредит!B46 -> 0 | AM51: =Кредит!B47 -> 0 | AN51: =Кредит!B48 -> 0 | AO51: =Кредит!B49 -> 0 | AP51: =SUM(AD51:AO51) -> 0 | AQ51: =P51+AC51+AP51 -> 0
A52: 14.5 | B52: Погашение процентов | D52: =Кредит!C14 -> 0 | E52: =Кредит!C15 -> 0 | F52: =Кредит!C16 -> 0 | G52: =Кредит!C17 -> 0 | H52: =Кредит!C18 -> 0 | I52: =Кредит!C19 -> 0 | J52: =Кредит!C20 -> 0 | K52: =Кредит!C21 -> 0 | L52: =Кредит!C22 -> 0 | M52: =Кредит!C23 -> 0 | N52: =Кредит!C24 -> 0 | O52: =Кредит!C25 -> 0 | P52: =SUM(D52:O52) -> 0 | Q52: =Кредит!C26 -> 0 | R52: =Кредит!C27 -> 0 | S52: =Кредит!C28 -> 0 | T52: =Кредит!C29 -> 0 | U52: =Кредит!C30 -> 0 | V52: =Кредит!C31 -> 0 | W52: =Кредит!C32 -> 0 | X52: =Кредит!C33 -> 0 | Y52: =Кредит!C34 -> 0 | Z52: =Кредит!C35 -> 0 | AA52: =Кредит!C36 -> 0 | AB52: =Кредит!C37 -> 0 | AC52: =SUM(Q52:AB52) -> 0 | AD52: =Кредит!C38 -> 0 | AE52: =Кредит!C39 -> 0 | AF52: =Кредит!C40 -> 0 | AG52: =Кредит!C41 -> 0 | AH52: =Кредит!C42 -> 0 | AI52: =Кредит!C43 -> 0 | AJ52: =Кредит!C44 -> 0 | AK52: =Кредит!C45 -> 0 | AL52: =Кредит!C46 -> 0 | AM52: =Кредит!C47 -> 0 | AN52: =Кредит!C48 -> 0 | AO52: =Кредит!C49 -> 0 | AP52: =SUM(AD52:AO52) -> 0 | AQ52: =P52+AC52+AP52 -> 0
A53: 14.6 | B53: Выплаты дивидендов | D53: 0 | E53: 0 | F53: 0 | G53: 0 | H53: 0 | I53: 0 | J53: 0 | K53: 0 | L53: 0 | M53: 0 | N53: 0 | O53: 0 | P53: =SUM(D53:O53) -> 0 | Q53: 0 | R53: 0 | S53: 0 | T53: 0 | U53: 0 | V53: 0 | W53: 0 | X53: 0 | Y53: 0 | Z53: 0 | AA53: 0 | AB53: 0 | AC53: =SUM(Q53:AB53) -> 0 | AD53: 0 | AE53: 0 | AF53: 0 | AG53: 0 | AH53: 0 | AI53: 0 | AJ53: 0 | AK53: 0 | AL53: 0 | AM53: 0 | AN53: 0 | AO53: 0 | AP53: =SUM(AD53:AO53) -> 0 | AQ53: =P53+AC53+AP53 -> 0
A54: 15 | B54: Нераспределенная прибыль (CashFlow) | C54: =C44-C45+C47 -> -1980000 | D54: =D44-D45+D47 -> -604640.43 | E54: =E44-E45+E47 -> -777160.23 | F54: =F44-F45+F47 -> -321550.83 | G54: =G44-G45+G47 -> -632631.03 | H54: =H44-H45+H47 -> -416491.43 | I54: =I44-I45+I47 -> -299682.03 | J54: =J44-J45+J47 -> -261042.43 | ... AQ54: =AQ44-AQ45+AQ47 -> 40787563
A55: 16 | B55: Прибыль нарастающим итогом | C55: =C54 -> -1980000 | D55: =C55+D54 -> -2584640.4 | E55: =D55+E54 -> -3361800.7 | F55: =E55+F54 -> -3683351.5 | G55: =F55+G54 -> -4315982.5 | H55: =G55+H54 -> -4732474 | I55: =H55+I54 -> -5032156 | J55: =I55+J54 -> -5293198.4 | K55: =J55+K54 -> -5546241.1 | ... O55: =N55+O54 -> -5715107.2 | P55: =O55 -> -5715107.2 | Q55: =P55+Q54 -> -5881773.8 | R55: =Q55+R54 -> -5715894 | S55: =R55+S54 -> -5607088 | T55: =S55+T54 -> -4941960.7 | U55: =T55+U54 -> -4538112.7 | V55: =U55+V54 -> -3785974.9 | W55: =V55+W54 -> -3064184.8 | X55: =W55+X54 -> -1788657.1 | ... AB55: =AA55+AB54 -> 3753842.6 | AC55: =AB55 -> 3753842.6 | AD55: =AC55+AD54 -> 5676977 | AE55: =AD55+AE54 -> 7820148.9 | AF55: =AE55+AF54 -> 9688108.5 | AG55: =AF55+AG54 -> 12247013 | AH55: =AG55+AH54 -> 14555594 | AI55: =AH55+AI54 -> 17534009 | AJ55: =AI55+AJ54 -> 20329102 | AK55: =AJ55+AK54 -> 23797838 | ... AO55: =AN55+AO54 -> 38807563 | AP55: =AO55 -> 38807563 | AQ55: =AP55 -> 38807563
B57: Номер месяца | C57: =C4 -> Инвестиционный месяц | D57: 1 | E57: 2 | F57: 3 | G57: 4 | H57: 5 | I57: 6 | J57: 7 | K57: 8 | L57: 9 | M57: 10 | N57: 11 | O57: 12 | P57: 13 | Q57: 14 | R57: 15 | S57: 16 | T57: 17 | U57: 18 | V57: 19 | W57: 20 | X57: 21 | Y57: 22 | Z57: 23 | AA57: 24 | AB57: 25 | AC57: 26 | AD57: 27 | AE57: 28 | AF57: 29 | AG57: 30 | AH57: 31 | AI57: 32 | AJ57: 33 | AK57: 34 | AL57: 35 | AM57: 36
B58: Накопленное сальдо | C58: =-C45 -> -2480000 | D58: =D55+C58 -> -5064640.4 | E58: =E55+D58 -> -8426441.1 | F58: =F55+E58 -> -12109793 | G58: =G55+F58 -> -16425775 | H58: =H55+G58 -> -21158249 | I58: =I55+H58 -> -26190405 | J58: =J55+I58 -> -31483604 | K58: =K55+J58 -> -37029845 | ... O58: =O55+N58 -> -59753097 | P58: =Q55+O58 -> -65634871 | Q58: =R55+P58 -> -71350765 | R58: =S55+Q58 -> -76957853 | S58: =T55+R58 -> -81899814 | T58: =U55+S58 -> -86437926 | U58: =V55+T58 -> -90223901 | V58: =W55+U58 -> -93288086 | W58: =X55+V58 -> -95076743 | ... AA58: =AB55+Z58 -> -89632226 | AB58: =AD55+AA58 -> -83955249 | AC58: =AE55+AB58 -> -76135100 | AD58: =AF55+AC58 -> -66446992 | AE58: =AG55+AD58 -> -54199979 | AF58: =AH55+AE58 -> -39644385 | AG58: =AI55+AF58 -> -22110376 | AH58: =AJ55+AG58 -> -1781274.2 | AI58: =AK55+AH58 -> 22016563 | ... AM58: =AO55+AL58 -> 1.5318303e+08
B59: ='Экономические показ.'!B9 -> Срок окупаемости (Tок.), мес. | C59: =SUM(D59:O59) -> 12 | D59: =IF(D58<0,1,IF(C58<0,-C58/(D58-C58)*1+1,0)) -> 1 | E59: =IF(E58<0,1,IF(D58<0,-D58/(E58-D58)*1+1,0)) -> 1 | F59: =IF(F58<0,1,IF(E58<0,-E58/(F58-E58)*1+1,0)) -> 1 | G59: =IF(G58<0,1,IF(F58<0,-F58/(G58-F58)*1+1,0)) -> 1 | H59: =IF(H58<0,1,IF(G58<0,-G58/(H58-G58)*1+1,0)) -> 1 | I59: =IF(I58<0,1,IF(H58<0,-H58/(I58-H58)*1+1,0)) -> 1 | J59: =IF(J58<0,1,IF(I58<0,-I58/(J58-I58)*1+1,0)) -> 1 | K59: =IF(K58<0,1,IF(J58<0,-J58/(K58-J58)*1+1,0)) -> 1 | ... AM59: =IF(AM58<0,1,IF(AL58<0,-AL58/(AM58-AL58)*1+1,0)) -> 0
B61: Период | C61: =C57 -> Инвестиционный месяц | D61: 1 год | E61: 2 год | F61: 3 год
B62: Сальдо (годовое) | C62: =C58 -> -2480000 | D62: =P54 -> -3735107.2 | E62: =AC54 -> 9468949.8 | F62: =AP54 -> 35053721

Sheet График чистой прибыли

Sheet План-график
B2: План-график реализации проекта
A3: № | B3: Этап проекта | C3: Начало этапа | D3: Длительность, день | E3: Конец этапа | F3: Стоимость этапа, руб.
A4: 1 | B4: Регистрация юр. лица, договоры | C4: 45658 | D4: 14 | E4: =C4+D4-1 -> 45671 | F4: 60000
A5: 2 | B5: Разработка UX/UI и брендинг | C5: =E4+1 -> 45672 | D5: 30 | E5: =C5+D5-1 -> 45701 | F5: 290000
A6: 3 | B6: Fronted + Backend (MVP) | C6: =E5+1 -> 45702 | D6: 90 | E6: =C6+D6-1 -> 45791 | F6: 900000
A7: 4 | B7: DevOps, CI/CD, инфраструктура | C7: =E6+1 -> 45792 | D7: 14 | E7: =C7+D7-1 -> 45805 | F7: 120000
A8: 5 | B8: Тестирование (QA) | C8: =E7+1 -> 45806 | D8: 21 | E8: =C8+D8-1 -> 45826 | F8: 150000
A9: 6 | B9: Запуск MVP, первые клиенты | C9: =E8+1 -> 45827 | D9: 14 | E9: =C9+D9-1 -> 45840 | F9: 100000
A10: 7 | B10: Маркетинг, привлечение (1 мес.) | C10: =E9+1 -> 45841 | D10: 31 | E10: =C10+D10-1 -> 45871 | F10: 160000
A11: 8 | B11: Поддержка, итерации, доработки | C11: =E10+1 -> 45872 | D11: 150 | E11: =C11+D11-1 -> 46021 | F11: 700000
A12: 9 | C12: =E11+1 -> 46022 | E12: =C12+D12-1 -> 46021 | F12: 0
A13: 10 | C13: =E12+1 -> 46022 | E13: =C13+D13-1 -> 46021 | F13: 0
A14: 11 | C14: =E13+1 -> 46022 | E14: =C14+D14-1 -> 46021 | F14: 0
A15: 12 | C15: =E14+1 -> 46022 | E15: =C15+D15-1 -> 46021 | F15: 0
A16: 13 | C16: =E15+1 -> 46022 | E16: =C16+D16-1 -> 46021 | F16: 0
A17: 14 | C17: =E16+1 -> 46022 | E17: =C17+D17-1 -> 46021 | F17: 0
A18: 15 | C18: =E17+1 -> 46022 | E18: =C18+D18-1 -> 46021 | F18: 0
A19: ИТОГО | D19: =SUM(D4:D18) -> 364 | E19: - | F19: =SUM(F4:F18) -> 2480000
B21: *Примечание: при отсутствии затрат на этапе запуска проекта, в графе "Стоимость этапа" оставлять пустую ячейку!!!

Sheet Диаграмма Ганта

Sheet График инвестиц.затрат

Sheet Кредит
B2: Кредитный калькулятор (аннуитетные платежи)
B4: Сумма кредита, руб.
B5: Годовая ставка | C5: 0.09
B6: Срок кредита, мес. | C6: 36
B8: Сумма ежемес. Выплат, руб. | C8: =-(PMT(C5/12,C6,C4,0,0)) -> 0
B9: Общая сумма выплат, руб. | C9: =C8*C6 -> 0
B10: Переплата, руб. | C10: =C9-C4 -> 0
A13: Период | B13: Выплата основного долга, руб. | C13: Выплата процентов, руб. | D13: Общая выплата, руб. | E13: Осталось выплатить, руб.
A14: 1 | B14: =-(PPMT($C$5/12,A14,$C$6,$C$4,0,0)) -> 0 | C14: =-(IPMT($C$5/12,A14,$C$6,$C$4,0,0)) -> 0 | D14: =B14+C14 -> 0 | E14: =C4-B14 -> 0
A15: =IF(A14>=$C$6,"",A14+1) -> 2 | B15: =-(IF(A15<>"",PPMT($C$5/12,A15,$C$6,$C$4,0,0),0)) -> 0 | C15: =-(IF(A15<>"",IPMT($C$5/12,A15,$C$6,$C$4,0,0),0)) -> 0 | D15: =IF(A15<>"",B15+C15,0) -> 0 | E15: =IF(A15<>"",$C$4-SUM($B$14:B15),0) -> 0
A16: =IF(A15>=$C$6,"",A15+1) -> 3 | B16: =-(IF(A16<>"",PPMT($C$5/12,A16,$C$6,$C$4,0,0),0)) -> 0 | C16: =-(IF(A16<>"",IPMT($C$5/12,A16,$C$6,$C$4,0,0),0)) -> 0 | D16: =IF(A16<>"",B16+C16,0) -> 0 | E16: =IF(A16<>"",$C$4-SUM($B$14:B16),0) -> 0
A17: =IF(A16>=$C$6,"",A16+1) -> 4 | B17: =-(IF(A17<>"",PPMT($C$5/12,A17,$C$6,$C$4,0,0),0)) -> 0 | C17: =-(IF(A17<>"",IPMT($C$5/12,A17,$C$6,$C$4,0,0),0)) -> 0 | D17: =IF(A17<>"",B17+C17,0) -> 0 | E17: =IF(A17<>"",$C$4-SUM($B$14:B17),0) -> 0
A18: =IF(A17>=$C$6,"",A17+1) -> 5 | B18: =-(IF(A18<>"",PPMT($C$5/12,A18,$C$6,$C$4,0,0),0)) -> 0 | C18: =-(IF(A18<>"",IPMT($C$5/12,A18,$C$6,$C$4,0,0),0)) -> 0 | D18: =IF(A18<>"",B18+C18,0) -> 0 | E18: =IF(A18<>"",$C$4-SUM($B$14:B18),0) -> 0
A19: =IF(A18>=$C$6,"",A18+1) -> 6 | B19: =-(IF(A19<>"",PPMT($C$5/12,A19,$C$6,$C$4,0,0),0)) -> 0 | C19: =-(IF(A19<>"",IPMT($C$5/12,A19,$C$6,$C$4,0,0),0)) -> 0 | D19: =IF(A19<>"",B19+C19,0) -> 0 | E19: =IF(A19<>"",$C$4-SUM($B$14:B19),0) -> 0
A20: =IF(A19>=$C$6,"",A19+1) -> 7 | B20: =-(IF(A20<>"",PPMT($C$5/12,A20,$C$6,$C$4,0,0),0)) -> 0 | C20: =-(IF(A20<>"",IPMT($C$5/12,A20,$C$6,$C$4,0,0),0)) -> 0 | D20: =IF(A20<>"",B20+C20,0) -> 0 | E20: =IF(A20<>"",$C$4-SUM($B$14:B20),0) -> 0
A21: =IF(A20>=$C$6,"",A20+1) -> 8 | B21: =-(IF(A21<>"",PPMT($C$5/12,A21,$C$6,$C$4,0,0),0)) -> 0 | C21: =-(IF(A21<>"",IPMT($C$5/12,A21,$C$6,$C$4,0,0),0)) -> 0 | D21: =IF(A21<>"",B21+C21,0) -> 0 | E21: =IF(A21<>"",$C$4-SUM($B$14:B21),0) -> 0
A22: =IF(A21>=$C$6,"",A21+1) -> 9 | B22: =-(IF(A22<>"",PPMT($C$5/12,A22,$C$6,$C$4,0,0),0)) -> 0 | C22: =-(IF(A22<>"",IPMT($C$5/12,A22,$C$6,$C$4,0,0),0)) -> 0 | D22: =IF(A22<>"",B22+C22,0) -> 0 | E22: =IF(A22<>"",$C$4-SUM($B$14:B22),0) -> 0
A23: =IF(A22>=$C$6,"",A22+1) -> 10 | B23: =-(IF(A23<>"",PPMT($C$5/12,A23,$C$6,$C$4,0,0),0)) -> 0 | C23: =-(IF(A23<>"",IPMT($C$5/12,A23,$C$6,$C$4,0,0),0)) -> 0 | D23: =IF(A23<>"",B23+C23,0) -> 0 | E23: =IF(A23<>"",$C$4-SUM($B$14:B23),0) -> 0
A24: =IF(A23>=$C$6,"",A23+1) -> 11 | B24: =-(IF(A24<>"",PPMT($C$5/12,A24,$C$6,$C$4,0,0),0)) -> 0 | C24: =-(IF(A24<>"",IPMT($C$5/12,A24,$C$6,$C$4,0,0),0)) -> 0 | D24: =IF(A24<>"",B24+C24,0) -> 0 | E24: =IF(A24<>"",$C$4-SUM($B$14:B24),0) -> 0
A25: =IF(A24>=$C$6,"",A24+1) -> 12 | B25: =-(IF(A25<>"",PPMT($C$5/12,A25,$C$6,$C$4,0,0),0)) -> 0 | C25: =-(IF(A25<>"",IPMT($C$5/12,A25,$C$6,$C$4,0,0),0)) -> 0 | D25: =IF(A25<>"",B25+C25,0) -> 0 | E25: =IF(A25<>"",$C$4-SUM($B$14:B25),0) -> 0
A26: =IF(A25>=$C$6,"",A25+1) -> 13 | B26: =-(IF(A26<>"",PPMT($C$5/12,A26,$C$6,$C$4,0,0),0)) -> 0 | C26: =-(IF(A26<>"",IPMT($C$5/12,A26,$C$6,$C$4,0,0),0)) -> 0 | D26: =IF(A26<>"",B26+C26,0) -> 0 | E26: =IF(A26<>"",$C$4-SUM($B$14:B26),0) -> 0
... A50: =IF(A49>=$C$6,"",A49+1) | B50: =-(IF(A50<>"",PPMT($C$5/12,A50,$C$6,$C$4,0,0),0)) -> 0 | C50: =-(IF(A50<>"",IPMT($C$5/12,A50,$C$6,$C$4,0,0),0)) -> 0 | D50: =IF(A50<>"",B50+C50,0) -> 0 | E50: =IF(A50<>"",$C$4-SUM($B$14:B50),0) -> 0

Sheet Продукция и цена 
A2: Цены реализации
A3: Наименование продукта/услуги | B3: Ед. изм | C3: Цена, руб. | D3: Цена, руб. | E3: Цена, руб.
A4: Аренда системы: "Базовый" тариф | B4: мес/объект | C4: 35000 | D4: =C4+C4*'Вводные данные'!$D$4 -> 40250 | E4: =D4+D4*'Вводные данные'!$E$4 -> 46287.5
A5: Поддержка системы | B5: мес/объект | C5: 15000 | D5: =C5+C5*'Вводные данные'!$D$4 -> 17250 | E5: =D5+D5*'Вводные данные'!$E$4 -> 19837.5
A6: Встроенная коммерция (доп. услуги) | B6: мес/услуга | C6: 9000 | D6: =C6+C6*'Вводные данные'!$D$4 -> 10350 | E6: =D6+D6*'Вводные данные'!$E$4 -> 11902.5
A7: Установка и настройка системы, онбординг | B7: разово | C7: 250000 | D7: =C7+C7*'Вводные данные'!$D$4 -> 287500 | E7: =D7+D7*'Вводные данные'!$E$4 -> 330625
A8: Реклама/партнёрства | B8: руб/мес | C8: 20000 | D8: =C8+C8*'Вводные данные'!$D$4 -> 23000 | E8: =D8+D8*'Вводные данные'!$E$4 -> 26450
D9: =C9+C9*'Вводные данные'!$D$4 -> 0 | E9: =D9+D9*'Вводные данные'!$E$4 -> 0
D10: =C10+C10*'Вводные данные'!$D$4 -> 0 | E10: =D10+D10*'Вводные данные'!$E$4 -> 0
A11: Аренда системы: "Продвинутый" тариф | B11: мес/объект | C11: 65000 | D11: =C11+C11*'Вводные данные'!$D$4 -> 74750 | E11: =D11+D11*'Вводные данные'!$E$4 -> 85962.5
A12: Аренда системы: "Бизнес" тариф | B12: мес/объект | C12: 12000 | D12: =C12+C12*'Вводные данные'!$D$4 -> 13800 | E12: =D12+D12*'Вводные данные'!$E$4 -> 15870
D13: =C13+C13*'Вводные данные'!$D$4 -> 0 | E13: =D13+D13*'Вводные данные'!$E$4 -> 0

Sheet Продажи
A2: Объем производства в натуральном выражении (шт, чел, тонн и пр.)
A3: Наименование продукта/услуги | B3: 1 год | N3: ИТОГО за 1 год | O3: 2 год | AA3: ИТОГО за 2 год | AB3: 3 год | AN3: ИТОГО за 3 год
B4: =РДДС!D5 -> 45809 | C4: =РДДС!E5 -> 45839 | D4: =РДДС!F5 -> 45870 | E4: =РДДС!G5 -> 45901 | F4: =РДДС!H5 -> 45931 | G4: =РДДС!I5 -> 45962 | H4: =РДДС!J5 -> 45992 | I4: =РДДС!K5 -> 46023 | ... M4: =РДДС!O5 -> 46143 | O4: =РДДС!Q5 -> 46174 | P4: =РДДС!R5 -> 46204 | Q4: =РДДС!S5 -> 46235 | R4: =РДДС!T5 -> 46266 | S4: =РДДС!U5 -> 46296 | T4: =РДДС!V5 -> 46327 | U4: =РДДС!W5 -> 46357 | V4: =РДДС!X5 -> 46388 | ... Z4: =РДДС!AB5 -> 46508 | AB4: =РДДС!AD5 -> 46539 | AC4: =РДДС!AE5 -> 46569 | AD4: =РДДС!AF5 -> 46600 | AE4: =РДДС!AG5 -> 46631 | AF4: =РДДС!AH5 -> 46661 | AG4: =РДДС!AI5 -> 46692 | AH4: =РДДС!AJ5 -> 46722 | AI4: =РДДС!AK5 -> 46753 | ... AM4: =РДДС!AO5 -> 46874
A5: ='Продукция и цена '!A4 -> Аренда системы: "Базовый" тариф | B5: 1 | C5: 2 | D5: 3 | E5: 4 | F5: 5 | G5: 7 | H5: 8 | I5: 8 | J5: 10 | K5: 12 | L5: 13 | M5: 14 | N5: =SUM(B5:M5) -> 87 | O5: 15 | P5: 16 | Q5: 18 | R5: 19.333333 | S5: 20.833333 | T5: 22.333333 | U5: 23.833333 | V5: 25.333333 | W5: 26.833333 | X5: 28.333333 | Y5: 29.833333 | Z5: 31.333333 | AA5: =SUM(O5:Z5) -> 277 | AB5: 6 | AC5: 6 | AD5: 6 | AE5: 6 | AF5: 6 | AG5: 6 | AH5: 7 | AI5: 7 | AJ5: 7 | AK5: 7 | AL5: 7 | AM5: 7 | AN5: =SUM(AB5:AM5) -> 78
A6: ='Продукция и цена '!A5 -> Поддержка системы | B6: 2 | C6: 0 | D6: 2 | E6: 2 | F6: 3 | G6: 4 | H6: 5 | I6: 6 | J6: 8 | K6: 8 | L6: 9 | M6: 10 | N6: =SUM(B6:M6) -> 59 | O6: 12 | P6: 15 | Q6: 17 | R6: 21 | S6: 23 | T6: 26 | U6: 28 | V6: 32 | W6: 34 | X6: 37 | Y6: 39 | Z6: 43 | AA6: =SUM(O6:Z6) -> 327 | AB6: 49 | AC6: 55 | AD6: 59 | AE6: 65 | AF6: 69 | AG6: 75 | AH6: 79 | AI6: 85 | AJ6: 89 | AK6: 95 | AL6: 99 | AM6: 105 | AN6: =SUM(AB6:AM6) -> 924
A7: ='Продукция и цена '!A6 -> Встроенная коммерция (доп. услуги) | B7: 1 | C7: 1 | D7: 1 | E7: 1 | F7: 1 | G7: 1 | H7: 1 | I7: 1 | J7: 1 | K7: 1 | L7: 1 | M7: 1 | N7: =SUM(B7:M7) -> 12 | O7: 10 | P7: 10 | Q7: 10 | R7: 10 | S7: 12 | T7: 12 | U7: 15 | V7: 14 | W7: 18 | X7: 18 | Y7: 18 | Z7: 18 | AA7: =SUM(O7:Z7) -> 165 | AB7: 20 | AC7: 20 | AD7: 20 | AE7: 20 | AF7: 23 | AG7: 23 | AH7: 27 | AI7: 25 | AJ7: 26 | AK7: 26 | AL7: 27 | AM7: 27 | AN7: =SUM(AB7:AM7) -> 284
A8: ='Продукция и цена '!A7 -> Установка и настройка системы, онбординг | B8: 1 | C8: 0 | D8: 2 | E8: 0 | F8: 1 | G8: 1 | H8: 1 | I8: 1 | J8: 2 | K8: 0 | L8: 1 | M8: 1 | N8: =SUM(B8:M8) -> 11 | O8: 2 | P8: 3 | Q8: 2 | R8: 4 | S8: 2 | T8: 3 | U8: 2 | V8: 4 | W8: 2 | X8: 3 | Y8: 2 | Z8: 4 | AA8: =SUM(O8:Z8) -> 33 | AB8: 6 | AC8: 6 | AD8: 4 | AE8: 6 | AF8: 4 | AG8: 6 | AH8: 4 | AI8: 6 | AJ8: 4 | AK8: 6 | AL8: 4 | AM8: 6 | AN8: =SUM(AB8:AM8) -> 62
A9: ='Продукция и цена '!A8 -> Реклама/партнёрства | B9: 0 | C9: 0 | D9: 0 | E9: 1 | F9: 1 | G9: 1 | H9: 1 | I9: 1 | J9: 1 | K9: 1 | L9: 1 | M9: 1 | N9: =SUM(B9:M9) -> 9 | O9: 1 | P9: 1 | Q9: 1 | R9: 1 | S9: 1 | T9: 1 | U9: 2 | V9: 2 | W9: 1 | X9: 1 | Y9: 2 | Z9: 2 | AA9: =SUM(O9:Z9) -> 16 | AB9: 2 | AC9: 2 | AD9: 2 | AE9: 2 | AF9: 2 | AG9: 1 | AH9: 2 | AI9: 2 | AJ9: 2 | AK9: 1 | AL9: 2 | AM9: 2 | AN9: =SUM(AB9:AM9) -> 22
A10: ='Продукция и цена '!A9 -> 0 | B10: 0 | C10: 0 | D10: 0 | E10: 0 | F10: 0 | G10: 0 | H10: 0 | I10: 0 | J10: 0 | K10: 0 | L10: 0 | M10: 0 | N10: =SUM(B10:M10) -> 0 | O10: 0 | P10: 0 | Q10: 0 | R10: 0 | S10: 0 | T10: 0 | U10: 0 | V10: 0 | W10: 3 | X10: 3 | Y10: 0 | Z10: 0 | AA10: =SUM(O10:Z10) -> 6 | AB10: 0 | AC10: 0 | AD10: 0 | AE10: 0 | AF10: 0 | AG10: 0 | AH10: 0 | AI10: 0 | AJ10: 0 | AK10: 0 | AL10: 0 | AM10: 0 | AN10: =SUM(AB10:AM10) -> 0
A11: ='Продукция и цена '!A10 -> 0 | B11: 0 | C11: 0 | D11: 0 | E11: 0 | F11: 0 | G11: 0 | H11: 0 | I11: 0 | J11: 0 | K11: 0 | L11: 0 | M11: 0 | N11: =SUM(B11:M11) -> 0 | O11: 0 | P11: 0 | Q11: 0 | R11: 0 | S11: 0 | T11: 0 | U11: 0 | V11: 0 | W11: 0 | X11: 0 | Y11: 0 | Z11: 0 | AA11: =SUM(O11:Z11) -> 0 | AB11: 0 | AC11: 0 | AD11: 0 | AE11: 0 | AF11: 0 | AG11: 0 | AH11: 0 | AI11: 0 | AJ11: 0 | AK11: 0 | AL11: 0 | AM11: 0 | AN11: =SUM(AB11:AM11) -> 0
A12: ='Продукция и цена '!A11 -> Аренда системы: "Продвинутый" тариф | B12: 0 | C12: 0 | D12: 1 | E12: 1 | F12: 1 | G12: 2 | H12: 2 | I12: 2 | J12: 3 | K12: 3 | L12: 3 | M12: 4 | N12: =SUM(B12:M12) -> 22 | O12: 5 | P12: 6 | Q12: 7 | R12: 8 | S12: 9 | T12: 10 | U12: 11 | V12: 12 | W12: 13 | X12: 14 | Y12: 15 | Z12: 16 | AA12: =SUM(O12:Z12) -> 126 | AB12: 18 | AC12: 20 | AD12: 22 | AE12: 24 | AF12: 26 | AG12: 28 | AH12: 30 | AI12: 32 | AJ12: 34 | AK12: 36 | AL12: 38 | AM12: 40 | AN12: =SUM(AB12:AM12) -> 348
A13: ='Продукция и цена '!A12 -> Аренда системы: "Бизнес" тариф | B13: 0 | C13: 0 | D13: 0 | E13: 0 | F13: 0 | G13: 0 | H13: 0 | I13: 1 | J13: 1 | K13: 1 | L13: 1 | M13: 1 | N13: =SUM(B13:M13) -> 5 | O13: 1 | P13: 1 | Q13: 1 | R13: 2 | S13: 2 | T13: 2 | U13: 2 | V13: 3 | W13: 3 | X13: 3 | Y13: 3 | Z13: 4 | AA13: =SUM(O13:Z13) -> 27 | AB13: 4 | AC13: 5 | AD13: 5 | AE13: 5.6666667 | AF13: 6.1666667 | AG13: 6.6666667 | AH13: 7.1666667 | AI13: 7.6666667 | AJ13: 8.1666667 | AK13: 8.6666667 | AL13: 9.1666667 | AM13: 9.6666667 | AN13: =SUM(AB13:AM13) -> 83
A14: ='Продукция и цена '!A13 -> 0 | N14: =SUM(B14:M14) -> 0 | AA14: =SUM(O14:Z14) -> 0 | AN14: =SUM(AB14:AM14) -> 0
A15: ИТОГО | B15: =SUM(B5:B14) -> 5 | C15: =SUM(C5:C14) -> 3 | D15: =SUM(D5:D14) -> 9 | E15: =SUM(E5:E14) -> 9 | F15: =SUM(F5:F14) -> 12 | G15: =SUM(G5:G14) -> 16 | H15: =SUM(H5:H14) -> 18 | I15: =SUM(I5:I14) -> 20 | ... M15: =SUM(M5:M14) -> 32 | N15: =SUM(B15:M15) -> 205 | O15: =SUM(O5:O14) -> 46 | P15: =SUM(P5:P14) -> 52 | Q15: =SUM(Q5:Q14) -> 56 | R15: =SUM(R5:R14) -> 65.333333 | S15: =SUM(S5:S14) -> 69.833333 | T15: =SUM(T5:T14) -> 76.333333 | U15: =SUM(U5:U14) -> 83.833333 | V15: =SUM(V5:V14) -> 92.333333 | ... Z15: =SUM(Z5:Z14) -> 118.33333 | AA15: =SUM(O15:Z15) -> 977 | AB15: =SUM(AB5:AB14) -> 105 | AC15: =SUM(AC5:AC14) -> 114 | AD15: =SUM(AD5:AD14) -> 118 | AE15: =SUM(AE5:AE14) -> 128.66667 | AF15: =SUM(AF5:AF14) -> 136.16667 | AG15: =SUM(AG5:AG14) -> 145.66667 | AH15: =SUM(AH5:AH14) -> 156.16667 | AI15: =SUM(AI5:AI14) -> 164.66667 | ... AM15: =SUM(AM5:AM14) -> 196.66667 | AN15: =SUM(AB15:AM15) -> 1801
A18: Прогноз выручки (с учетом % потерь при сбыте), руб.
A19: Наименование продукта/услуги | B19: 1 год | N19: ИТОГО за 1 год | O19: =O3 -> 2 год | AA19: =AA3 -> ИТОГО за 2 год | AB19: =AB3 -> 3 год | AN19: =AN3 -> ИТОГО за 3 год
B20: =B4 -> 45809 | C20: =C4 -> 45839 | D20: =D4 -> 45870 | E20: =E4 -> 45901 | F20: =F4 -> 45931 | G20: =G4 -> 45962 | H20: =H4 -> 45992 | I20: =I4 -> 46023 | ... M20: =M4 -> 46143 | O20: =O4 -> 46174 | P20: =P4 -> 46204 | Q20: =Q4 -> 46235 | R20: =R4 -> 46266 | S20: =S4 -> 46296 | T20: =T4 -> 46327 | U20: =U4 -> 46357 | V20: =V4 -> 46388 | ... Z20: =Z4 -> 46508 | AB20: =AB4 -> 46539 | AC20: =AC4 -> 46569 | AD20: =AD4 -> 46600 | AE20: =AE4 -> 46631 | AF20: =AF4 -> 46661 | AG20: =AG4 -> 46692 | AH20: =AH4 -> 46722 | AI20: =AI4 -> 46753 | ... AM20: =AM4 -> 46874
A21: ='Продукция и цена '!A4 -> Аренда системы: "Базовый" тариф | B21: =(B5*'Продукция и цена '!$C$4)-((B5*'Продукция и цена '!$C$4)*'Вводные данные'!$C$5) -> 35000 | C21: =(C5*'Продукция и цена '!$C$4)-((C5*'Продукция и цена '!$C$4)*'Вводные данные'!$C$5) -> 70000 | D21: =(D5*'Продукция и цена '!$C$4)-((D5*'Продукция и цена '!$C$4)*'Вводные данные'!$C$5) -> 105000 | E21: =(E5*'Продукция и цена '!$C$4)-((E5*'Продукция и цена '!$C$4)*'Вводные данные'!$C$5) -> 140000 | F21: =(F5*'Продукция и цена '!$C$4)-((F5*'Продукция и цена '!$C$4)*'Вводные данные'!$C$5) -> 175000 | G21: =(G5*'Продукция и цена '!$C$4)-((G5*'Продукция и цена '!$C$4)*'Вводные данные'!$C$5) -> 245000 | H21: =(H5*'Продукция и цена '!$C$4)-((H5*'Продукция и цена '!$C$4)*'Вводные данные'!$C$5) -> 280000 | I21: =(I5*'Продукция и цена '!$C$4)-((I5*'Продукция и цена '!$C$4)*'Вводные данные'!$C$5) -> 280000 | ... M21: =(M5*'Продукция и цена '!$C$4)-((M5*'Продукция и цена '!$C$4)*'Вводные данные'!$C$5) -> 490000 | N21: =SUM(B21:M21) -> 3045000 | O21: =(O5*'Продукция и цена '!$D$4)-((O5*'Продукция и цена '!$D$4)*'Вводные данные'!$D$5) -> 603750 | P21: =(P5*'Продукция и цена '!$D$4)-((P5*'Продукция и цена '!$D$4)*'Вводные данные'!$D$5) -> 644000 | Q21: =(Q5*'Продукция и цена '!$D$4)-((Q5*'Продукция и цена '!$D$4)*'Вводные данные'!$D$5) -> 724500 | R21: =(R5*'Продукция и цена '!$D$4)-((R5*'Продукция и цена '!$D$4)*'Вводные данные'!$D$5) -> 778166.67 | S21: =(S5*'Продукция и цена '!$D$4)-((S5*'Продукция и цена '!$D$4)*'Вводные данные'!$D$5) -> 838541.67 | T21: =(T5*'Продукция и цена '!$D$4)-((T5*'Продукция и цена '!$D$4)*'Вводные данные'!$D$5) -> 898916.67 | U21: =(U5*'Продукция и цена '!$D$4)-((U5*'Продукция и цена '!$D$4)*'Вводные данные'!$D$5) -> 959291.67 | V21: =(V5*'Продукция и цена '!$D$4)-((V5*'Продукция и цена '!$D$4)*'Вводные данные'!$D$5) -> 1019666.7 | ... Z21: =(Z5*'Продукция и цена '!$D$4)-((Z5*'Продукция и цена '!$D$4)*'Вводные данные'!$D$5) -> 1261166.7 | AA21: =SUM(O21:Z21) -> 11149250 | AB21: =(AB5*'Продукция и цена '!$E$4)-((AB5*'Продукция и цена '!$E$4)*'Вводные данные'!$E$5) -> 277725 | AC21: =(AC5*'Продукция и цена '!$E$4)-((AC5*'Продукция и цена '!$E$4)*'Вводные данные'!$E$5) -> 277725 | AD21: =(AD5*'Продукция и цена '!$E$4)-((AD5*'Продукция и цена '!$E$4)*'Вводные данные'!$E$5) -> 277725 | AE21: =(AE5*'Продукция и цена '!$E$4)-((AE5*'Продукция и цена '!$E$4)*'Вводные данные'!$E$5) -> 277725 | AF21: =(AF5*'Продукция и цена '!$E$4)-((AF5*'Продукция и цена '!$E$4)*'Вводные данные'!$E$5) -> 277725 | AG21: =(AG5*'Продукция и цена '!$E$4)-((AG5*'Продукция и цена '!$E$4)*'Вводные данные'!$E$5) -> 277725 | AH21: =(AH5*'Продукция и цена '!$E$4)-((AH5*'Продукция и цена '!$E$4)*'Вводные данные'!$E$5) -> 324012.5 | AI21: =(AI5*'Продукция и цена '!$E$4)-((AI5*'Продукция и цена '!$E$4)*'Вводные данные'!$E$5) -> 324012.5 | ... AM21: =(AM5*'Продукция и цена '!$E$4)-((AM5*'Продукция и цена '!$E$4)*'Вводные данные'!$E$5) -> 324012.5 | AN21: =SUM(AB21:AM21) -> 3610425
A22: ='Продукция и цена '!A5 -> Поддержка системы | B22: =(B6*'Продукция и цена '!$C$5)-((B6*'Продукция и цена '!$C$5)*'Вводные данные'!$C$5) -> 30000 | C22: =(C6*'Продукция и цена '!$C$5)-((C6*'Продукция и цена '!$C$5)*'Вводные данные'!$C$5) -> 0 | D22: =(D6*'Продукция и цена '!$C$5)-((D6*'Продукция и цена '!$C$5)*'Вводные данные'!$C$5) -> 30000 | E22: =(E6*'Продукция и цена '!$C$5)-((E6*'Продукция и цена '!$C$5)*'Вводные данные'!$C$5) -> 30000 | F22: =(F6*'Продукция и цена '!$C$5)-((F6*'Продукция и цена '!$C$5)*'Вводные данные'!$C$5) -> 45000 | G22: =(G6*'Продукция и цена '!$C$5)-((G6*'Продукция и цена '!$C$5)*'Вводные данные'!$C$5) -> 60000 | H22: =(H6*'Продукция и цена '!$C$5)-((H6*'Продукция и цена '!$C$5)*'Вводные данные'!$C$5) -> 75000 | I22: =(I6*'Продукция и цена '!$C$5)-((I6*'Продукция и цена '!$C$5)*'Вводные данные'!$C$5) -> 90000 | ... M22: =(M6*'Продукция и цена '!$C$5)-((M6*'Продукция и цена '!$C$5)*'Вводные данные'!$C$5) -> 150000 | N22: =SUM(B22:M22) -> 885000 | O22: =(O6*'Продукция и цена '!$D$5)-((O6*'Продукция и цена '!$D$5)*'Вводные данные'!$D$5) -> 207000 | P22: =(P6*'Продукция и цена '!$D$5)-((P6*'Продукция и цена '!$D$5)*'Вводные данные'!$D$5) -> 258750 | Q22: =(Q6*'Продукция и цена '!$D$5)-((Q6*'Продукция и цена '!$D$5)*'Вводные данные'!$D$5) -> 293250 | R22: =(R6*'Продукция и цена '!$D$5)-((R6*'Продукция и цена '!$D$5)*'Вводные данные'!$D$5) -> 362250 | S22: =(S6*'Продукция и цена '!$D$5)-((S6*'Продукция и цена '!$D$5)*'Вводные данные'!$D$5) -> 396750 | T22: =(T6*'Продукция и цена '!$D$5)-((T6*'Продукция и цена '!$D$5)*'Вводные данные'!$D$5) -> 448500 | U22: =(U6*'Продукция и цена '!$D$5)-((U6*'Продукция и цена '!$D$5)*'Вводные данные'!$D$5) -> 483000 | V22: =(V6*'Продукция и цена '!$D$5)-((V6*'Продукция и цена '!$D$5)*'Вводные данные'!$D$5) -> 552000 | ... Z22: =(Z6*'Продукция и цена '!$D$5)-((Z6*'Продукция и цена '!$D$5)*'Вводные данные'!$D$5) -> 741750 | AA22: =SUM(O22:Z22) -> 5640750 | AB22: =(AB6*'Продукция и цена '!$E$5)-((AB6*'Продукция и цена '!$E$5)*'Вводные данные'!$E$5) -> 972037.5 | AC22: =(AC6*'Продукция и цена '!$E$5)-((AC6*'Продукция и цена '!$E$5)*'Вводные данные'!$E$5) -> 1091062.5 | AD22: =(AD6*'Продукция и цена '!$E$5)-((AD6*'Продукция и цена '!$E$5)*'Вводные данные'!$E$5) -> 1170412.5 | AE22: =(AE6*'Продукция и цена '!$E$5)-((AE6*'Продукция и цена '!$E$5)*'Вводные данные'!$E$5) -> 1289437.5 | AF22: =(AF6*'Продукция и цена '!$E$5)-((AF6*'Продукция и цена '!$E$5)*'Вводные данные'!$E$5) -> 1368787.5 | AG22: =(AG6*'Продукция и цена '!$E$5)-((AG6*'Продукция и цена '!$E$5)*'Вводные данные'!$E$5) -> 1487812.5 | AH22: =(AH6*'Продукция и цена '!$E$5)-((AH6*'Продукция и цена '!$E$5)*'Вводные данные'!$E$5) -> 1567162.5 | AI22: =(AI6*'Продукция и цена '!$E$5)-((AI6*'Продукция и цена '!$E$5)*'Вводные данные'!$E$5) -> 1686187.5 | ... AM22: =(AM6*'Продукция и цена '!$E$5)-((AM6*'Продукция и цена '!$E$5)*'Вводные данные'!$E$5) -> 2082937.5 | AN22: =SUM(AB22:AM22) -> 18329850
A23: ='Продукция и цена '!A6 -> Встроенная коммерция (доп. услуги) | B23: =(B7*'Продукция и цена '!$C$6)-((B7*'Продукция и цена '!$C$6)*'Вводные данные'!$C$5) -> 9000 | C23: =(C7*'Продукция и цена '!$C$6)-((C7*'Продукция и цена '!$C$6)*'Вводные данные'!$C$5) -> 9000 | D23: =(D7*'Продукция и цена '!$C$6)-((D7*'Продукция и цена '!$C$6)*'Вводные данные'!$C$5) -> 9000 | E23: =(E7*'Продукция и цена '!$C$6)-((E7*'Продукция и цена '!$C$6)*'Вводные данные'!$C$5) -> 9000 | F23: =(F7*'Продукция и цена '!$C$6)-((F7*'Продукция и цена '!$C$6)*'Вводные данные'!$C$5) -> 9000 | G23: =(G7*'Продукция и цена '!$C$6)-((G7*'Продукция и цена '!$C$6)*'Вводные данные'!$C$5) -> 9000 | H23: =(H7*'Продукция и цена '!$C$6)-((H7*'Продукция и цена '!$C$6)*'Вводные данные'!$C$5) -> 9000 | I23: =(I7*'Продукция и цена '!$C$6)-((I7*'Продукция и цена '!$C$6)*'Вводные данные'!$C$5) -> 9000 | ... M23: =(M7*'Продукция и цена '!$C$6)-((M7*'Продукция и цена '!$C$6)*'Вводные данные'!$C$5) -> 9000 | N23: =SUM(B23:M23) -> 108000 | O23: =(O7*'Продукция и цена '!$D$6)-((O7*'Продукция и цена '!$D$6)*'Вводные данные'!$D$5) -> 103500 | P23: =(P7*'Продукция и цена '!$D$6)-((P7*'Продукция и цена '!$D$6)*'Вводные данные'!$D$5) -> 103500 | Q23: =(Q7*'Продукция и цена '!$D$6)-((Q7*'Продукция и цена '!$D$6)*'Вводные данные'!$D$5) -> 103500 | R23: =(R7*'Продукция и цена '!$D$6)-((R7*'Продукция и цена '!$D$6)*'Вводные данные'!$D$5) -> 103500 | S23: =(S7*'Продукция и цена '!$D$6)-((S7*'Продукция и цена '!$D$6)*'Вводные данные'!$D$5) -> 124200 | T23: =(T7*'Продукция и цена '!$D$6)-((T7*'Продукция и цена '!$D$6)*'Вводные данные'!$D$5) -> 124200 | U23: =(U7*'Продукция и цена '!$D$6)-((U7*'Продукция и цена '!$D$6)*'Вводные данные'!$D$5) -> 155250 | V23: =(V7*'Продукция и цена '!$D$6)-((V7*'Продукция и цена '!$D$6)*'Вводные данные'!$D$5) -> 144900 | ... Z23: =(Z7*'Продукция и цена '!$D$6)-((Z7*'Продукция и цена '!$D$6)*'Вводные данные'!$D$5) -> 186300 | AA23: =SUM(O23:Z23) -> 1707750 | AB23: =(AB7*'Продукция и цена '!$E$6)-((AB7*'Продукция и цена '!$E$6)*'Вводные данные'!$E$5) -> 238050 | AC23: =(AC7*'Продукция и цена '!$E$6)-((AC7*'Продукция и цена '!$E$6)*'Вводные данные'!$E$5) -> 238050 | AD23: =(AD7*'Продукция и цена '!$E$6)-((AD7*'Продукция и цена '!$E$6)*'Вводные данные'!$E$5) -> 238050 | AE23: =(AE7*'Продукция и цена '!$E$6)-((AE7*'Продукция и цена '!$E$6)*'Вводные данные'!$E$5) -> 238050 | AF23: =(AF7*'Продукция и цена '!$E$6)-((AF7*'Продукция и цена '!$E$6)*'Вводные данные'!$E$5) -> 273757.5 | AG23: =(AG7*'Продукция и цена '!$E$6)-((AG7*'Продукция и цена '!$E$6)*'Вводные данные'!$E$5) -> 273757.5 | AH23: =(AH7*'Продукция и цена '!$E$6)-((AH7*'Продукция и цена '!$E$6)*'Вводные данные'!$E$5) -> 321367.5 | AI23: =(AI7*'Продукция и цена '!$E$6)-((AI7*'Продукция и цена '!$E$6)*'Вводные данные'!$E$5) -> 297562.5 | ... AM23: =(AM7*'Продукция и цена '!$E$6)-((AM7*'Продукция и цена '!$E$6)*'Вводные данные'!$E$5) -> 321367.5 | AN23: =SUM(AB23:AM23) -> 3380310
A24: ='Продукция и цена '!A7 -> Установка и настройка системы, онбординг | B24: =(B8*'Продукция и цена '!$C$7)-((B8*'Продукция и цена '!$C$7)*'Вводные данные'!$C$5) -> 250000 | C24: =(C8*'Продукция и цена '!$C$7)-((C8*'Продукция и цена '!$C$7)*'Вводные данные'!$C$5) -> 0 | D24: =(D8*'Продукция и цена '!$C$7)-((D8*'Продукция и цена '!$C$7)*'Вводные данные'!$C$5) -> 500000 | E24: =(E8*'Продукция и цена '!$C$7)-((E8*'Продукция и цена '!$C$7)*'Вводные данные'!$C$5) -> 0 | F24: =(F8*'Продукция и цена '!$C$7)-((F8*'Продукция и цена '!$C$7)*'Вводные данные'!$C$5) -> 250000 | G24: =(G8*'Продукция и цена '!$C$7)-((G8*'Продукция и цена '!$C$7)*'Вводные данные'!$C$5) -> 250000 | H24: =(H8*'Продукция и цена '!$C$7)-((H8*'Продукция и цена '!$C$7)*'Вводные данные'!$C$5) -> 250000 | I24: =(I8*'Продукция и цена '!$C$7)-((I8*'Продукция и цена '!$C$7)*'Вводные данные'!$C$5) -> 250000 | ... M24: =(M8*'Продукция и цена '!$C$7)-((M8*'Продукция и цена '!$C$7)*'Вводные данные'!$C$5) -> 250000 | N24: =SUM(B24:M24) -> 2750000 | O24: =(O8*'Продукция и цена '!$D$7)-((O8*'Продукция и цена '!$D$7)*'Вводные данные'!$D$5) -> 575000 | P24: =(P8*'Продукция и цена '!$D$7)-((P8*'Продукция и цена '!$D$7)*'Вводные данные'!$D$5) -> 862500 | Q24: =(Q8*'Продукция и цена '!$D$7)-((Q8*'Продукция и цена '!$D$7)*'Вводные данные'!$D$5) -> 575000 | R24: =(R8*'Продукция и цена '!$D$7)-((R8*'Продукция и цена '!$D$7)*'Вводные данные'!$D$5) -> 1150000 | S24: =(S8*'Продукция и цена '!$D$7)-((S8*'Продукция и цена '!$D$7)*'Вводные данные'!$D$5) -> 575000 | T24: =(T8*'Продукция и цена '!$D$7)-((T8*'Продукция и цена '!$D$7)*'Вводные данные'!$D$5) -> 862500 | U24: =(U8*'Продукция и цена '!$D$7)-((U8*'Продукция и цена '!$D$7)*'Вводные данные'!$D$5) -> 575000 | V24: =(V8*'Продукция и цена '!$D$7)-((V8*'Продукция и цена '!$D$7)*'Вводные данные'!$D$5) -> 1150000 | ... Z24: =(Z8*'Продукция и цена '!$D$7)-((Z8*'Продукция и цена '!$D$7)*'Вводные данные'!$D$5) -> 1150000 | AA24: =SUM(O24:Z24) -> 9487500 | AB24: =(AB8*'Продукция и цена '!$E$7)-((AB8*'Продукция и цена '!$E$7)*'Вводные данные'!$E$5) -> 1983750 | AC24: =(AC8*'Продукция и цена '!$E$7)-((AC8*'Продукция и цена '!$E$7)*'Вводные данные'!$E$5) -> 1983750 | AD24: =(AD8*'Продукция и цена '!$E$7)-((AD8*'Продукция и цена '!$E$7)*'Вводные данные'!$E$5) -> 1322500 | AE24: =(AE8*'Продукция и цена '!$E$7)-((AE8*'Продукция и цена '!$E$7)*'Вводные данные'!$E$5) -> 1983750 | AF24: =(AF8*'Продукция и цена '!$E$7)-((AF8*'Продукция и цена '!$E$7)*'Вводные данные'!$E$5) -> 1322500 | AG24: =(AG8*'Продукция и цена '!$E$7)-((AG8*'Продукция и цена '!$E$7)*'Вводные данные'!$E$5) -> 1983750 | AH24: =(AH8*'Продукция и цена '!$E$7)-((AH8*'Продукция и цена '!$E$7)*'Вводные данные'!$E$5) -> 1322500 | AI24: =(AI8*'Продукция и цена '!$E$7)-((AI8*'Продукция и цена '!$E$7)*'Вводные данные'!$E$5) -> 1983750 | ... AM24: =(AM8*'Продукция и цена '!$E$7)-((AM8*'Продукция и цена '!$E$7)*'Вводные данные'!$E$5) -> 1983750 | AN24: =SUM(AB24:AM24) -> 20498750
A25: ='Продукция и цена '!A8 -> Реклама/партнёрства | B25: =(B9*'Продукция и цена '!$C$8)-((B9*'Продукция и цена '!$C$8)*'Вводные данные'!$C$5) -> 0 | C25: =(C9*'Продукция и цена '!$C$8)-((C9*'Продукция и цена '!$C$8)*'Вводные данные'!$C$5) -> 0 | D25: =(D9*'Продукция и цена '!$C$8)-((D9*'Продукция и цена '!$C$8)*'Вводные данные'!$C$5) -> 0 | E25: =(E9*'Продукция и цена '!$C$8)-((E9*'Продукция и цена '!$C$8)*'Вводные данные'!$C$5) -> 20000 | F25: =(F9*'Продукция и цена '!$C$8)-((F9*'Продукция и цена '!$C$8)*'Вводные данные'!$C$5) -> 20000 | G25: =(G9*'Продукция и цена '!$C$8)-((G9*'Продукция и цена '!$C$8)*'Вводные данные'!$C$5) -> 20000 | H25: =(H9*'Продукция и цена '!$C$8)-((H9*'Продукция и цена '!$C$8)*'Вводные данные'!$C$5) -> 20000 | I25: =(I9*'Продукция и цена '!$C$8)-((I9*'Продукция и цена '!$C$8)*'Вводные данные'!$C$5) -> 20000 | ... M25: =(M9*'Продукция и цена '!$C$8)-((M9*'Продукция и цена '!$C$8)*'Вводные данные'!$C$5) -> 20000 | N25: =SUM(B25:M25) -> 180000 | O25: =(O9*'Продукция и цена '!$D$8)-((O9*'Продукция и цена '!$D$8)*'Вводные данные'!$D$5) -> 23000 | P25: =(P9*'Продукция и цена '!$D$8)-((P9*'Продукция и цена '!$D$8)*'Вводные данные'!$D$5) -> 23000 | Q25: =(Q9*'Продукция и цена '!$D$8)-((Q9*'Продукция и цена '!$D$8)*'Вводные данные'!$D$5) -> 23000 | R25: =(R9*'Продукция и цена '!$D$8)-((R9*'Продукция и цена '!$D$8)*'Вводные данные'!$D$5) -> 23000 | S25: =(S9*'Продукция и цена '!$D$8)-((S9*'Продукция и цена '!$D$8)*'Вводные данные'!$D$5) -> 23000 | T25: =(T9*'Продукция и цена '!$D$8)-((T9*'Продукция и цена '!$D$8)*'Вводные данные'!$D$5) -> 23000 | U25: =(U9*'Продукция и цена '!$D$8)-((U9*'Продукция и цена '!$D$8)*'Вводные данные'!$D$5) -> 46000 | V25: =(V9*'Продукция и цена '!$D$8)-((V9*'Продукция и цена '!$D$8)*'Вводные данные'!$D$5) -> 46000 | ... Z25: =(Z9*'Продукция и цена '!$D$8)-((Z9*'Продукция и цена '!$D$8)*'Вводные данные'!$D$5) -> 46000 | AA25: =SUM(O25:Z25) -> 368000 | AB25: =(AB9*'Продукция и цена '!$E$8)-((AB9*'Продукция и цена '!$E$8)*'Вводные данные'!$E$5) -> 52900 | AC25: =(AC9*'Продукция и цена '!$E$8)-((AC9*'Продукция и цена '!$E$8)*'Вводные данные'!$E$5) -> 52900 | AD25: =(AD9*'Продукция и цена '!$E$8)-((AD9*'Продукция и цена '!$E$8)*'Вводные данные'!$E$5) -> 52900 | AE25: =(AE9*'Продукция и цена '!$E$8)-((AE9*'Продукция и цена '!$E$8)*'Вводные данные'!$E$5) -> 52900 | AF25: =(AF9*'Продукция и цена '!$E$8)-((AF9*'Продукция и цена '!$E$8)*'Вводные данные'!$E$5) -> 52900 | AG25: =(AG9*'Продукция и цена '!$E$8)-((AG9*'Продукция и цена '!$E$8)*'Вводные данные'!$E$5) -> 26450 | AH25: =(AH9*'Продукция и цена '!$E$8)-((AH9*'Продукция и цена '!$E$8)*'Вводные данные'!$E$5) -> 52900 | AI25: =(AI9*'Продукция и цена '!$E$8)-((AI9*'Продукция и цена '!$E$8)*'Вводные данные'!$E$5) -> 52900 | ... AM25: =(AM9*'Продукция и цена '!$E$8)-((AM9*'Продукция и цена '!$E$8)*'Вводные данные'!$E$5) -> 52900 | AN25: =SUM(AB25:AM25) -> 581900
A26: ='Продукция и цена '!A9 -> 0 | B26: =(B10*'Продукция и цена '!$C$9)-((B10*'Продукция и цена '!$C$9)*'Вводные данные'!$C$5) -> 0 | C26: =(C10*'Продукция и цена '!$C$9)-((C10*'Продукция и цена '!$C$9)*'Вводные данные'!$C$5) -> 0 | D26: =(D10*'Продукция и цена '!$C$9)-((D10*'Продукция и цена '!$C$9)*'Вводные данные'!$C$5) -> 0 | E26: =(E10*'Продукция и цена '!$C$9)-((E10*'Продукция и цена '!$C$9)*'Вводные данные'!$C$5) -> 0 | F26: =(F10*'Продукция и цена '!$C$9)-((F10*'Продукция и цена '!$C$9)*'Вводные данные'!$C$5) -> 0 | G26: =(G10*'Продукция и цена '!$C$9)-((G10*'Продукция и цена '!$C$9)*'Вводные данные'!$C$5) -> 0 | H26: =(H10*'Продукция и цена '!$C$9)-((H10*'Продукция и цена '!$C$9)*'Вводные данные'!$C$5) -> 0 | I26: =(I10*'Продукция и цена '!$C$9)-((I10*'Продукция и цена '!$C$9)*'Вводные данные'!$C$5) -> 0 | ... M26: =(M10*'Продукция и цена '!$C$9)-((M10*'Продукция и цена '!$C$9)*'Вводные данные'!$C$5) -> 0 | N26: =SUM(B26:M26) -> 0 | O26: =(O10*'Продукция и цена '!$D$9)-((O10*'Продукция и цена '!$D$9)*'Вводные данные'!$D$5) -> 0 | P26: =(P10*'Продукция и цена '!$D$9)-((P10*'Продукция и цена '!$D$9)*'Вводные данные'!$D$5) -> 0 | Q26: =(Q10*'Продукция и цена '!$D$9)-((Q10*'Продукция и цена '!$D$9)*'Вводные данные'!$D$5) -> 0 | R26: =(R10*'Продукция и цена '!$D$9)-((R10*'Продукция и цена '!$D$9)*'Вводные данные'!$D$5) -> 0 | S26: =(S10*'Продукция и цена '!$D$9)-((S10*'Продукция и цена '!$D$9)*'Вводные данные'!$D$5) -> 0 | T26: =(T10*'Продукция и цена '!$D$9)-((T10*'Продукция и цена '!$D$9)*'Вводные данные'!$D$5) -> 0 | U26: =(U10*'Продукция и цена '!$D$9)-((U10*'Продукция и цена '!$D$9)*'Вводные данные'!$D$5) -> 0 | V26: =(V10*'Продукция и цена '!$D$9)-((V10*'Продукция и цена '!$D$9)*'Вводные данные'!$D$5) -> 0 | ... Z26: =(Z10*'Продукция и цена '!$D$9)-((Z10*'Продукция и цена '!$D$9)*'Вводные данные'!$D$5) -> 0 | AA26: =SUM(O26:Z26) -> 0 | AB26: =(AB10*'Продукция и цена '!$E$9)-((AB10*'Продукция и цена '!$E$9)*'Вводные данные'!$E$5) -> 0 | AC26: =(AC10*'Продукция и цена '!$E$9)-((AC10*'Продукция и цена '!$E$9)*'Вводные данные'!$E$5) -> 0 | AD26: =(AD10*'Продукция и цена '!$E$9)-((AD10*'Продукция и цена '!$E$9)*'Вводные данные'!$E$5) -> 0 | AE26: =(AE10*'Продукция и цена '!$E$9)-((AE10*'Продукция и цена '!$E$9)*'Вводные данные'!$E$5) -> 0 | AF26: =(AF10*'Продукция и цена '!$E$9)-((AF10*'Продукция и цена '!$E$9)*'Вводные данные'!$E$5) -> 0 | AG26: =(AG10*'Продукция и цена '!$E$9)-((AG10*'Продукция и цена '!$E$9)*'Вводные данные'!$E$5) -> 0 | AH26: =(AH10*'Продукция и цена '!$E$9)-((AH10*'Продукция и цена '!$E$9)*'Вводные данные'!$E$5) -> 0 | AI26: =(AI10*'Продукция и цена '!$E$9)-((AI10*'Продукция и цена '!$E$9)*'Вводные данные'!$E$5) -> 0 | ... AM26: =(AM10*'Продукция и цена '!$E$9)-((AM10*'Продукция и цена '!$E$9)*'Вводные данные'!$E$5) -> 0 | AN26: =SUM(AB26:AM26) -> 0
A27: ='Продукция и цена '!A10 -> 0 | B27: =(B11*'Продукция и цена '!$C$10)-((B11*'Продукция и цена '!$C$10)*'Вводные данные'!$C$5) -> 0 | C27: =(C11*'Продукция и цена '!$C$10)-((C11*'Продукция и цена '!$C$10)*'Вводные данные'!$C$5) -> 0 | D27: =(D11*'Продукция и цена '!$C$10)-((D11*'Продукция и цена '!$C$10)*'Вводные данные'!$C$5) -> 0 | E27: =(E11*'Продукция и цена '!$C$10)-((E11*'Продукция и цена '!$C$10)*'Вводные данные'!$C$5) -> 0 | F27: =(F11*'Продукция и цена '!$C$10)-((F11*'Продукция и цена '!$C$10)*'Вводные данные'!$C$5) -> 0 | G27: =(G11*'Продукция и цена '!$C$10)-((G11*'Продукция и цена '!$C$10)*'Вводные данные'!$C$5) -> 0 | H27: =(H11*'Продукция и цена '!$C$10)-((H11*'Продукция и цена '!$C$10)*'Вводные данные'!$C$5) -> 0 | I27: =(I11*'Продукция и цена '!$C$10)-((I11*'Продукция и цена '!$C$10)*'Вводные данные'!$C$5) -> 0 | ... M27: =(M11*'Продукция и цена '!$C$10)-((M11*'Продукция и цена '!$C$10)*'Вводные данные'!$C$5) -> 0 | N27: =SUM(B27:M27) -> 0 | O27: =(O11*'Продукция и цена '!$D$10)-((O11*'Продукция и цена '!$D$10)*'Вводные данные'!$D$5) -> 0 | P27: =(P11*'Продукция и цена '!$D$10)-((P11*'Продукция и цена '!$D$10)*'Вводные данные'!$D$5) -> 0 | Q27: =(Q11*'Продукция и цена '!$D$10)-((Q11*'Продукция и цена '!$D$10)*'Вводные данные'!$D$5) -> 0 | R27: =(R11*'Продукция и цена '!$D$10)-((R11*'Продукция и цена '!$D$10)*'Вводные данные'!$D$5) -> 0 | S27: =(S11*'Продукция и цена '!$D$10)-((S11*'Продукция и цена '!$D$10)*'Вводные данные'!$D$5) -> 0 | T27: =(T11*'Продукция и цена '!$D$10)-((T11*'Продукция и цена '!$D$10)*'Вводные данные'!$D$5) -> 0 | U27: =(U11*'Продукция и цена '!$D$10)-((U11*'Продукция и цена '!$D$10)*'Вводные данные'!$D$5) -> 0 | V27: =(V11*'Продукция и цена '!$D$10)-((V11*'Продукция и цена '!$D$10)*'Вводные данные'!$D$5) -> 0 | ... Z27: =(Z11*'Продукция и цена '!$D$10)-((Z11*'Продукция и цена '!$D$10)*'Вводные данные'!$D$5) -> 0 | AA27: =SUM(O27:Z27) -> 0 | AB27: =(AB11*'Продукция и цена '!$E$10)-((AB11*'Продукция и цена '!$E$10)*'Вводные данные'!$E$5) -> 0 | AC27: =(AC11*'Продукция и цена '!$E$10)-((AC11*'Продукция и цена '!$E$10)*'Вводные данные'!$E$5) -> 0 | AD27: =(AD11*'Продукция и цена '!$E$10)-((AD11*'Продукция и цена '!$E$10)*'Вводные данные'!$E$5) -> 0 | AE27: =(AE11*'Продукция и цена '!$E$10)-((AE11*'Продукция и цена '!$E$10)*'Вводные данные'!$E$5) -> 0 | AF27: =(AF11*'Продукция и цена '!$E$10)-((AF11*'Продукция и цена '!$E$10)*'Вводные данные'!$E$5) -> 0 | AG27: =(AG11*'Продукция и цена '!$E$10)-((AG11*'Продукция и цена '!$E$10)*'Вводные данные'!$E$5) -> 0 | AH27: =(AH11*'Продукция и цена '!$E$10)-((AH11*'Продукция и цена '!$E$10)*'Вводные данные'!$E$5) -> 0 | AI27: =(AI11*'Продукция и цена '!$E$10)-((AI11*'Продукция и цена '!$E$10)*'Вводные данные'!$E$5) -> 0 | ... AM27: =(AM11*'Продукция и цена '!$E$10)-((AM11*'Продукция и цена '!$E$10)*'Вводные данные'!$E$5) -> 0 | AN27: =SUM(AB27:AM27) -> 0
A28: ='Продукция и цена '!A11 -> Аренда системы: "Продвинутый" тариф | B28: =(B12*'Продукция и цена '!$C$11)-((B12*'Продукция и цена '!$C$11)*'Вводные данные'!$C$5) -> 0 | C28: =(C12*'Продукция и цена '!$C$11)-((C12*'Продукция и цена '!$C$11)*'Вводные данные'!$C$5) -> 0 | D28: =(D12*'Продукция и цена '!$C$11)-((D12*'Продукция и цена '!$C$11)*'Вводные данные'!$C$5) -> 65000 | E28: =(E12*'Продукция и цена '!$C$11)-((E12*'Продукция и цена '!$C$11)*'Вводные данные'!$C$5) -> 65000 | F28: =(F12*'Продукция и цена '!$C$11)-((F12*'Продукция и цена '!$C$11)*'Вводные данные'!$C$5) -> 65000 | G28: =(G12*'Продукция и цена '!$C$11)-((G12*'Продукция и цена '!$C$11)*'Вводные данные'!$C$5) -> 130000 | H28: =(H12*'Продукция и цена '!$C$11)-((H12*'Продукция и цена '!$C$11)*'Вводные данные'!$C$5) -> 130000 | I28: =(I12*'Продукция и цена '!$C$11)-((I12*'Продукция и цена '!$C$11)*'Вводные данные'!$C$5) -> 130000 | ... M28: =(M12*'Продукция и цена '!$C$11)-((M12*'Продукция и цена '!$C$11)*'Вводные данные'!$C$5) -> 260000 | N28: =SUM(B28:M28) -> 1430000 | O28: =(O12*'Продукция и цена '!$D$11)-((O12*'Продукция и цена '!$D$11)*'Вводные данные'!$D$5) -> 373750 | P28: =(P12*'Продукция и цена '!$D$11)-((P12*'Продукция и цена '!$D$11)*'Вводные данные'!$D$5) -> 448500 | Q28: =(Q12*'Продукция и цена '!$D$11)-((Q12*'Продукция и цена '!$D$11)*'Вводные данные'!$D$5) -> 523250 | R28: =(R12*'Продукция и цена '!$D$11)-((R12*'Продукция и цена '!$D$11)*'Вводные данные'!$D$5) -> 598000 | S28: =(S12*'Продукция и цена '!$D$11)-((S12*'Продукция и цена '!$D$11)*'Вводные данные'!$D$5) -> 672750 | T28: =(T12*'Продукция и цена '!$D$11)-((T12*'Продукция и цена '!$D$11)*'Вводные данные'!$D$5) -> 747500 | U28: =(U12*'Продукция и цена '!$D$11)-((U12*'Продукция и цена '!$D$11)*'Вводные данные'!$D$5) -> 822250 | V28: =(V12*'Продукция и цена '!$D$11)-((V12*'Продукция и цена '!$D$11)*'Вводные данные'!$D$5) -> 897000 | ... Z28: =(Z12*'Продукция и цена '!$D$11)-((Z12*'Продукция и цена '!$D$11)*'Вводные данные'!$D$5) -> 1196000 | AA28: =SUM(O28:Z28) -> 9418500 | AB28: =(AB12*'Продукция и цена '!$E$11)-((AB12*'Продукция и цена '!$E$11)*'Вводные данные'!$E$5) -> 1547325 | AC28: =(AC12*'Продукция и цена '!$E$11)-((AC12*'Продукция и цена '!$E$11)*'Вводные данные'!$E$5) -> 1719250 | AD28: =(AD12*'Продукция и цена '!$E$11)-((AD12*'Продукция и цена '!$E$11)*'Вводные данные'!$E$5) -> 1891175 | AE28: =(AE12*'Продукция и цена '!$E$11)-((AE12*'Продукция и цена '!$E$11)*'Вводные данные'!$E$5) -> 2063100 | AF28: =(AF12*'Продукция и цена '!$E$11)-((AF12*'Продукция и цена '!$E$11)*'Вводные данные'!$E$5) -> 2235025 | AG28: =(AG12*'Продукция и цена '!$E$11)-((AG12*'Продукция и цена '!$E$11)*'Вводные данные'!$E$5) -> 2406950 | AH28: =(AH12*'Продукция и цена '!$E$11)-((AH12*'Продукция и цена '!$E$11)*'Вводные данные'!$E$5) -> 2578875 | AI28: =(AI12*'Продукция и цена '!$E$11)-((AI12*'Продукция и цена '!$E$11)*'Вводные данные'!$E$5) -> 2750800 | ... AM28: =(AM12*'Продукция и цена '!$E$11)-((AM12*'Продукция и цена '!$E$11)*'Вводные данные'!$E$5) -> 3438500 | AN28: =SUM(AB28:AM28) -> 29914950
A29: ='Продукция и цена '!A12 -> Аренда системы: "Бизнес" тариф | B29: =(B13*'Продукция и цена '!$C$12)-((B13*'Продукция и цена '!$C$12)*'Вводные данные'!$C$5) -> 0 | C29: =(C13*'Продукция и цена '!$C$12)-((C13*'Продукция и цена '!$C$12)*'Вводные данные'!$C$5) -> 0 | D29: =(D13*'Продукция и цена '!$C$12)-((D13*'Продукция и цена '!$C$12)*'Вводные данные'!$C$5) -> 0 | E29: =(E13*'Продукция и цена '!$C$12)-((E13*'Продукция и цена '!$C$12)*'Вводные данные'!$C$5) -> 0 | F29: =(F13*'Продукция и цена '!$C$12)-((F13*'Продукция и цена '!$C$12)*'Вводные данные'!$C$5) -> 0 | G29: =(G13*'Продукция и цена '!$C$12)-((G13*'Продукция и цена '!$C$12)*'Вводные данные'!$C$5) -> 0 | H29: =(H13*'Продукция и цена '!$C$12)-((H13*'Продукция и цена '!$C$12)*'Вводные данные'!$C$5) -> 0 | I29: =(I13*'Продукция и цена '!$C$12)-((I13*'Продукция и цена '!$C$12)*'Вводные данные'!$C$5) -> 12000 | ... M29: =(M13*'Продукция и цена '!$C$12)-((M13*'Продукция и цена '!$C$12)*'Вводные данные'!$C$5) -> 12000 | N29: =SUM(B29:M29) -> 60000 | O29: =(O13*'Продукция и цена '!$D$12)-((O13*'Продукция и цена '!$D$12)*'Вводные данные'!$D$5) -> 13800 | P29: =(P13*'Продукция и цена '!$D$12)-((P13*'Продукция и цена '!$D$12)*'Вводные данные'!$D$5) -> 13800 | Q29: =(Q13*'Продукция и цена '!$D$12)-((Q13*'Продукция и цена '!$D$12)*'Вводные данные'!$D$5) -> 13800 | R29: =(R13*'Продукция и цена '!$D$12)-((R13*'Продукция и цена '!$D$12)*'Вводные данные'!$D$5) -> 27600 | S29: =(S13*'Продукция и цена '!$D$12)-((S13*'Продукция и цена '!$D$12)*'Вводные данные'!$D$5) -> 27600 | T29: =(T13*'Продукция и цена '!$D$12)-((T13*'Продукция и цена '!$D$12)*'Вводные данные'!$D$5) -> 27600 | U29: =(U13*'Продукция и цена '!$D$12)-((U13*'Продукция и цена '!$D$12)*'Вводные данные'!$D$5) -> 27600 | V29: =(V13*'Продукция и цена '!$D$12)-((V13*'Продукция и цена '!$D$12)*'Вводные данные'!$D$5) -> 41400 | ... Z29: =(Z13*'Продукция и цена '!$D$12)-((Z13*'Продукция и цена '!$D$12)*'Вводные данные'!$D$5) -> 55200 | AA29: =SUM(O29:Z29) -> 372600 | AB29: =(AB13*'Продукция и цена '!$E$12)-((AB13*'Продукция и цена '!$E$12)*'Вводные данные'!$E$5) -> 63480 | AC29: =(AC13*'Продукция и цена '!$E$12)-((AC13*'Продукция и цена '!$E$12)*'Вводные данные'!$E$5) -> 79350 | AD29: =(AD13*'Продукция и цена '!$E$12)-((AD13*'Продукция и цена '!$E$12)*'Вводные данные'!$E$5) -> 79350 | AE29: =(AE13*'Продукция и цена '!$E$12)-((AE13*'Продукция и цена '!$E$12)*'Вводные данные'!$E$5) -> 89930 | AF29: =(AF13*'Продукция и цена '!$E$12)-((AF13*'Продукция и цена '!$E$12)*'Вводные данные'!$E$5) -> 97865 | AG29: =(AG13*'Продукция и цена '!$E$12)-((AG13*'Продукция и цена '!$E$12)*'Вводные данные'!$E$5) -> 105800 | AH29: =(AH13*'Продукция и цена '!$E$12)-((AH13*'Продукция и цена '!$E$12)*'Вводные данные'!$E$5) -> 113735 | AI29: =(AI13*'Продукция и цена '!$E$12)-((AI13*'Продукция и цена '!$E$12)*'Вводные данные'!$E$5) -> 121670 | ... AM29: =(AM13*'Продукция и цена '!$E$12)-((AM13*'Продукция и цена '!$E$12)*'Вводные данные'!$E$5) -> 153410 | AN29: =SUM(AB29:AM29) -> 1317210
A30: ='Продукция и цена '!A13 -> 0 | B30: =(B14*'Продукция и цена '!$C$13)-((B14*'Продукция и цена '!$C$13)*'Вводные данные'!$C$5) -> 0 | C30: =(C14*'Продукция и цена '!$C$13)-((C14*'Продукция и цена '!$C$13)*'Вводные данные'!$C$5) -> 0 | D30: =(D14*'Продукция и цена '!$C$13)-((D14*'Продукция и цена '!$C$13)*'Вводные данные'!$C$5) -> 0 | E30: =(E14*'Продукция и цена '!$C$13)-((E14*'Продукция и цена '!$C$13)*'Вводные данные'!$C$5) -> 0 | F30: =(F14*'Продукция и цена '!$C$13)-((F14*'Продукция и цена '!$C$13)*'Вводные данные'!$C$5) -> 0 | G30: =(G14*'Продукция и цена '!$C$13)-((G14*'Продукция и цена '!$C$13)*'Вводные данные'!$C$5) -> 0 | H30: =(H14*'Продукция и цена '!$C$13)-((H14*'Продукция и цена '!$C$13)*'Вводные данные'!$C$5) -> 0 | I30: =(I14*'Продукция и цена '!$C$13)-((I14*'Продукция и цена '!$C$13)*'Вводные данные'!$C$5) -> 0 | ... M30: =(M14*'Продукция и цена '!$C$13)-((M14*'Продукция и цена '!$C$13)*'Вводные данные'!$C$5) -> 0 | N30: =SUM(B30:M30) -> 0 | O30: =(O14*'Продукция и цена '!$D$13)-((O14*'Продукция и цена '!$D$13)*'Вводные данные'!$D$5) -> 0 | P30: =(P14*'Продукция и цена '!$D$13)-((P14*'Продукция и цена '!$D$13)*'Вводные данные'!$D$5) -> 0 | Q30: =(Q14*'Продукция и цена '!$D$13)-((Q14*'Продукция и цена '!$D$13)*'Вводные данные'!$D$5) -> 0 | R30: =(R14*'Продукция и цена '!$D$13)-((R14*'Продукция и цена '!$D$13)*'Вводные данные'!$D$5) -> 0 | S30: =(S14*'Продукция и цена '!$D$13)-((S14*'Продукция и цена '!$D$13)*'Вводные данные'!$D$5) -> 0 | T30: =(T14*'Продукция и цена '!$D$13)-((T14*'Продукция и цена '!$D$13)*'Вводные данные'!$D$5) -> 0 | U30: =(U14*'Продукция и цена '!$D$13)-((U14*'Продукция и цена '!$D$13)*'Вводные данные'!$D$5) -> 0 | V30: =(V14*'Продукция и цена '!$D$13)-((V14*'Продукция и цена '!$D$13)*'Вводные данные'!$D$5) -> 0 | ... Z30: =(Z14*'Продукция и цена '!$D$13)-((Z14*'Продукция и цена '!$D$13)*'Вводные данные'!$D$5) -> 0 | AA30: =SUM(O30:Z30) -> 0 | AB30: =(AB14*'Продукция и цена '!$E$13)-((AB14*'Продукция и цена '!$E$13)*'Вводные данные'!$E$5) -> 0 | AC30: =(AC14*'Продукция и цена '!$E$13)-((AC14*'Продукция и цена '!$E$13)*'Вводные данные'!$E$5) -> 0 | AD30: =(AD14*'Продукция и цена '!$E$13)-((AD14*'Продукция и цена '!$E$13)*'Вводные данные'!$E$5) -> 0 | AE30: =(AE14*'Продукция и цена '!$E$13)-((AE14*'Продукция и цена '!$E$13)*'Вводные данные'!$E$5) -> 0 | AF30: =(AF14*'Продукция и цена '!$E$13)-((AF14*'Продукция и цена '!$E$13)*'Вводные данные'!$E$5) -> 0 | AG30: =(AG14*'Продукция и цена '!$E$13)-((AG14*'Продукция и цена '!$E$13)*'Вводные данные'!$E$5) -> 0 | AH30: =(AH14*'Продукция и цена '!$E$13)-((AH14*'Продукция и цена '!$E$13)*'Вводные данные'!$E$5) -> 0 | AI30: =(AI14*'Продукция и цена '!$E$13)-((AI14*'Продукция и цена '!$E$13)*'Вводные данные'!$E$5) -> 0 | ... AM30: =(AM14*'Продукция и цена '!$E$13)-((AM14*'Продукция и цена '!$E$13)*'Вводные данные'!$E$5) -> 0 | AN30: =SUM(AB30:AM30) -> 0
A31: ИТОГО | B31: =SUM(B21:B30) -> 324000 | C31: =SUM(C21:C30) -> 79000 | D31: =SUM(D21:D30) -> 709000 | E31: =SUM(E21:E30) -> 264000 | F31: =SUM(F21:F30) -> 564000 | G31: =SUM(G21:G30) -> 714000 | H31: =SUM(H21:H30) -> 764000 | I31: =SUM(I21:I30) -> 791000 | ... M31: =SUM(M21:M30) -> 1191000 | N31: =SUM(B31:M31) -> 8458000 | O31: =SUM(O21:O30) -> 1899800 | P31: =SUM(P21:P30) -> 2354050 | Q31: =SUM(Q21:Q30) -> 2256300 | R31: =SUM(R21:R30) -> 3042516.7 | S31: =SUM(S21:S30) -> 2657841.7 | T31: =SUM(T21:T30) -> 3132216.7 | U31: =SUM(U21:U30) -> 3068391.7 | V31: =SUM(V21:V30) -> 3850966.7 | ... Z31: =SUM(Z21:Z30) -> 4636416.7 | AA31: =SUM(O31:Z31) -> 38144350 | AB31: =SUM(AB21:AB30) -> 5135267.5 | AC31: =SUM(AC21:AC30) -> 5442087.5 | AD31: =SUM(AD21:AD30) -> 5032112.5 | AE31: =SUM(AE21:AE30) -> 5994892.5 | AF31: =SUM(AF21:AF30) -> 5628560 | AG31: =SUM(AG21:AG30) -> 6562245 | AH31: =SUM(AH21:AH30) -> 6280552.5 | AI31: =SUM(AI21:AI30) -> 7216882.5 | ... AM31: =SUM(AM21:AM30) -> 8356877.5 | AN31: =SUM(AB31:AM31) -> 77633395

Sheet Маркетинг
A2: Бюджет маркетинга, руб.
A3: Название рекламы или метода продвижения | B3: 1 год | N3: ИТОГО за 1 год | O3: 2 год | AA3: ИТОГО за 2 год | AB3: 3 ГОД | AN3: ИТОГО за 3 год
B4: =РДДС!D5 -> 45809 | C4: =РДДС!E5 -> 45839 | D4: =РДДС!F5 -> 45870 | E4: =РДДС!G5 -> 45901 | F4: =РДДС!H5 -> 45931 | G4: =РДДС!I5 -> 45962 | H4: =РДДС!J5 -> 45992 | I4: =РДДС!K5 -> 46023 | ... M4: =РДДС!O5 -> 46143 | O4: =РДДС!Q5 -> 46174 | P4: =РДДС!R5 -> 46204 | Q4: =РДДС!S5 -> 46235 | R4: =РДДС!T5 -> 46266 | S4: =РДДС!U5 -> 46296 | T4: =РДДС!V5 -> 46327 | U4: =РДДС!W5 -> 46357 | V4: =РДДС!X5 -> 46388 | ... Z4: =РДДС!AB5 -> 46508 | AB4: =РДДС!AD5 -> 46539 | AC4: =РДДС!AE5 -> 46569 | AD4: =РДДС!AF5 -> 46600 | AE4: =РДДС!AG5 -> 46631 | AF4: =РДДС!AH5 -> 46661 | AG4: =РДДС!AI5 -> 46692 | AH4: =РДДС!AJ5 -> 46722 | AI4: =РДДС!AK5 -> 46753 | ... AM4: =РДДС!AO5 -> 46874
A5: Контекстная реклама | B5: 25000 | C5: 25000 | D5: 25000 | E5: 25000 | F5: 25000 | G5: 25000 | H5: 25000 | I5: 25000 | J5: 25000 | K5: 25000 | L5: 25000 | M5: 25000 | N5: =SUM(B5:M5) -> 300000 | O5: =B5+B5*'Вводные данные'!$D$4 -> 28750 | P5: =C5+C5*'Вводные данные'!$D$4 -> 28750 | Q5: =D5+D5*'Вводные данные'!$D$4 -> 28750 | R5: =E5+E5*'Вводные данные'!$D$4 -> 28750 | S5: =F5+F5*'Вводные данные'!$D$4 -> 28750 | T5: =G5+G5*'Вводные данные'!$D$4 -> 28750 | U5: =H5+H5*'Вводные данные'!$D$4 -> 28750 | V5: =I5+I5*'Вводные данные'!$D$4 -> 28750 | ... Z5: =M5+M5*'Вводные данные'!$D$4 -> 28750 | AA5: =SUM(O5:Z5) -> 345000 | AB5: =O5+O5*'Вводные данные'!$E$4 -> 33062.5 | AC5: =P5+P5*'Вводные данные'!$E$4 -> 33062.5 | AD5: =Q5+Q5*'Вводные данные'!$E$4 -> 33062.5 | AE5: =R5+R5*'Вводные данные'!$E$4 -> 33062.5 | AF5: =S5+S5*'Вводные данные'!$E$4 -> 33062.5 | AG5: =T5+T5*'Вводные данные'!$E$4 -> 33062.5 | AH5: =U5+U5*'Вводные данные'!$E$4 -> 33062.5 | AI5: =V5+V5*'Вводные данные'!$E$4 -> 33062.5 | ... AM5: =Z5+Z5*'Вводные данные'!$E$4 -> 33062.5 | AN5: =SUM(AB5:AM5) -> 396750
A6: Таргетная реклама | B6: 17000 | C6: 17000 | D6: 17000 | E6: 17000 | F6: 17000 | G6: 17000 | H6: 17000 | I6: 17000 | J6: 17000 | K6: 17000 | L6: 17000 | M6: 17000 | N6: =SUM(B6:M6) -> 204000 | O6: =B6+B6*'Вводные данные'!$D$4 -> 19550 | P6: =C6+C6*'Вводные данные'!$D$4 -> 19550 | Q6: =D6+D6*'Вводные данные'!$D$4 -> 19550 | R6: =E6+E6*'Вводные данные'!$D$4 -> 19550 | S6: =F6+F6*'Вводные данные'!$D$4 -> 19550 | T6: =G6+G6*'Вводные данные'!$D$4 -> 19550 | U6: =H6+H6*'Вводные данные'!$D$4 -> 19550 | V6: =I6+I6*'Вводные данные'!$D$4 -> 19550 | ... Z6: =M6+M6*'Вводные данные'!$D$4 -> 19550 | AA6: =SUM(O6:Z6) -> 234600 | AB6: =O6+O6*'Вводные данные'!$E$4 -> 22482.5 | AC6: =P6+P6*'Вводные данные'!$E$4 -> 22482.5 | AD6: =Q6+Q6*'Вводные данные'!$E$4 -> 22482.5 | AE6: =R6+R6*'Вводные данные'!$E$4 -> 22482.5 | AF6: =S6+S6*'Вводные данные'!$E$4 -> 22482.5 | AG6: =T6+T6*'Вводные данные'!$E$4 -> 22482.5 | AH6: =U6+U6*'Вводные данные'!$E$4 -> 22482.5 | AI6: =V6+V6*'Вводные данные'!$E$4 -> 22482.5 | ... AM6: =Z6+Z6*'Вводные данные'!$E$4 -> 22482.5 | AN6: =SUM(AB6:AM6) -> 269790
A7: Выставки и мероприятия | B7: 12500 | C7: 12500 | D7: 12500 | E7: 12500 | F7: 12500 | G7: 12500 | H7: 12500 | I7: 12500 | J7: 12500 | K7: 12500 | L7: 12500 | M7: 12500 | N7: =SUM(B7:M7) -> 150000 | O7: =B7+B7*'Вводные данные'!$D$4 -> 14375 | P7: =C7+C7*'Вводные данные'!$D$4 -> 14375 | Q7: =D7+D7*'Вводные данные'!$D$4 -> 14375 | R7: =E7+E7*'Вводные данные'!$D$4 -> 14375 | S7: =F7+F7*'Вводные данные'!$D$4 -> 14375 | T7: =G7+G7*'Вводные данные'!$D$4 -> 14375 | U7: =H7+H7*'Вводные данные'!$D$4 -> 14375 | V7: =I7+I7*'Вводные данные'!$D$4 -> 14375 | ... Z7: =M7+M7*'Вводные данные'!$D$4 -> 14375 | AA7: =SUM(O7:Z7) -> 172500 | AB7: =O7+O7*'Вводные данные'!$E$4 -> 16531.25 | AC7: =P7+P7*'Вводные данные'!$E$4 -> 16531.25 | AD7: =Q7+Q7*'Вводные данные'!$E$4 -> 16531.25 | AE7: =R7+R7*'Вводные данные'!$E$4 -> 16531.25 | AF7: =S7+S7*'Вводные данные'!$E$4 -> 16531.25 | AG7: =T7+T7*'Вводные данные'!$E$4 -> 16531.25 | AH7: =U7+U7*'Вводные данные'!$E$4 -> 16531.25 | AI7: =V7+V7*'Вводные данные'!$E$4 -> 16531.25 | ... AM7: =Z7+Z7*'Вводные данные'!$E$4 -> 16531.25 | AN7: =SUM(AB7:AM7) -> 198375
A8: Контент (блог) | B8: 7000 | C8: 7000 | D8: 7000 | E8: 7000 | F8: 7000 | G8: 7000 | H8: 7000 | I8: 7000 | J8: 7000 | K8: 7000 | L8: 7000 | M8: 7000 | N8: =SUM(B8:M8) -> 84000 | O8: =B8+B8*'Вводные данные'!$D$4 -> 8050 | P8: =C8+C8*'Вводные данные'!$D$4 -> 8050 | Q8: =D8+D8*'Вводные данные'!$D$4 -> 8050 | R8: =E8+E8*'Вводные данные'!$D$4 -> 8050 | S8: =F8+F8*'Вводные данные'!$D$4 -> 8050 | T8: =G8+G8*'Вводные данные'!$D$4 -> 8050 | U8: =H8+H8*'Вводные данные'!$D$4 -> 8050 | V8: =I8+I8*'Вводные данные'!$D$4 -> 8050 | ... Z8: =M8+M8*'Вводные данные'!$D$4 -> 8050 | AA8: =SUM(O8:Z8) -> 96600 | AB8: =O8+O8*'Вводные данные'!$E$4 -> 9257.5 | AC8: =P8+P8*'Вводные данные'!$E$4 -> 9257.5 | AD8: =Q8+Q8*'Вводные данные'!$E$4 -> 9257.5 | AE8: =R8+R8*'Вводные данные'!$E$4 -> 9257.5 | AF8: =S8+S8*'Вводные данные'!$E$4 -> 9257.5 | AG8: =T8+T8*'Вводные данные'!$E$4 -> 9257.5 | AH8: =U8+U8*'Вводные данные'!$E$4 -> 9257.5 | AI8: =V8+V8*'Вводные данные'!$E$4 -> 9257.5 | ... AM8: =Z8+Z8*'Вводные данные'!$E$4 -> 9257.5 | AN8: =SUM(AB8:AM8) -> 111090
N9: =SUM(B9:M9) -> 0 | O9: =B9+B9*'Вводные данные'!$D$4 -> 0 | P9: =C9+C9*'Вводные данные'!$D$4 -> 0 | Q9: =D9+D9*'Вводные данные'!$D$4 -> 0 | R9: =E9+E9*'Вводные данные'!$D$4 -> 0 | S9: =F9+F9*'Вводные данные'!$D$4 -> 0 | T9: =G9+G9*'Вводные данные'!$D$4 -> 0 | U9: =H9+H9*'Вводные данные'!$D$4 -> 0 | V9: =I9+I9*'Вводные данные'!$D$4 -> 0 | ... Z9: =M9+M9*'Вводные данные'!$D$4 -> 0 | AA9: =SUM(O9:Z9) -> 0 | AB9: =O9+O9*'Вводные данные'!$E$4 -> 0 | AC9: =P9+P9*'Вводные данные'!$E$4 -> 0 | AD9: =Q9+Q9*'Вводные данные'!$E$4 -> 0 | AE9: =R9+R9*'Вводные данные'!$E$4 -> 0 | AF9: =S9+S9*'Вводные данные'!$E$4 -> 0 | AG9: =T9+T9*'Вводные данные'!$E$4 -> 0 | AH9: =U9+U9*'Вводные данные'!$E$4 -> 0 | AI9: =V9+V9*'Вводные данные'!$E$4 -> 0 | ... AM9: =Z9+Z9*'Вводные данные'!$E$4 -> 0 | AN9: =SUM(AB9:AM9) -> 0
N10: =SUM(B10:M10) -> 0 | O10: =B10+B10*'Вводные данные'!$D$4 -> 0 | P10: =C10+C10*'Вводные данные'!$D$4 -> 0 | Q10: =D10+D10*'Вводные данные'!$D$4 -> 0 | R10: =E10+E10*'Вводные данные'!$D$4 -> 0 | S10: =F10+F10*'Вводные данные'!$D$4 -> 0 | T10: =G10+G10*'Вводные данные'!$D$4 -> 0 | U10: =H10+H10*'Вводные данные'!$D$4 -> 0 | V10: =I10+I10*'Вводные данные'!$D$4 -> 0 | ... Z10: =M10+M10*'Вводные данные'!$D$4 -> 0 | AA10: =SUM(O10:Z10) -> 0 | AB10: =O10+O10*'Вводные данные'!$E$4 -> 0 | AC10: =P10+P10*'Вводные данные'!$E$4 -> 0 | AD10: =Q10+Q10*'Вводные данные'!$E$4 -> 0 | AE10: =R10+R10*'Вводные данные'!$E$4 -> 0 | AF10: =S10+S10*'Вводные данные'!$E$4 -> 0 | AG10: =T10+T10*'Вводные данные'!$E$4 -> 0 | AH10: =U10+U10*'Вводные данные'!$E$4 -> 0 | AI10: =V10+V10*'Вводные данные'!$E$4 -> 0 | ... AM10: =Z10+Z10*'Вводные данные'!$E$4 -> 0 | AN10: =SUM(AB10:AM10) -> 0
N11: =SUM(B11:M11) -> 0 | O11: =B11+B11*'Вводные данные'!$D$4 -> 0 | P11: =C11+C11*'Вводные данные'!$D$4 -> 0 | Q11: =D11+D11*'Вводные данные'!$D$4 -> 0 | R11: =E11+E11*'Вводные данные'!$D$4 -> 0 | S11: =F11+F11*'Вводные данные'!$D$4 -> 0 | T11: =G11+G11*'Вводные данные'!$D$4 -> 0 | U11: =H11+H11*'Вводные данные'!$D$4 -> 0 | V11: =I11+I11*'Вводные данные'!$D$4 -> 0 | ... Z11: =M11+M11*'Вводные данные'!$D$4 -> 0 | AA11: =SUM(O11:Z11) -> 0 | AB11: =O11+O11*'Вводные данные'!$E$4 -> 0 | AC11: =P11+P11*'Вводные данные'!$E$4 -> 0 | AD11: =Q11+Q11*'Вводные данные'!$E$4 -> 0 | AE11: =R11+R11*'Вводные данные'!$E$4 -> 0 | AF11: =S11+S11*'Вводные данные'!$E$4 -> 0 | AG11: =T11+T11*'Вводные данные'!$E$4 -> 0 | AH11: =U11+U11*'Вводные данные'!$E$4 -> 0 | AI11: =V11+V11*'Вводные данные'!$E$4 -> 0 | ... AM11: =Z11+Z11*'Вводные данные'!$E$4 -> 0 | AN11: =SUM(AB11:AM11) -> 0
A12: ИТОГО | B12: =SUM(B5:B11) -> 61500 | C12: =SUM(C5:C11) -> 61500 | D12: =SUM(D5:D11) -> 61500 | E12: =SUM(E5:E11) -> 61500 | F12: =SUM(F5:F11) -> 61500 | G12: =SUM(G5:G11) -> 61500 | H12: =SUM(H5:H11) -> 61500 | I12: =SUM(I5:I11) -> 61500 | ... M12: =SUM(M5:M11) -> 61500 | N12: =SUM(B12:M12) -> 738000 | O12: =SUM(O5:O11) -> 70725 | P12: =SUM(P5:P11) -> 70725 | Q12: =SUM(Q5:Q11) -> 70725 | R12: =SUM(R5:R11) -> 70725 | S12: =SUM(S5:S11) -> 70725 | T12: =SUM(T5:T11) -> 70725 | U12: =SUM(U5:U11) -> 70725 | V12: =SUM(V5:V11) -> 70725 | ... Z12: =SUM(Z5:Z11) -> 70725 | AA12: =SUM(O12:Z12) -> 848700 | AB12: =SUM(AB5:AB11) -> 81333.75 | AC12: =SUM(AC5:AC11) -> 81333.75 | AD12: =SUM(AD5:AD11) -> 81333.75 | AE12: =SUM(AE5:AE11) -> 81333.75 | AF12: =SUM(AF5:AF11) -> 81333.75 | AG12: =SUM(AG5:AG11) -> 81333.75 | AH12: =SUM(AH5:AH11) -> 81333.75 | AI12: =SUM(AI5:AI11) -> 81333.75 | ... AM12: =SUM(AM5:AM11) -> 81333.75 | AN12: =SUM(AB12:AM12) -> 976005

Sheet Постоянные затраты
A2: Ежемесячные расходы, руб. (за исключением расходов на рекламу и персонал)
A3: Название расходов | B3: 1 год | N3: ИТОГО за 1 год | O3: 2 год | AA3: ИТОГО за 2 год | AB3: 3 год | AN3: ИТОГО за 3 год
B4: =РДДС!D5 -> 45809 | C4: =РДДС!E5 -> 45839 | D4: =РДДС!F5 -> 45870 | E4: =РДДС!G5 -> 45901 | F4: =РДДС!H5 -> 45931 | G4: =РДДС!I5 -> 45962 | H4: =РДДС!J5 -> 45992 | I4: =РДДС!K5 -> 46023 | ... M4: =РДДС!O5 -> 46143 | O4: =РДДС!Q5 -> 46174 | P4: =РДДС!R5 -> 46204 | Q4: =РДДС!S5 -> 46235 | R4: =РДДС!T5 -> 46266 | S4: =РДДС!U5 -> 46296 | T4: =РДДС!V5 -> 46327 | U4: =РДДС!W5 -> 46357 | V4: =РДДС!X5 -> 46388 | ... Z4: =РДДС!AB5 -> 46508 | AB4: =РДДС!AD5 -> 46539 | AC4: =РДДС!AE5 -> 46569 | AD4: =РДДС!AF5 -> 46600 | AE4: =РДДС!AG5 -> 46631 | AF4: =РДДС!AH5 -> 46661 | AG4: =РДДС!AI5 -> 46692 | AH4: =РДДС!AJ5 -> 46722 | AI4: =РДДС!AK5 -> 46753 | ... AM4: =РДДС!AO5 -> 46874
A5: Бухгалтерия | B5: 10000 | C5: 10000 | D5: 10000 | E5: 10000 | F5: 10000 | G5: 10000 | H5: 10000 | I5: 10000 | J5: 10000 | K5: 10000 | L5: 10000 | M5: 10000 | N5: =SUM(B5:M5) -> 120000 | O5: =B5+B5*'Вводные данные'!$D$4 -> 11500 | P5: =C5+C5*'Вводные данные'!$D$4 -> 11500 | Q5: =D5+D5*'Вводные данные'!$D$4 -> 11500 | R5: =E5+E5*'Вводные данные'!$D$4 -> 11500 | S5: =F5+F5*'Вводные данные'!$D$4 -> 11500 | T5: =G5+G5*'Вводные данные'!$D$4 -> 11500 | U5: =H5+H5*'Вводные данные'!$D$4 -> 11500 | V5: =I5+I5*'Вводные данные'!$D$4 -> 11500 | ... Z5: =M5+M5*'Вводные данные'!$D$4 -> 11500 | AA5: =SUM(O5:Z5) -> 138000 | AB5: =O5+O5*'Вводные данные'!$E$4 -> 13225 | AC5: =P5+P5*'Вводные данные'!$E$4 -> 13225 | AD5: =Q5+Q5*'Вводные данные'!$E$4 -> 13225 | AE5: =R5+R5*'Вводные данные'!$E$4 -> 13225 | AF5: =S5+S5*'Вводные данные'!$E$4 -> 13225 | AG5: =T5+T5*'Вводные данные'!$E$4 -> 13225 | AH5: =U5+U5*'Вводные данные'!$E$4 -> 13225 | AI5: =V5+V5*'Вводные данные'!$E$4 -> 13225 | ... AM5: =Z5+Z5*'Вводные данные'!$E$4 -> 13225 | AN5: =SUM(AB5:AM5) -> 158700
A6: Юридические | B6: 10000 | C6: 10000 | D6: 10000 | E6: 10000 | F6: 10000 | G6: 10000 | H6: 10000 | I6: 10000 | J6: 10000 | K6: 10000 | L6: 10000 | M6: 10000 | N6: =SUM(B6:M6) -> 120000 | O6: =B6+B6*'Вводные данные'!$D$4 -> 11500 | P6: =C6+C6*'Вводные данные'!$D$4 -> 11500 | Q6: =D6+D6*'Вводные данные'!$D$4 -> 11500 | R6: =E6+E6*'Вводные данные'!$D$4 -> 11500 | S6: =F6+F6*'Вводные данные'!$D$4 -> 11500 | T6: =G6+G6*'Вводные данные'!$D$4 -> 11500 | U6: =H6+H6*'Вводные данные'!$D$4 -> 11500 | V6: =I6+I6*'Вводные данные'!$D$4 -> 11500 | ... Z6: =M6+M6*'Вводные данные'!$D$4 -> 11500 | AA6: =SUM(O6:Z6) -> 138000 | AB6: =O6+O6*'Вводные данные'!$E$4 -> 13225 | AC6: =P6+P6*'Вводные данные'!$E$4 -> 13225 | AD6: =Q6+Q6*'Вводные данные'!$E$4 -> 13225 | AE6: =R6+R6*'Вводные данные'!$E$4 -> 13225 | AF6: =S6+S6*'Вводные данные'!$E$4 -> 13225 | AG6: =T6+T6*'Вводные данные'!$E$4 -> 13225 | AH6: =U6+U6*'Вводные данные'!$E$4 -> 13225 | AI6: =V6+V6*'Вводные данные'!$E$4 -> 13225 | ... AM6: =Z6+Z6*'Вводные данные'!$E$4 -> 13225 | AN6: =SUM(AB6:AM6) -> 158700
B7: 0 | C7: 0 | D7: 0 | E7: 0 | F7: 0 | G7: 0 | H7: 0 | I7: 0 | J7: 0 | K7: 0 | L7: 0 | M7: 0 | N7: =SUM(B7:M7) -> 0 | O7: =B7+B7*'Вводные данные'!$D$4 -> 0 | P7: =C7+C7*'Вводные данные'!$D$4 -> 0 | Q7: =D7+D7*'Вводные данные'!$D$4 -> 0 | R7: =E7+E7*'Вводные данные'!$D$4 -> 0 | S7: =F7+F7*'Вводные данные'!$D$4 -> 0 | T7: =G7+G7*'Вводные данные'!$D$4 -> 0 | U7: =H7+H7*'Вводные данные'!$D$4 -> 0 | V7: =I7+I7*'Вводные данные'!$D$4 -> 0 | ... Z7: =M7+M7*'Вводные данные'!$D$4 -> 0 | AA7: =SUM(O7:Z7) -> 0 | AB7: =O7+O7*'Вводные данные'!$E$4 -> 0 | AC7: =P7+P7*'Вводные данные'!$E$4 -> 0 | AD7: =Q7+Q7*'Вводные данные'!$E$4 -> 0 | AE7: =R7+R7*'Вводные данные'!$E$4 -> 0 | AF7: =S7+S7*'Вводные данные'!$E$4 -> 0 | AG7: =T7+T7*'Вводные данные'!$E$4 -> 0 | AH7: =U7+U7*'Вводные данные'!$E$4 -> 0 | AI7: =V7+V7*'Вводные данные'!$E$4 -> 0 | ... AM7: =Z7+Z7*'Вводные данные'!$E$4 -> 0 | AN7: =SUM(AB7:AM7) -> 0
A8: Офис аренда | B8: 30000 | C8: 30000 | D8: 30000 | E8: 30000 | F8: 30000 | G8: 30000 | H8: 30000 | I8: 30000 | J8: 30000 | K8: 30000 | L8: 30000 | M8: 30000 | N8: =SUM(B8:M8) -> 360000 | O8: =B8+B8*'Вводные данные'!$D$4 -> 34500 | P8: =C8+C8*'Вводные данные'!$D$4 -> 34500 | Q8: =D8+D8*'Вводные данные'!$D$4 -> 34500 | R8: =E8+E8*'Вводные данные'!$D$4 -> 34500 | S8: =F8+F8*'Вводные данные'!$D$4 -> 34500 | T8: =G8+G8*'Вводные данные'!$D$4 -> 34500 | U8: =H8+H8*'Вводные данные'!$D$4 -> 34500 | V8: =I8+I8*'Вводные данные'!$D$4 -> 34500 | ... Z8: =M8+M8*'Вводные данные'!$D$4 -> 34500 | AA8: =SUM(O8:Z8) -> 414000 | AB8: =O8+O8*'Вводные данные'!$E$4 -> 39675 | AC8: =P8+P8*'Вводные данные'!$E$4 -> 39675 | AD8: =Q8+Q8*'Вводные данные'!$E$4 -> 39675 | AE8: =R8+R8*'Вводные данные'!$E$4 -> 39675 | AF8: =S8+S8*'Вводные данные'!$E$4 -> 39675 | AG8: =T8+T8*'Вводные данные'!$E$4 -> 39675 | AH8: =U8+U8*'Вводные данные'!$E$4 -> 39675 | AI8: =V8+V8*'Вводные данные'!$E$4 -> 39675 | ... AM8: =Z8+Z8*'Вводные данные'!$E$4 -> 39675 | AN8: =SUM(AB8:AM8) -> 476100
A9: Прочее (связь, интернет, канцелярия) | B9: 4000 | C9: 4000 | D9: 4000 | E9: 4000 | F9: 4000 | G9: 4000 | H9: 4000 | I9: 4000 | J9: 4000 | K9: 4000 | L9: 4000 | M9: 4000 | N9: =SUM(B9:M9) -> 48000 | O9: =B9+B9*'Вводные данные'!$D$4 -> 4600 | P9: =C9+C9*'Вводные данные'!$D$4 -> 4600 | Q9: =D9+D9*'Вводные данные'!$D$4 -> 4600 | R9: =E9+E9*'Вводные данные'!$D$4 -> 4600 | S9: =F9+F9*'Вводные данные'!$D$4 -> 4600 | T9: =G9+G9*'Вводные данные'!$D$4 -> 4600 | U9: =H9+H9*'Вводные данные'!$D$4 -> 4600 | V9: =I9+I9*'Вводные данные'!$D$4 -> 4600 | ... Z9: =M9+M9*'Вводные данные'!$D$4 -> 4600 | AA9: =SUM(O9:Z9) -> 55200 | AB9: =O9+O9*'Вводные данные'!$E$4 -> 5290 | AC9: =P9+P9*'Вводные данные'!$E$4 -> 5290 | AD9: =Q9+Q9*'Вводные данные'!$E$4 -> 5290 | AE9: =R9+R9*'Вводные данные'!$E$4 -> 5290 | AF9: =S9+S9*'Вводные данные'!$E$4 -> 5290 | AG9: =T9+T9*'Вводные данные'!$E$4 -> 5290 | AH9: =U9+U9*'Вводные данные'!$E$4 -> 5290 | AI9: =V9+V9*'Вводные данные'!$E$4 -> 5290 | ... AM9: =Z9+Z9*'Вводные данные'!$E$4 -> 5290 | AN9: =SUM(AB9:AM9) -> 63480
A10: Хостинг и облака | B10: 15000 | C10: 15000 | D10: 15000 | E10: 15000 | F10: 15000 | G10: 15000 | H10: 15000 | I10: 15000 | J10: 15000 | K10: 15000 | L10: 15000 | M10: 15000 | N10: =SUM(B10:M10) -> 180000 | O10: =B10+B10*'Вводные данные'!$D$4 -> 17250 | P10: =C10+C10*'Вводные данные'!$D$4 -> 17250 | Q10: =D10+D10*'Вводные данные'!$D$4 -> 17250 | R10: =E10+E10*'Вводные данные'!$D$4 -> 17250 | S10: =F10+F10*'Вводные данные'!$D$4 -> 17250 | T10: =G10+G10*'Вводные данные'!$D$4 -> 17250 | U10: =H10+H10*'Вводные данные'!$D$4 -> 17250 | V10: =I10+I10*'Вводные данные'!$D$4 -> 17250 | ... Z10: =M10+M10*'Вводные данные'!$D$4 -> 17250 | AA10: =SUM(O10:Z10) -> 207000 | AB10: =O10+O10*'Вводные данные'!$E$4 -> 19837.5 | AC10: =P10+P10*'Вводные данные'!$E$4 -> 19837.5 | AD10: =Q10+Q10*'Вводные данные'!$E$4 -> 19837.5 | AE10: =R10+R10*'Вводные данные'!$E$4 -> 19837.5 | AF10: =S10+S10*'Вводные данные'!$E$4 -> 19837.5 | AG10: =T10+T10*'Вводные данные'!$E$4 -> 19837.5 | AH10: =U10+U10*'Вводные данные'!$E$4 -> 19837.5 | AI10: =V10+V10*'Вводные данные'!$E$4 -> 19837.5 | ... AM10: =Z10+Z10*'Вводные данные'!$E$4 -> 19837.5 | AN10: =SUM(AB10:AM10) -> 238050
A11: Домены, SSL, почта | B11: 5000 | C11: 5000 | D11: 5000 | E11: 5000 | F11: 5000 | G11: 5000 | H11: 5000 | I11: 5000 | J11: 5000 | K11: 5000 | L11: 5000 | M11: 5000 | N11: =SUM(B11:M11) -> 60000 | O11: =B11+B11*'Вводные данные'!$D$4 -> 5750 | P11: =C11+C11*'Вводные данные'!$D$4 -> 5750 | Q11: =D11+D11*'Вводные данные'!$D$4 -> 5750 | R11: =E11+E11*'Вводные данные'!$D$4 -> 5750 | S11: =F11+F11*'Вводные данные'!$D$4 -> 5750 | T11: =G11+G11*'Вводные данные'!$D$4 -> 5750 | U11: =H11+H11*'Вводные данные'!$D$4 -> 5750 | V11: =I11+I11*'Вводные данные'!$D$4 -> 5750 | ... Z11: =M11+M11*'Вводные данные'!$D$4 -> 5750 | AA11: =SUM(O11:Z11) -> 69000 | AB11: =O11+O11*'Вводные данные'!$E$4 -> 6612.5 | AC11: =P11+P11*'Вводные данные'!$E$4 -> 6612.5 | AD11: =Q11+Q11*'Вводные данные'!$E$4 -> 6612.5 | AE11: =R11+R11*'Вводные данные'!$E$4 -> 6612.5 | AF11: =S11+S11*'Вводные данные'!$E$4 -> 6612.5 | AG11: =T11+T11*'Вводные данные'!$E$4 -> 6612.5 | AH11: =U11+U11*'Вводные данные'!$E$4 -> 6612.5 | AI11: =V11+V11*'Вводные данные'!$E$4 -> 6612.5 | ... AM11: =Z11+Z11*'Вводные данные'!$E$4 -> 6612.5 | AN11: =SUM(AB11:AM11) -> 79350
A12: SaaS-сервисы | B12: 10000 | C12: 10000 | D12: 10000 | E12: 10000 | F12: 10000 | G12: 10000 | H12: 10000 | I12: 10000 | J12: 10000 | K12: 10000 | L12: 10000 | M12: 10000 | N12: =SUM(B12:M12) -> 120000 | O12: =B12+B12*'Вводные данные'!$D$4 -> 11500 | P12: =C12+C12*'Вводные данные'!$D$4 -> 11500 | Q12: =D12+D12*'Вводные данные'!$D$4 -> 11500 | R12: =E12+E12*'Вводные данные'!$D$4 -> 11500 | S12: =F12+F12*'Вводные данные'!$D$4 -> 11500 | T12: =G12+G12*'Вводные данные'!$D$4 -> 11500 | U12: =H12+H12*'Вводные данные'!$D$4 -> 11500 | V12: =I12+I12*'Вводные данные'!$D$4 -> 11500 | ... Z12: =M12+M12*'Вводные данные'!$D$4 -> 11500 | AA12: =SUM(O12:Z12) -> 138000 | AB12: =O12+O12*'Вводные данные'!$E$4 -> 13225 | AC12: =P12+P12*'Вводные данные'!$E$4 -> 13225 | AD12: =Q12+Q12*'Вводные данные'!$E$4 -> 13225 | AE12: =R12+R12*'Вводные данные'!$E$4 -> 13225 | AF12: =S12+S12*'Вводные данные'!$E$4 -> 13225 | AG12: =T12+T12*'Вводные данные'!$E$4 -> 13225 | AH12: =U12+U12*'Вводные данные'!$E$4 -> 13225 | AI12: =V12+V12*'Вводные данные'!$E$4 -> 13225 | ... AM12: =Z12+Z12*'Вводные данные'!$E$4 -> 13225 | AN12: =SUM(AB12:AM12) -> 158700
A13: Мониторинг и аналитика | B13: 5000 | C13: 5000 | D13: 5000 | E13: 5000 | F13: 5000 | G13: 5000 | H13: 5000 | I13: 5000 | J13: 5000 | K13: 5000 | L13: 5000 | M13: 5000 | N13: =SUM(B13:M13) -> 60000 | O13: =B13+B13*'Вводные данные'!$D$4 -> 5750 | P13: =C13+C13*'Вводные данные'!$D$4 -> 5750 | Q13: =D13+D13*'Вводные данные'!$D$4 -> 5750 | R13: =E13+E13*'Вводные данные'!$D$4 -> 5750 | S13: =F13+F13*'Вводные данные'!$D$4 -> 5750 | T13: =G13+G13*'Вводные данные'!$D$4 -> 5750 | U13: =H13+H13*'Вводные данные'!$D$4 -> 5750 | V13: =I13+I13*'Вводные данные'!$D$4 -> 5750 | ... Z13: =M13+M13*'Вводные данные'!$D$4 -> 5750 | AA13: =SUM(O13:Z13) -> 69000 | AB13: =O13+O13*'Вводные данные'!$E$4 -> 6612.5 | AC13: =P13+P13*'Вводные данные'!$E$4 -> 6612.5 | AD13: =Q13+Q13*'Вводные данные'!$E$4 -> 6612.5 | AE13: =R13+R13*'Вводные данные'!$E$4 -> 6612.5 | AF13: =S13+S13*'Вводные данные'!$E$4 -> 6612.5 | AG13: =T13+T13*'Вводные данные'!$E$4 -> 6612.5 | AH13: =U13+U13*'Вводные данные'!$E$4 -> 6612.5 | AI13: =V13+V13*'Вводные данные'!$E$4 -> 6612.5 | ... AM13: =Z13+Z13*'Вводные данные'!$E$4 -> 6612.5 | AN13: =SUM(AB13:AM13) -> 79350
A14: Расходы 10 | N14: =SUM(B14:M14) -> 0 | O14: =B14+B14*'Вводные данные'!$D$4 -> 0 | P14: =C14+C14*'Вводные данные'!$D$4 -> 0 | Q14: =D14+D14*'Вводные данные'!$D$4 -> 0 | R14: =E14+E14*'Вводные данные'!$D$4 -> 0 | S14: =F14+F14*'Вводные данные'!$D$4 -> 0 | T14: =G14+G14*'Вводные данные'!$D$4 -> 0 | U14: =H14+H14*'Вводные данные'!$D$4 -> 0 | V14: =I14+I14*'Вводные данные'!$D$4 -> 0 | ... Z14: =M14+M14*'Вводные данные'!$D$4 -> 0 | AA14: =SUM(O14:Z14) -> 0 | AB14: =O14+O14*'Вводные данные'!$E$4 -> 0 | AC14: =P14+P14*'Вводные данные'!$E$4 -> 0 | AD14: =Q14+Q14*'Вводные данные'!$E$4 -> 0 | AE14: =R14+R14*'Вводные данные'!$E$4 -> 0 | AF14: =S14+S14*'Вводные данные'!$E$4 -> 0 | AG14: =T14+T14*'Вводные данные'!$E$4 -> 0 | AH14: =U14+U14*'Вводные данные'!$E$4 -> 0 | AI14: =V14+V14*'Вводные данные'!$E$4 -> 0 | ... AM14: =Z14+Z14*'Вводные данные'!$E$4 -> 0 | AN14: =SUM(AB14:AM14) -> 0
A15: Расходы 11 | N15: =SUM(B15:M15) -> 0 | O15: =B15+B15*'Вводные данные'!$D$4 -> 0 | P15: =C15+C15*'Вводные данные'!$D$4 -> 0 | Q15: =D15+D15*'Вводные данные'!$D$4 -> 0 | R15: =E15+E15*'Вводные данные'!$D$4 -> 0 | S15: =F15+F15*'Вводные данные'!$D$4 -> 0 | T15: =G15+G15*'Вводные данные'!$D$4 -> 0 | U15: =H15+H15*'Вводные данные'!$D$4 -> 0 | V15: =I15+I15*'Вводные данные'!$D$4 -> 0 | ... Z15: =M15+M15*'Вводные данные'!$D$4 -> 0 | AA15: =SUM(O15:Z15) -> 0 | AB15: =O15+O15*'Вводные данные'!$E$4 -> 0 | AC15: =P15+P15*'Вводные данные'!$E$4 -> 0 | AD15: =Q15+Q15*'Вводные данные'!$E$4 -> 0 | AE15: =R15+R15*'Вводные данные'!$E$4 -> 0 | AF15: =S15+S15*'Вводные данные'!$E$4 -> 0 | AG15: =T15+T15*'Вводные данные'!$E$4 -> 0 | AH15: =U15+U15*'Вводные данные'!$E$4 -> 0 | AI15: =V15+V15*'Вводные данные'!$E$4 -> 0 | ... AM15: =Z15+Z15*'Вводные данные'!$E$4 -> 0 | AN15: =SUM(AB15:AM15) -> 0
A16: Расходы 12 | N16: =SUM(B16:M16) -> 0 | O16: =B16+B16*'Вводные данные'!$D$4 -> 0 | P16: =C16+C16*'Вводные данные'!$D$4 -> 0 | Q16: =D16+D16*'Вводные данные'!$D$4 -> 0 | R16: =E16+E16*'Вводные данные'!$D$4 -> 0 | S16: =F16+F16*'Вводные данные'!$D$4 -> 0 | T16: =G16+G16*'Вводные данные'!$D$4 -> 0 | U16: =H16+H16*'Вводные данные'!$D$4 -> 0 | V16: =I16+I16*'Вводные данные'!$D$4 -> 0 | ... Z16: =M16+M16*'Вводные данные'!$D$4 -> 0 | AA16: =SUM(O16:Z16) -> 0 | AB16: =O16+O16*'Вводные данные'!$E$4 -> 0 | AC16: =P16+P16*'Вводные данные'!$E$4 -> 0 | AD16: =Q16+Q16*'Вводные данные'!$E$4 -> 0 | AE16: =R16+R16*'Вводные данные'!$E$4 -> 0 | AF16: =S16+S16*'Вводные данные'!$E$4 -> 0 | AG16: =T16+T16*'Вводные данные'!$E$4 -> 0 | AH16: =U16+U16*'Вводные данные'!$E$4 -> 0 | AI16: =V16+V16*'Вводные данные'!$E$4 -> 0 | ... AM16: =Z16+Z16*'Вводные данные'!$E$4 -> 0 | AN16: =SUM(AB16:AM16) -> 0
A17: Расходы 13 | N17: =SUM(B17:M17) -> 0 | O17: =B17+B17*'Вводные данные'!$D$4 -> 0 | P17: =C17+C17*'Вводные данные'!$D$4 -> 0 | Q17: =D17+D17*'Вводные данные'!$D$4 -> 0 | R17: =E17+E17*'Вводные данные'!$D$4 -> 0 | S17: =F17+F17*'Вводные данные'!$D$4 -> 0 | T17: =G17+G17*'Вводные данные'!$D$4 -> 0 | U17: =H17+H17*'Вводные данные'!$D$4 -> 0 | V17: =I17+I17*'Вводные данные'!$D$4 -> 0 | ... Z17: =M17+M17*'Вводные данные'!$D$4 -> 0 | AA17: =SUM(O17:Z17) -> 0 | AB17: =O17+O17*'Вводные данные'!$E$4 -> 0 | AC17: =P17+P17*'Вводные данные'!$E$4 -> 0 | AD17: =Q17+Q17*'Вводные данные'!$E$4 -> 0 | AE17: =R17+R17*'Вводные данные'!$E$4 -> 0 | AF17: =S17+S17*'Вводные данные'!$E$4 -> 0 | AG17: =T17+T17*'Вводные данные'!$E$4 -> 0 | AH17: =U17+U17*'Вводные данные'!$E$4 -> 0 | AI17: =V17+V17*'Вводные данные'!$E$4 -> 0 | ... AM17: =Z17+Z17*'Вводные данные'!$E$4 -> 0 | AN17: =SUM(AB17:AM17) -> 0
A18: Расходы 14 | N18: =SUM(B18:M18) -> 0 | O18: =B18+B18*'Вводные данные'!$D$4 -> 0 | P18: =C18+C18*'Вводные данные'!$D$4 -> 0 | Q18: =D18+D18*'Вводные данные'!$D$4 -> 0 | R18: =E18+E18*'Вводные данные'!$D$4 -> 0 | S18: =F18+F18*'Вводные данные'!$D$4 -> 0 | T18: =G18+G18*'Вводные данные'!$D$4 -> 0 | U18: =H18+H18*'Вводные данные'!$D$4 -> 0 | V18: =I18+I18*'Вводные данные'!$D$4 -> 0 | ... Z18: =M18+M18*'Вводные данные'!$D$4 -> 0 | AA18: =SUM(O18:Z18) -> 0 | AB18: =O18+O18*'Вводные данные'!$E$4 -> 0 | AC18: =P18+P18*'Вводные данные'!$E$4 -> 0 | AD18: =Q18+Q18*'Вводные данные'!$E$4 -> 0 | AE18: =R18+R18*'Вводные данные'!$E$4 -> 0 | AF18: =S18+S18*'Вводные данные'!$E$4 -> 0 | AG18: =T18+T18*'Вводные данные'!$E$4 -> 0 | AH18: =U18+U18*'Вводные данные'!$E$4 -> 0 | AI18: =V18+V18*'Вводные данные'!$E$4 -> 0 | ... AM18: =Z18+Z18*'Вводные данные'!$E$4 -> 0 | AN18: =SUM(AB18:AM18) -> 0
A19: Расходы 15 | N19: =SUM(B19:M19) -> 0 | O19: =B19+B19*'Вводные данные'!$D$4 -> 0 | P19: =C19+C19*'Вводные данные'!$D$4 -> 0 | Q19: =D19+D19*'Вводные данные'!$D$4 -> 0 | R19: =E19+E19*'Вводные данные'!$D$4 -> 0 | S19: =F19+F19*'Вводные данные'!$D$4 -> 0 | T19: =G19+G19*'Вводные данные'!$D$4 -> 0 | U19: =H19+H19*'Вводные данные'!$D$4 -> 0 | V19: =I19+I19*'Вводные данные'!$D$4 -> 0 | ... Z19: =M19+M19*'Вводные данные'!$D$4 -> 0 | AA19: =SUM(O19:Z19) -> 0 | AB19: =O19+O19*'Вводные данные'!$E$4 -> 0 | AC19: =P19+P19*'Вводные данные'!$E$4 -> 0 | AD19: =Q19+Q19*'Вводные данные'!$E$4 -> 0 | AE19: =R19+R19*'Вводные данные'!$E$4 -> 0 | AF19: =S19+S19*'Вводные данные'!$E$4 -> 0 | AG19: =T19+T19*'Вводные данные'!$E$4 -> 0 | AH19: =U19+U19*'Вводные данные'!$E$4 -> 0 | AI19: =V19+V19*'Вводные данные'!$E$4 -> 0 | ... AM19: =Z19+Z19*'Вводные данные'!$E$4 -> 0 | AN19: =SUM(AB19:AM19) -> 0
A20: ИТОГО | B20: =SUM(B5:B19) -> 89000 | C20: =SUM(C5:C19) -> 89000 | D20: =SUM(D5:D19) -> 89000 | E20: =SUM(E5:E19) -> 89000 | F20: =SUM(F5:F19) -> 89000 | G20: =SUM(G5:G19) -> 89000 | H20: =SUM(H5:H19) -> 89000 | I20: =SUM(I5:I19) -> 89000 | ... M20: =SUM(M5:M19) -> 89000 | N20: =SUM(B20:M20) -> 1068000 | O20: =SUM(O5:O19) -> 102350 | P20: =SUM(P5:P19) -> 102350 | Q20: =SUM(Q5:Q19) -> 102350 | R20: =SUM(R5:R19) -> 102350 | S20: =SUM(S5:S19) -> 102350 | T20: =SUM(T5:T19) -> 102350 | U20: =SUM(U5:U19) -> 102350 | V20: =SUM(V5:V19) -> 102350 | ... Z20: =SUM(Z5:Z19) -> 102350 | AA20: =SUM(O20:Z20) -> 1228200 | AB20: =SUM(AB5:AB19) -> 117702.5 | AC20: =SUM(AC5:AC19) -> 117702.5 | AD20: =SUM(AD5:AD19) -> 117702.5 | AE20: =SUM(AE5:AE19) -> 117702.5 | AF20: =SUM(AF5:AF19) -> 117702.5 | AG20: =SUM(AG5:AG19) -> 117702.5 | AH20: =SUM(AH5:AH19) -> 117702.5 | AI20: =SUM(AI5:AI19) -> 117702.5 | ... AM20: =SUM(AM5:AM19) -> 117702.5 | AN20: =SUM(AB20:AM20) -> 1412430

Sheet Переменные затраты
A2: Себестоимость изготовления продукции / оказания услуг
A4: № | B4: Наименование сырья и материалов | C4: Цена за 1 единицу, в руб | D4: Среднее количество, необходимое на единицу | E4: Сумма затрат на единицу продукцию, руб. | H4: 1 год | T4: ИТОГО за 1 год | U4: 2 год | AG4: ИТОГО за 2 год | AH4: 3 год | AT4: ИТОГО за 3 год
H5: =РДДС!D5 -> 45809 | I5: =РДДС!E5 -> 45839 | J5: =РДДС!F5 -> 45870 | K5: =РДДС!G5 -> 45901 | L5: =РДДС!H5 -> 45931 | M5: =РДДС!I5 -> 45962 | N5: =РДДС!J5 -> 45992 | O5: =РДДС!K5 -> 46023 | ... S5: =РДДС!O5 -> 46143 | U5: =РДДС!Q5 -> 46174 | V5: =РДДС!R5 -> 46204 | W5: =РДДС!S5 -> 46235 | X5: =РДДС!T5 -> 46266 | Y5: =РДДС!U5 -> 46296 | Z5: =РДДС!V5 -> 46327 | AA5: =РДДС!W5 -> 46357 | AB5: =РДДС!X5 -> 46388 | ... AF5: =РДДС!AB5 -> 46508 | AH5: =РДДС!AD5 -> 46539 | AI5: =РДДС!AE5 -> 46569 | AJ5: =РДДС!AF5 -> 46600 | AK5: =РДДС!AG5 -> 46631 | AL5: =РДДС!AH5 -> 46661 | AM5: =РДДС!AI5 -> 46692 | AN5: =РДДС!AJ5 -> 46722 | AO5: =РДДС!AK5 -> 46753 | ... AS5: =РДДС!AO5 -> 46874
A6: 1 | B6: ='Продукция и цена '!A4 -> Аренда системы: "Базовый" тариф | C6: - | D6: - | E6: 1 год | F6: 2 год | G6: 3 год | H6: =SUM(H7:H16) -> 3600 | I6: =SUM(I7:I16) -> 7200 | J6: =SUM(J7:J16) -> 10800 | K6: =SUM(K7:K16) -> 14400 | L6: =SUM(L7:L16) -> 18000 | M6: =SUM(M7:M16) -> 25200 | N6: =SUM(N7:N16) -> 28800 | O6: =SUM(O7:O16) -> 28800 | ... S6: =SUM(S7:S16) -> 50400 | T6: =SUM(H6:S6) -> 313200 | U6: =SUM(U7:U16) -> 62100 | V6: =SUM(V7:V16) -> 66240 | W6: =SUM(W7:W16) -> 74520 | X6: =SUM(X7:X16) -> 80040 | Y6: =SUM(Y7:Y16) -> 86250 | Z6: =SUM(Z7:Z16) -> 92460 | AA6: =SUM(AA7:AA16) -> 98670 | AB6: =SUM(AB7:AB16) -> 104880 | ... AF6: =SUM(AF7:AF16) -> 129720 | AG6: =SUM(U6:AF6) -> 1146780 | AH6: =SUM(AH7:AH16) -> 28566 | AI6: =SUM(AI7:AI16) -> 28566 | AJ6: =SUM(AJ7:AJ16) -> 28566 | AK6: =SUM(AK7:AK16) -> 28566 | AL6: =SUM(AL7:AL16) -> 28566 | AM6: =SUM(AM7:AM16) -> 28566 | AN6: =SUM(AN7:AN16) -> 33327 | AO6: =SUM(AO7:AO16) -> 33327 | ... AS6: =SUM(AS7:AS16) -> 33327 | AT6: =SUM(AH6:AS6) -> 371358
A7: 1.1 | B7: Сервер и облака | C7: 800 | D7: 1 | E7: =C7*D7 -> 800 | F7: =E7+E7*'Вводные данные'!$D$4 -> 920 | G7: =F7+F7*'Вводные данные'!$E$4 -> 1058 | H7: =$E$7*Продажи!B5 -> 800 | I7: =$E$7*Продажи!C5 -> 1600 | J7: =$E$7*Продажи!D5 -> 2400 | K7: =$E$7*Продажи!E5 -> 3200 | L7: =$E$7*Продажи!F5 -> 4000 | M7: =$E$7*Продажи!G5 -> 5600 | N7: =$E$7*Продажи!H5 -> 6400 | O7: =$E$7*Продажи!I5 -> 6400 | ... S7: =$E$7*Продажи!M5 -> 11200 | T7: =SUM(H7:S7) -> 69600 | U7: =$F$7*Продажи!O5 -> 13800 | V7: =$F$7*Продажи!P5 -> 14720 | W7: =$F$7*Продажи!Q5 -> 16560 | X7: =$F$7*Продажи!R5 -> 17786.667 | Y7: =$F$7*Продажи!S5 -> 19166.667 | Z7: =$F$7*Продажи!T5 -> 20546.667 | AA7: =$F$7*Продажи!U5 -> 21926.667 | AB7: =$F$7*Продажи!V5 -> 23306.667 | ... AF7: =$F$7*Продажи!Z5 -> 28826.667 | AG7: =SUM(U7:AF7) -> 254840 | AH7: =$G$7*Продажи!AB5 -> 6348 | AI7: =$G$7*Продажи!AC5 -> 6348 | AJ7: =$G$7*Продажи!AD5 -> 6348 | AK7: =$G$7*Продажи!AE5 -> 6348 | AL7: =$G$7*Продажи!AF5 -> 6348 | AM7: =$G$7*Продажи!AG5 -> 6348 | AN7: =$G$7*Продажи!AH5 -> 7406 | AO7: =$G$7*Продажи!AI5 -> 7406 | ... AS7: =$G$7*Продажи!AM5 -> 7406 | AT7: =SUM(AH7:AS7) -> 82524
A8: 1.2 | B8: Техподдержка | C8: 2500 | D8: 1 | E8: =C8*D8 -> 2500 | F8: =E8+E8*'Вводные данные'!$D$4 -> 2875 | G8: =F8+F8*'Вводные данные'!$E$4 -> 3306.25 | H8: =$E$8*Продажи!B5 -> 2500 | I8: =$E$8*Продажи!C5 -> 5000 | J8: =$E$8*Продажи!D5 -> 7500 | K8: =$E$8*Продажи!E5 -> 10000 | L8: =$E$8*Продажи!F5 -> 12500 | M8: =$E$8*Продажи!G5 -> 17500 | N8: =$E$8*Продажи!H5 -> 20000 | O8: =$E$8*Продажи!I5 -> 20000 | ... S8: =$E$8*Продажи!M5 -> 35000 | T8: =SUM(H8:S8) -> 217500 | U8: =$F$8*Продажи!O5 -> 43125 | V8: =$F$8*Продажи!P5 -> 46000 | W8: =$F$8*Продажи!Q5 -> 51750 | X8: =$F$8*Продажи!R5 -> 55583.333 | Y8: =$F$8*Продажи!S5 -> 59895.833 | Z8: =$F$8*Продажи!T5 -> 64208.333 | AA8: =$F$8*Продажи!U5 -> 68520.833 | AB8: =$F$8*Продажи!V5 -> 72833.333 | ... AF8: =$F$8*Продажи!Z5 -> 90083.333 | AG8: =SUM(U8:AF8) -> 796375 | AH8: =$G$8*Продажи!AB5 -> 19837.5 | AI8: =$G$8*Продажи!AC5 -> 19837.5 | AJ8: =$G$8*Продажи!AD5 -> 19837.5 | AK8: =$G$8*Продажи!AE5 -> 19837.5 | AL8: =$G$8*Продажи!AF5 -> 19837.5 | AM8: =$G$8*Продажи!AG5 -> 19837.5 | AN8: =$G$8*Продажи!AH5 -> 23143.75 | AO8: =$G$8*Продажи!AI5 -> 23143.75 | ... AS8: =$G$8*Продажи!AM5 -> 23143.75 | AT8: =SUM(AH8:AS8) -> 257887.5
A9: 1.3 | B9: Лицензии и API | C9: 300 | D9: 1 | E9: =C9*D9 -> 300 | F9: =E9+E9*'Вводные данные'!$D$4 -> 345 | G9: =F9+F9*'Вводные данные'!$E$4 -> 396.75 | H9: =$E$9*Продажи!B5 -> 300 | I9: =$E$9*Продажи!C5 -> 600 | J9: =$E$9*Продажи!D5 -> 900 | K9: =$E$9*Продажи!E5 -> 1200 | L9: =$E$9*Продажи!F5 -> 1500 | M9: =$E$9*Продажи!G5 -> 2100 | N9: =$E$9*Продажи!H5 -> 2400 | O9: =$E$9*Продажи!I5 -> 2400 | ... S9: =$E$9*Продажи!M5 -> 4200 | T9: =SUM(H9:S9) -> 26100 | U9: =$F$9*Продажи!O5 -> 5175 | V9: =$F$9*Продажи!P5 -> 5520 | W9: =$F$9*Продажи!Q5 -> 6210 | X9: =$F$9*Продажи!R5 -> 6670 | Y9: =$F$9*Продажи!S5 -> 7187.5 | Z9: =$F$9*Продажи!T5 -> 7705 | AA9: =$F$9*Продажи!U5 -> 8222.5 | AB9: =$F$9*Продажи!V5 -> 8740 | ... AF9: =$F$9*Продажи!Z5 -> 10810 | AG9: =SUM(U9:AF9) -> 95565 | AH9: =$G$9*Продажи!AB5 -> 2380.5 | AI9: =$G$9*Продажи!AC5 -> 2380.5 | AJ9: =$G$9*Продажи!AD5 -> 2380.5 | AK9: =$G$9*Продажи!AE5 -> 2380.5 | AL9: =$G$9*Продажи!AF5 -> 2380.5 | AM9: =$G$9*Продажи!AG5 -> 2380.5 | AN9: =$G$9*Продажи!AH5 -> 2777.25 | AO9: =$G$9*Продажи!AI5 -> 2777.25 | ... AS9: =$G$9*Продажи!AM5 -> 2777.25 | AT9: =SUM(AH9:AS9) -> 30946.5
A10: 1.4 | C10: 0 | D10: 0 | E10: =C10*D10 -> 0 | F10: =E10+E10*'Вводные данные'!$D$4 -> 0 | G10: =F10+F10*'Вводные данные'!$E$4 -> 0 | H10: =$E$10*Продажи!B5 -> 0 | I10: =$E$10*Продажи!C5 -> 0 | J10: =$E$10*Продажи!D5 -> 0 | K10: =$E$10*Продажи!E5 -> 0 | L10: =$E$10*Продажи!F5 -> 0 | M10: =$E$10*Продажи!G5 -> 0 | N10: =$E$10*Продажи!H5 -> 0 | O10: =$E$10*Продажи!I5 -> 0 | ... S10: =$E$10*Продажи!M5 -> 0 | T10: =SUM(H10:S10) -> 0 | U10: =$F$10*Продажи!O5 -> 0 | V10: =$F$10*Продажи!P5 -> 0 | W10: =$F$10*Продажи!Q5 -> 0 | X10: =$F$10*Продажи!R5 -> 0 | Y10: =$F$10*Продажи!S5 -> 0 | Z10: =$F$10*Продажи!T5 -> 0 | AA10: =$F$10*Продажи!U5 -> 0 | AB10: =$F$10*Продажи!V5 -> 0 | ... AF10: =$F$10*Продажи!Z5 -> 0 | AG10: =SUM(U10:AF10) -> 0 | AH10: =$G$10*Продажи!AB5 -> 0 | AI10: =$G$10*Продажи!AC5 -> 0 | AJ10: =$G$10*Продажи!AD5 -> 0 | AK10: =$G$10*Продажи!AE5 -> 0 | AL10: =$G$10*Продажи!AF5 -> 0 | AM10: =$G$10*Продажи!AG5 -> 0 | AN10: =$G$10*Продажи!AH5 -> 0 | AO10: =$G$10*Продажи!AI5 -> 0 | ... AS10: =$G$10*Продажи!AM5 -> 0 | AT10: =SUM(AH10:AS10) -> 0
A11: 1.5 | B11: 0 | C11: 0 | D11: 0 | E11: =C11*D11 -> 0 | F11: =E11+E11*'Вводные данные'!$D$4 -> 0 | G11: =F11+F11*'Вводные данные'!$E$4 -> 0 | H11: =$E$11*Продажи!B5 -> 0 | I11: =$E$11*Продажи!C5 -> 0 | J11: =$E$11*Продажи!D5 -> 0 | K11: =$E$11*Продажи!E5 -> 0 | L11: =$E$11*Продажи!F5 -> 0 | M11: =$E$11*Продажи!G5 -> 0 | N11: =$E$11*Продажи!H5 -> 0 | O11: =$E$11*Продажи!I5 -> 0 | ... S11: =$E$11*Продажи!M5 -> 0 | T11: =SUM(H11:S11) -> 0 | U11: =$F$11*Продажи!O5 -> 0 | V11: =$F$11*Продажи!P5 -> 0 | W11: =$F$11*Продажи!Q5 -> 0 | X11: =$F$11*Продажи!R5 -> 0 | Y11: =$F$11*Продажи!S5 -> 0 | Z11: =$F$11*Продажи!T5 -> 0 | AA11: =$F$11*Продажи!U5 -> 0 | AB11: =$F$11*Продажи!V5 -> 0 | ... AF11: =$F$11*Продажи!Z5 -> 0 | AG11: =SUM(U11:AF11) -> 0 | AH11: =$G$11*Продажи!AB5 -> 0 | AI11: =$G$11*Продажи!AC5 -> 0 | AJ11: =$G$11*Продажи!AD5 -> 0 | AK11: =$G$11*Продажи!AE5 -> 0 | AL11: =$G$11*Продажи!AF5 -> 0 | AM11: =$G$11*Продажи!AG5 -> 0 | AN11: =$G$11*Продажи!AH5 -> 0 | AO11: =$G$11*Продажи!AI5 -> 0 | ... AS11: =$G$11*Продажи!AM5 -> 0 | AT11: =SUM(AH11:AS11) -> 0
A12: 1.6 | B12: 0 | C12: 0 | D12: 0 | E12: =C12*D12 -> 0 | F12: =E12+E12*'Вводные данные'!$D$4 -> 0 | G12: =F12+F12*'Вводные данные'!$E$4 -> 0 | H12: =$E$12*Продажи!B5 -> 0 | I12: =$E$12*Продажи!C5 -> 0 | J12: =$E$12*Продажи!D5 -> 0 | K12: =$E$12*Продажи!E5 -> 0 | L12: =$E$12*Продажи!F5 -> 0 | M12: =$E$12*Продажи!G5 -> 0 | N12: =$E$12*Продажи!H5 -> 0 | O12: =$E$12*Продажи!I5 -> 0 | ... S12: =$E$12*Продажи!M5 -> 0 | T12: =SUM(H12:S12) -> 0 | U12: =$F$12*Продажи!O5 -> 0 | V12: =$F$12*Продажи!P5 -> 0 | W12: =$F$12*Продажи!Q5 -> 0 | X12: =$F$12*Продажи!R5 -> 0 | Y12: =$F$12*Продажи!S5 -> 0 | Z12: =$F$12*Продажи!T5 -> 0 | AA12: =$F$12*Продажи!U5 -> 0 | AB12: =$F$12*Продажи!V5 -> 0 | ... AF12: =$F$12*Продажи!Z5 -> 0 | AG12: =SUM(U12:AF12) -> 0 | AH12: =$G$12*Продажи!AB5 -> 0 | AI12: =$G$12*Продажи!AC5 -> 0 | AJ12: =$G$12*Продажи!AD5 -> 0 | AK12: =$G$12*Продажи!AE5 -> 0 | AL12: =$G$12*Продажи!AF5 -> 0 | AM12: =$G$12*Продажи!AG5 -> 0 | AN12: =$G$12*Продажи!AH5 -> 0 | AO12: =$G$12*Продажи!AI5 -> 0 | ... AS12: =$G$12*Продажи!AM5 -> 0 | AT12: =SUM(AH12:AS12) -> 0
A13: 1.7 | B13: Сырье и материалы 7 | E13: =C13*D13 -> 0 | F13: =E13+E13*'Вводные данные'!$D$4 -> 0 | G13: =F13+F13*'Вводные данные'!$E$4 -> 0 | H13: =$E$13*Продажи!B5 -> 0 | I13: =$E$13*Продажи!C5 -> 0 | J13: =$E$13*Продажи!D5 -> 0 | K13: =$E$13*Продажи!E5 -> 0 | L13: =$E$13*Продажи!F5 -> 0 | M13: =$E$13*Продажи!G5 -> 0 | N13: =$E$13*Продажи!H5 -> 0 | O13: =$E$13*Продажи!I5 -> 0 | ... S13: =$E$13*Продажи!M5 -> 0 | T13: =SUM(H13:S13) -> 0 | U13: =$F$13*Продажи!O5 -> 0 | V13: =$F$13*Продажи!P5 -> 0 | W13: =$F$13*Продажи!Q5 -> 0 | X13: =$F$13*Продажи!R5 -> 0 | Y13: =$F$13*Продажи!S5 -> 0 | Z13: =$F$13*Продажи!T5 -> 0 | AA13: =$F$13*Продажи!U5 -> 0 | AB13: =$F$13*Продажи!V5 -> 0 | ... AF13: =$F$13*Продажи!Z5 -> 0 | AG13: =SUM(U13:AF13) -> 0 | AH13: =$G$13*Продажи!AB5 -> 0 | AI13: =$G$13*Продажи!AC5 -> 0 | AJ13: =$G$13*Продажи!AD5 -> 0 | AK13: =$G$13*Продажи!AE5 -> 0 | AL13: =$G$13*Продажи!AF5 -> 0 | AM13: =$G$13*Продажи!AG5 -> 0 | AN13: =$G$13*Продажи!AH5 -> 0 | AO13: =$G$13*Продажи!AI5 -> 0 | ... AS13: =$G$13*Продажи!AM5 -> 0 | AT13: =SUM(AH13:AS13) -> 0
A14: 1.8 | B14: Сырье и материалы 8 | E14: =C14*D14 -> 0 | F14: =E14+E14*'Вводные данные'!$D$4 -> 0 | G14: =F14+F14*'Вводные данные'!$E$4 -> 0 | H14: =$E$14*Продажи!B5 -> 0 | I14: =$E$14*Продажи!C5 -> 0 | J14: =$E$14*Продажи!D5 -> 0 | K14: =$E$14*Продажи!E5 -> 0 | L14: =$E$14*Продажи!F5 -> 0 | M14: =$E$14*Продажи!G5 -> 0 | N14: =$E$14*Продажи!H5 -> 0 | O14: =$E$14*Продажи!I5 -> 0 | ... S14: =$E$14*Продажи!M5 -> 0 | T14: =SUM(H14:S14) -> 0 | U14: =$F$14*Продажи!O5 -> 0 | V14: =$F$14*Продажи!P5 -> 0 | W14: =$F$14*Продажи!Q5 -> 0 | X14: =$F$14*Продажи!R5 -> 0 | Y14: =$F$14*Продажи!S5 -> 0 | Z14: =$F$14*Продажи!T5 -> 0 | AA14: =$F$14*Продажи!U5 -> 0 | AB14: =$F$14*Продажи!V5 -> 0 | ... AF14: =$F$14*Продажи!Z5 -> 0 | AG14: =SUM(U14:AF14) -> 0 | AH14: =$G$14*Продажи!AB5 -> 0 | AI14: =$G$14*Продажи!AC5 -> 0 | AJ14: =$G$14*Продажи!AD5 -> 0 | AK14: =$G$14*Продажи!AE5 -> 0 | AL14: =$G$14*Продажи!AF5 -> 0 | AM14: =$G$14*Продажи!AG5 -> 0 | AN14: =$G$14*Продажи!AH5 -> 0 | AO14: =$G$14*Продажи!AI5 -> 0 | ... AS14: =$G$14*Продажи!AM5 -> 0 | AT14: =SUM(AH14:AS14) -> 0
A15: 1.9 | B15: Сырье и материалы 9 | E15: =C15*D15 -> 0 | F15: =E15+E15*'Вводные данные'!$D$4 -> 0 | G15: =F15+F15*'Вводные данные'!$E$4 -> 0 | H15: =$E$15*Продажи!B5 -> 0 | I15: =$E$15*Продажи!C5 -> 0 | J15: =$E$15*Продажи!D5 -> 0 | K15: =$E$15*Продажи!E5 -> 0 | L15: =$E$15*Продажи!F5 -> 0 | M15: =$E$15*Продажи!G5 -> 0 | N15: =$E$15*Продажи!H5 -> 0 | O15: =$E$15*Продажи!I5 -> 0 | ... S15: =$E$15*Продажи!M5 -> 0 | T15: =SUM(H15:S15) -> 0 | U15: =$F$15*Продажи!O5 -> 0 | V15: =$F$15*Продажи!P5 -> 0 | W15: =$F$15*Продажи!Q5 -> 0 | X15: =$F$15*Продажи!R5 -> 0 | Y15: =$F$15*Продажи!S5 -> 0 | Z15: =$F$15*Продажи!T5 -> 0 | AA15: =$F$15*Продажи!U5 -> 0 | AB15: =$F$15*Продажи!V5 -> 0 | ... AF15: =$F$15*Продажи!Z5 -> 0 | AG15: =SUM(U15:AF15) -> 0 | AH15: =$G$15*Продажи!AB5 -> 0 | AI15: =$G$15*Продажи!AC5 -> 0 | AJ15: =$G$15*Продажи!AD5 -> 0 | AK15: =$G$15*Продажи!AE5 -> 0 | AL15: =$G$15*Продажи!AF5 -> 0 | AM15: =$G$15*Продажи!AG5 -> 0 | AN15: =$G$15*Продажи!AH5 -> 0 | AO15: =$G$15*Продажи!AI5 -> 0 | ... AS15: =$G$15*Продажи!AM5 -> 0 | AT15: =SUM(AH15:AS15) -> 0
A16: 1.10 | B16: Сырье и материалы 10 | E16: =C16*D16 -> 0 | F16: =E16+E16*'Вводные данные'!$D$4 -> 0 | G16: =F16+F16*'Вводные данные'!$E$4 -> 0 | H16: =$E$16*Продажи!B5 -> 0 | I16: =$E$16*Продажи!C5 -> 0 | J16: =$E$16*Продажи!D5 -> 0 | K16: =$E$16*Продажи!E5 -> 0 | L16: =$E$16*Продажи!F5 -> 0 | M16: =$E$16*Продажи!G5 -> 0 | N16: =$E$16*Продажи!H5 -> 0 | O16: =$E$16*Продажи!I5 -> 0 | ... S16: =$E$16*Продажи!M5 -> 0 | T16: =SUM(H16:S16) -> 0 | U16: =$F$16*Продажи!O5 -> 0 | V16: =$F$16*Продажи!P5 -> 0 | W16: =$F$16*Продажи!Q5 -> 0 | X16: =$F$16*Продажи!R5 -> 0 | Y16: =$F$16*Продажи!S5 -> 0 | Z16: =$F$16*Продажи!T5 -> 0 | AA16: =$F$16*Продажи!U5 -> 0 | AB16: =$F$16*Продажи!V5 -> 0 | ... AF16: =$F$16*Продажи!Z5 -> 0 | AG16: =SUM(U16:AF16) -> 0 | AH16: =$G$16*Продажи!AB5 -> 0 | AI16: =$G$16*Продажи!AC5 -> 0 | AJ16: =$G$16*Продажи!AD5 -> 0 | AK16: =$G$16*Продажи!AE5 -> 0 | AL16: =$G$16*Продажи!AF5 -> 0 | AM16: =$G$16*Продажи!AG5 -> 0 | AN16: =$G$16*Продажи!AH5 -> 0 | AO16: =$G$16*Продажи!AI5 -> 0 | ... AS16: =$G$16*Продажи!AM5 -> 0 | AT16: =SUM(AH16:AS16) -> 0
A17: 1.11 | B17: Cправочно стоимость услуги | H17: ='Продукция и цена '!C4 -> 35000 | T17: =H17 -> 35000 | U17: ='Продукция и цена '!D4 -> 40250 | AG17: =SUM(U17:AF17) -> 40250 | AH17: ='Продукция и цена '!E4 -> 46287.5 | AT17: =SUM(AH17:AS17) -> 46287.5
A18: 2 | B18: ='Продукция и цена '!A5 -> Поддержка системы | C18: - | D18: - | E18: 1 год | F18: 2 год | G18: 3 год | H18: =SUM(H19:H28) -> 4000 | I18: =SUM(I19:I28) -> 0 | J18: =SUM(J19:J28) -> 4000 | K18: =SUM(K19:K28) -> 4000 | L18: =SUM(L19:L28) -> 6000 | M18: =SUM(M19:M28) -> 8000 | N18: =SUM(N19:N28) -> 10000 | O18: =SUM(O19:O28) -> 12000 | ... S18: =SUM(S19:S28) -> 20000 | T18: =SUM(H18:S18) -> 118000 | U18: =SUM(U19:U28) -> 27600 | V18: =SUM(V19:V28) -> 34500 | W18: =SUM(W19:W28) -> 39100 | X18: =SUM(X19:X28) -> 48300 | Y18: =SUM(Y19:Y28) -> 52900 | Z18: =SUM(Z19:Z28) -> 59800 | AA18: =SUM(AA19:AA28) -> 64400 | AB18: =SUM(AB19:AB28) -> 73600 | ... AF18: =SUM(AF19:AF28) -> 98900 | AG18: =SUM(U18:AF18) -> 752100 | AH18: =SUM(AH19:AH28) -> 129605 | AI18: =SUM(AI19:AI28) -> 145475 | AJ18: =SUM(AJ19:AJ28) -> 156055 | AK18: =SUM(AK19:AK28) -> 171925 | AL18: =SUM(AL19:AL28) -> 182505 | AM18: =SUM(AM19:AM28) -> 198375 | AN18: =SUM(AN19:AN28) -> 208955 | AO18: =SUM(AO19:AO28) -> 224825 | ... AS18: =SUM(AS19:AS28) -> 277725 | AT18: =SUM(AH18:AS18) -> 2443980
A19: 2.1 | B19: Техподдержка | C19: 2000 | D19: 1 | E19: =C19*D19 -> 2000 | F19: =E19+E19*'Вводные данные'!$D$4 -> 2300 | G19: =F19+F19*'Вводные данные'!$E$4 -> 2645 | H19: =$E$19*Продажи!B6 -> 4000 | I19: =$E$19*Продажи!C6 -> 0 | J19: =$E$19*Продажи!D6 -> 4000 | K19: =$E$19*Продажи!E6 -> 4000 | L19: =$E$19*Продажи!F6 -> 6000 | M19: =$E$19*Продажи!G6 -> 8000 | N19: =$E$19*Продажи!H6 -> 10000 | O19: =$E$19*Продажи!I6 -> 12000 | ... S19: =$E$19*Продажи!M6 -> 20000 | T19: =SUM(H19:S19) -> 118000 | U19: =$F$19*Продажи!O6 -> 27600 | V19: =$F$19*Продажи!P6 -> 34500 | W19: =$F$19*Продажи!Q6 -> 39100 | X19: =$F$19*Продажи!R6 -> 48300 | Y19: =$F$19*Продажи!S6 -> 52900 | Z19: =$F$19*Продажи!T6 -> 59800 | AA19: =$F$19*Продажи!U6 -> 64400 | AB19: =$F$19*Продажи!V6 -> 73600 | ... AF19: =$F$19*Продажи!Z6 -> 98900 | AG19: =SUM(U19:AF19) -> 752100 | AH19: =$G$19*Продажи!AB6 -> 129605 | AI19: =$G$19*Продажи!AC6 -> 145475 | AJ19: =$G$19*Продажи!AD6 -> 156055 | AK19: =$G$19*Продажи!AE6 -> 171925 | AL19: =$G$19*Продажи!AF6 -> 182505 | AM19: =$G$19*Продажи!AG6 -> 198375 | AN19: =$G$19*Продажи!AH6 -> 208955 | AO19: =$G$19*Продажи!AI6 -> 224825 | ... AS19: =$G$19*Продажи!AM6 -> 277725 | AT19: =SUM(AH19:AS19) -> 2443980
A20: 2.2 | B20: 0 | C20: 0 | D20: 0 | E20: =C20*D20 -> 0 | F20: =E20+E20*'Вводные данные'!$D$4 -> 0 | G20: =F20+F20*'Вводные данные'!$E$4 -> 0 | H20: =$E$20*Продажи!B6 -> 0 | I20: =$E$20*Продажи!C6 -> 0 | J20: =$E$20*Продажи!D6 -> 0 | K20: =$E$20*Продажи!E6 -> 0 | L20: =$E$20*Продажи!F6 -> 0 | M20: =$E$20*Продажи!G6 -> 0 | N20: =$E$20*Продажи!H6 -> 0 | O20: =$E$20*Продажи!I6 -> 0 | ... S20: =$E$20*Продажи!M6 -> 0 | T20: =SUM(H20:S20) -> 0 | U20: =$F$20*Продажи!O6 -> 0 | V20: =$F$20*Продажи!P6 -> 0 | W20: =$F$20*Продажи!Q6 -> 0 | X20: =$F$20*Продажи!R6 -> 0 | Y20: =$F$20*Продажи!S6 -> 0 | Z20: =$F$20*Продажи!T6 -> 0 | AA20: =$F$20*Продажи!U6 -> 0 | AB20: =$F$20*Продажи!V6 -> 0 | ... AF20: =$F$20*Продажи!Z6 -> 0 | AG20: =SUM(U20:AF20) -> 0 | AH20: =$G$20*Продажи!AB6 -> 0 | AI20: =$G$20*Продажи!AC6 -> 0 | AJ20: =$G$20*Продажи!AD6 -> 0 | AK20: =$G$20*Продажи!AE6 -> 0 | AL20: =$G$20*Продажи!AF6 -> 0 | AM20: =$G$20*Продажи!AG6 -> 0 | AN20: =$G$20*Продажи!AH6 -> 0 | AO20: =$G$20*Продажи!AI6 -> 0 | ... AS20: =$G$20*Продажи!AM6 -> 0 | AT20: =SUM(AH20:AS20) -> 0
A21: 2.3 | B21: 0 | C21: 0 | D21: 0 | E21: =C21*D21 -> 0 | F21: =E21+E21*'Вводные данные'!$D$4 -> 0 | G21: =F21+F21*'Вводные данные'!$E$4 -> 0 | H21: =$E$21*Продажи!B6 -> 0 | I21: =$E$21*Продажи!C6 -> 0 | J21: =$E$21*Продажи!D6 -> 0 | K21: =$E$21*Продажи!E6 -> 0 | L21: =$E$21*Продажи!F6 -> 0 | M21: =$E$21*Продажи!G6 -> 0 | N21: =$E$21*Продажи!H6 -> 0 | O21: =$E$21*Продажи!I6 -> 0 | ... S21: =$E$21*Продажи!M6 -> 0 | T21: =SUM(H21:S21) -> 0 | U21: =$F$21*Продажи!O6 -> 0 | V21: =$F$21*Продажи!P6 -> 0 | W21: =$F$21*Продажи!Q6 -> 0 | X21: =$F$21*Продажи!R6 -> 0 | Y21: =$F$21*Продажи!S6 -> 0 | Z21: =$F$21*Продажи!T6 -> 0 | AA21: =$F$21*Продажи!U6 -> 0 | AB21: =$F$21*Продажи!V6 -> 0 | ... AF21: =$F$21*Продажи!Z6 -> 0 | AG21: =SUM(U21:AF21) -> 0 | AH21: =$G$21*Продажи!AB6 -> 0 | AI21: =$G$21*Продажи!AC6 -> 0 | AJ21: =$G$21*Продажи!AD6 -> 0 | AK21: =$G$21*Продажи!AE6 -> 0 | AL21: =$G$21*Продажи!AF6 -> 0 | AM21: =$G$21*Продажи!AG6 -> 0 | AN21: =$G$21*Продажи!AH6 -> 0 | AO21: =$G$21*Продажи!AI6 -> 0 | ... AS21: =$G$21*Продажи!AM6 -> 0 | AT21: =SUM(AH21:AS21) -> 0
A22: 2.4 | B22: 0 | C22: 0 | D22: 0 | E22: =C22*D22 -> 0 | F22: =E22+E22*'Вводные данные'!$D$4 -> 0 | G22: =F22+F22*'Вводные данные'!$E$4 -> 0 | H22: =$E$22*Продажи!B6 -> 0 | I22: =$E$22*Продажи!C6 -> 0 | J22: =$E$22*Продажи!D6 -> 0 | K22: =$E$22*Продажи!E6 -> 0 | L22: =$E$22*Продажи!F6 -> 0 | M22: =$E$22*Продажи!G6 -> 0 | N22: =$E$22*Продажи!H6 -> 0 | O22: =$E$22*Продажи!I6 -> 0 | ... S22: =$E$22*Продажи!M6 -> 0 | T22: =SUM(H22:S22) -> 0 | U22: =$F$22*Продажи!O6 -> 0 | V22: =$F$22*Продажи!P6 -> 0 | W22: =$F$22*Продажи!Q6 -> 0 | X22: =$F$22*Продажи!R6 -> 0 | Y22: =$F$22*Продажи!S6 -> 0 | Z22: =$F$22*Продажи!T6 -> 0 | AA22: =$F$22*Продажи!U6 -> 0 | AB22: =$F$22*Продажи!V6 -> 0 | ... AF22: =$F$22*Продажи!Z6 -> 0 | AG22: =SUM(U22:AF22) -> 0 | AH22: =$G$22*Продажи!AB6 -> 0 | AI22: =$G$22*Продажи!AC6 -> 0 | AJ22: =$G$22*Продажи!AD6 -> 0 | AK22: =$G$22*Продажи!AE6 -> 0 | AL22: =$G$22*Продажи!AF6 -> 0 | AM22: =$G$22*Продажи!AG6 -> 0 | AN22: =$G$22*Продажи!AH6 -> 0 | AO22: =$G$22*Продажи!AI6 -> 0 | ... AS22: =$G$22*Продажи!AM6 -> 0 | AT22: =SUM(AH22:AS22) -> 0
A23: 2.5 | B23: Сырье и материалы 5 | E23: =C23*D23 -> 0 | F23: =E23+E23*'Вводные данные'!$D$4 -> 0 | G23: =F23+F23*'Вводные данные'!$E$4 -> 0 | H23: =$E$23*Продажи!B6 -> 0 | I23: =$E$23*Продажи!C6 -> 0 | J23: =$E$23*Продажи!D6 -> 0 | K23: =$E$23*Продажи!E6 -> 0 | L23: =$E$23*Продажи!F6 -> 0 | M23: =$E$23*Продажи!G6 -> 0 | N23: =$E$23*Продажи!H6 -> 0 | O23: =$E$23*Продажи!I6 -> 0 | ... S23: =$E$23*Продажи!M6 -> 0 | T23: =SUM(H23:S23) -> 0 | U23: =$F$23*Продажи!O6 -> 0 | V23: =$F$23*Продажи!P6 -> 0 | W23: =$F$23*Продажи!Q6 -> 0 | X23: =$F$23*Продажи!R6 -> 0 | Y23: =$F$23*Продажи!S6 -> 0 | Z23: =$F$23*Продажи!T6 -> 0 | AA23: =$F$23*Продажи!U6 -> 0 | AB23: =$F$23*Продажи!V6 -> 0 | ... AF23: =$F$23*Продажи!Z6 -> 0 | AG23: =SUM(U23:AF23) -> 0 | AH23: =$G$23*Продажи!AB6 -> 0 | AI23: =$G$23*Продажи!AC6 -> 0 | AJ23: =$G$23*Продажи!AD6 -> 0 | AK23: =$G$23*Продажи!AE6 -> 0 | AL23: =$G$23*Продажи!AF6 -> 0 | AM23: =$G$23*Продажи!AG6 -> 0 | AN23: =$G$23*Продажи!AH6 -> 0 | AO23: =$G$23*Продажи!AI6 -> 0 | ... AS23: =$G$23*Продажи!AM6 -> 0 | AT23: =SUM(AH23:AS23) -> 0
A24: 2.6 | B24: Сырье и материалы 6 | E24: =C24*D24 -> 0 | F24: =E24+E24*'Вводные данные'!$D$4 -> 0 | G24: =F24+F24*'Вводные данные'!$E$4 -> 0 | H24: =$E$24*Продажи!B6 -> 0 | I24: =$E$24*Продажи!C6 -> 0 | J24: =$E$24*Продажи!D6 -> 0 | K24: =$E$24*Продажи!E6 -> 0 | L24: =$E$24*Продажи!F6 -> 0 | M24: =$E$24*Продажи!G6 -> 0 | N24: =$E$24*Продажи!H6 -> 0 | O24: =$E$24*Продажи!I6 -> 0 | ... S24: =$E$24*Продажи!M6 -> 0 | T24: =SUM(H24:S24) -> 0 | U24: =$F$24*Продажи!O6 -> 0 | V24: =$F$24*Продажи!P6 -> 0 | W24: =$F$24*Продажи!Q6 -> 0 | X24: =$F$24*Продажи!R6 -> 0 | Y24: =$F$24*Продажи!S6 -> 0 | Z24: =$F$24*Продажи!T6 -> 0 | AA24: =$F$24*Продажи!U6 -> 0 | AB24: =$F$24*Продажи!V6 -> 0 | ... AF24: =$F$24*Продажи!Z6 -> 0 | AG24: =SUM(U24:AF24) -> 0 | AH24: =$G$24*Продажи!AB6 -> 0 | AI24: =$G$24*Продажи!AC6 -> 0 | AJ24: =$G$24*Продажи!AD6 -> 0 | AK24: =$G$24*Продажи!AE6 -> 0 | AL24: =$G$24*Продажи!AF6 -> 0 | AM24: =$G$24*Продажи!AG6 -> 0 | AN24: =$G$24*Продажи!AH6 -> 0 | AO24: =$G$24*Продажи!AI6 -> 0 | ... AS24: =$G$24*Продажи!AM6 -> 0 | AT24: =SUM(AH24:AS24) -> 0
A25: 2.7 | B25: Сырье и материалы 7 | E25: =C25*D25 -> 0 | F25: =E25+E25*'Вводные данные'!$D$4 -> 0 | G25: =F25+F25*'Вводные данные'!$E$4 -> 0 | H25: =$E$25*Продажи!B6 -> 0 | I25: =$E$25*Продажи!C6 -> 0 | J25: =$E$25*Продажи!D6 -> 0 | K25: =$E$25*Продажи!E6 -> 0 | L25: =$E$25*Продажи!F6 -> 0 | M25: =$E$25*Продажи!G6 -> 0 | N25: =$E$25*Продажи!H6 -> 0 | O25: =$E$25*Продажи!I6 -> 0 | ... S25: =$E$25*Продажи!M6 -> 0 | T25: =SUM(H25:S25) -> 0 | U25: =$F$25*Продажи!O6 -> 0 | V25: =$F$25*Продажи!P6 -> 0 | W25: =$F$25*Продажи!Q6 -> 0 | X25: =$F$25*Продажи!R6 -> 0 | Y25: =$F$25*Продажи!S6 -> 0 | Z25: =$F$25*Продажи!T6 -> 0 | AA25: =$F$25*Продажи!U6 -> 0 | AB25: =$F$25*Продажи!V6 -> 0 | ... AF25: =$F$25*Продажи!Z6 -> 0 | AG25: =SUM(U25:AF25) -> 0 | AH25: =$G$25*Продажи!AB6 -> 0 | AI25: =$G$25*Продажи!AC6 -> 0 | AJ25: =$G$25*Продажи!AD6 -> 0 | AK25: =$G$25*Продажи!AE6 -> 0 | AL25: =$G$25*Продажи!AF6 -> 0 | AM25: =$G$25*Продажи!AG6 -> 0 | AN25: =$G$25*Продажи!AH6 -> 0 | AO25: =$G$25*Продажи!AI6 -> 0 | ... AS25: =$G$25*Продажи!AM6 -> 0 | AT25: =SUM(AH25:AS25) -> 0
A26: 2.8 | B26: Сырье и материалы 8 | E26: =C26*D26 -> 0 | F26: =E26+E26*'Вводные данные'!$D$4 -> 0 | G26: =F26+F26*'Вводные данные'!$E$4 -> 0 | H26: =$E$26*Продажи!B6 -> 0 | I26: =$E$26*Продажи!C6 -> 0 | J26: =$E$26*Продажи!D6 -> 0 | K26: =$E$26*Продажи!E6 -> 0 | L26: =$E$26*Продажи!F6 -> 0 | M26: =$E$26*Продажи!G6 -> 0 | N26: =$E$26*Продажи!H6 -> 0 | O26: =$E$26*Продажи!I6 -> 0 | ... S26: =$E$26*Продажи!M6 -> 0 | T26: =SUM(H26:S26) -> 0 | U26: =$F$26*Продажи!O6 -> 0 | V26: =$F$26*Продажи!P6 -> 0 | W26: =$F$26*Продажи!Q6 -> 0 | X26: =$F$26*Продажи!R6 -> 0 | Y26: =$F$26*Продажи!S6 -> 0 | Z26: =$F$26*Продажи!T6 -> 0 | AA26: =$F$26*Продажи!U6 -> 0 | AB26: =$F$26*Продажи!V6 -> 0 | ... AF26: =$F$26*Продажи!Z6 -> 0 | AG26: =SUM(U26:AF26) -> 0 | AH26: =$G$26*Продажи!AB6 -> 0 | AI26: =$G$26*Продажи!AC6 -> 0 | AJ26: =$G$26*Продажи!AD6 -> 0 | AK26: =$G$26*Продажи!AE6 -> 0 | AL26: =$G$26*Продажи!AF6 -> 0 | AM26: =$G$26*Продажи!AG6 -> 0 | AN26: =$G$26*Продажи!AH6 -> 0 | AO26: =$G$26*Продажи!AI6 -> 0 | ... AS26: =$G$26*Продажи!AM6 -> 0 | AT26: =SUM(AH26:AS26) -> 0
A27: 2.9 | B27: Сырье и материалы 9 | E27: =C27*D27 -> 0 | F27: =E27+E27*'Вводные данные'!$D$4 -> 0 | G27: =F27+F27*'Вводные данные'!$E$4 -> 0 | H27: =$E$27*Продажи!B6 -> 0 | I27: =$E$27*Продажи!C6 -> 0 | J27: =$E$27*Продажи!D6 -> 0 | K27: =$E$27*Продажи!E6 -> 0 | L27: =$E$27*Продажи!F6 -> 0 | M27: =$E$27*Продажи!G6 -> 0 | N27: =$E$27*Продажи!H6 -> 0 | O27: =$E$27*Продажи!I6 -> 0 | ... S27: =$E$27*Продажи!M6 -> 0 | T27: =SUM(H27:S27) -> 0 | U27: =$F$27*Продажи!O6 -> 0 | V27: =$F$27*Продажи!P6 -> 0 | W27: =$F$27*Продажи!Q6 -> 0 | X27: =$F$27*Продажи!R6 -> 0 | Y27: =$F$27*Продажи!S6 -> 0 | Z27: =$F$27*Продажи!T6 -> 0 | AA27: =$F$27*Продажи!U6 -> 0 | AB27: =$F$27*Продажи!V6 -> 0 | ... AF27: =$F$27*Продажи!Z6 -> 0 | AG27: =SUM(U27:AF27) -> 0 | AH27: =$G$27*Продажи!AB6 -> 0 | AI27: =$G$27*Продажи!AC6 -> 0 | AJ27: =$G$27*Продажи!AD6 -> 0 | AK27: =$G$27*Продажи!AE6 -> 0 | AL27: =$G$27*Продажи!AF6 -> 0 | AM27: =$G$27*Продажи!AG6 -> 0 | AN27: =$G$27*Продажи!AH6 -> 0 | AO27: =$G$27*Продажи!AI6 -> 0 | ... AS27: =$G$27*Продажи!AM6 -> 0 | AT27: =SUM(AH27:AS27) -> 0
A28: 2.10 | B28: Сырье и материалы 10 | E28: =C28*D28 -> 0 | F28: =E28+E28*'Вводные данные'!$D$4 -> 0 | G28: =F28+F28*'Вводные данные'!$E$4 -> 0 | H28: =$E$28*Продажи!B6 -> 0 | I28: =$E$28*Продажи!C6 -> 0 | J28: =$E$28*Продажи!D6 -> 0 | K28: =$E$28*Продажи!E6 -> 0 | L28: =$E$28*Продажи!F6 -> 0 | M28: =$E$28*Продажи!G6 -> 0 | N28: =$E$28*Продажи!H6 -> 0 | O28: =$E$28*Продажи!I6 -> 0 | ... S28: =$E$28*Продажи!M6 -> 0 | T28: =SUM(H28:S28) -> 0 | U28: =$F$28*Продажи!O6 -> 0 | V28: =$F$28*Продажи!P6 -> 0 | W28: =$F$28*Продажи!Q6 -> 0 | X28: =$F$28*Продажи!R6 -> 0 | Y28: =$F$28*Продажи!S6 -> 0 | Z28: =$F$28*Продажи!T6 -> 0 | AA28: =$F$28*Продажи!U6 -> 0 | AB28: =$F$28*Продажи!V6 -> 0 | ... AF28: =$F$28*Продажи!Z6 -> 0 | AG28: =SUM(U28:AF28) -> 0 | AH28: =$G$28*Продажи!AB6 -> 0 | AI28: =$G$28*Продажи!AC6 -> 0 | AJ28: =$G$28*Продажи!AD6 -> 0 | AK28: =$G$28*Продажи!AE6 -> 0 | AL28: =$G$28*Продажи!AF6 -> 0 | AM28: =$G$28*Продажи!AG6 -> 0 | AN28: =$G$28*Продажи!AH6 -> 0 | AO28: =$G$28*Продажи!AI6 -> 0 | ... AS28: =$G$28*Продажи!AM6 -> 0 | AT28: =SUM(AH28:AS28) -> 0
A29: 2.11 | B29: Cправочно стоимость услуги | H29: ='Продукция и цена '!C5 -> 15000 | T29: =H29 -> 15000 | U29: ='Продукция и цена '!D5 -> 17250 | AG29: =SUM(U29:AF29) -> 17250 | AH29: ='Продукция и цена '!E5 -> 19837.5 | AT29: =SUM(AH29:AS29) -> 19837.5
A30: 3 | B30: ='Продукция и цена '!A6 -> Встроенная коммерция (доп. услуги) | C30: - | D30: - | E30: 1 год | F30: 2 год | G30: 3 год | H30: =SUM(H31:H40) -> 1200 | I30: =SUM(I31:I40) -> 1200 | J30: =SUM(J31:J40) -> 1200 | K30: =SUM(K31:K40) -> 1200 | L30: =SUM(L31:L40) -> 1200 | M30: =SUM(M31:M40) -> 1200 | N30: =SUM(N31:N40) -> 1200 | O30: =SUM(O31:O40) -> 1200 | ... S30: =SUM(S31:S40) -> 1200 | T30: =SUM(H30:S30) -> 14400 | U30: =SUM(U31:U40) -> 13800 | V30: =SUM(V31:V40) -> 13800 | W30: =SUM(W31:W40) -> 13800 | X30: =SUM(X31:X40) -> 13800 | Y30: =SUM(Y31:Y40) -> 16560 | Z30: =SUM(Z31:Z40) -> 16560 | AA30: =SUM(AA31:AA40) -> 20700 | AB30: =SUM(AB31:AB40) -> 19320 | ... AF30: =SUM(AF31:AF40) -> 24840 | AG30: =SUM(U30:AF30) -> 227700 | AH30: =SUM(AH31:AH40) -> 31740 | AI30: =SUM(AI31:AI40) -> 31740 | AJ30: =SUM(AJ31:AJ40) -> 31740 | AK30: =SUM(AK31:AK40) -> 31740 | AL30: =SUM(AL31:AL40) -> 36501 | AM30: =SUM(AM31:AM40) -> 36501 | AN30: =SUM(AN31:AN40) -> 42849 | AO30: =SUM(AO31:AO40) -> 39675 | ... AS30: =SUM(AS31:AS40) -> 42849 | AT30: =SUM(AH30:AS30) -> 450708
A31: 3.1 | B31: Хостинг + поддержка модуля | C31: 1200 | D31: 1 | E31: =C31*D31 -> 1200 | F31: =E31+E31*'Вводные данные'!$D$4 -> 1380 | G31: =F31+F31*'Вводные данные'!$E$4 -> 1587 | H31: =$E$31*Продажи!B7 -> 1200 | I31: =$E$31*Продажи!C7 -> 1200 | J31: =$E$31*Продажи!D7 -> 1200 | K31: =$E$31*Продажи!E7 -> 1200 | L31: =$E$31*Продажи!F7 -> 1200 | M31: =$E$31*Продажи!G7 -> 1200 | N31: =$E$31*Продажи!H7 -> 1200 | O31: =$E$31*Продажи!I7 -> 1200 | ... S31: =$E$31*Продажи!M7 -> 1200 | T31: =SUM(H31:S31) -> 14400 | U31: =$F$31*Продажи!O7 -> 13800 | V31: =$F$31*Продажи!P7 -> 13800 | W31: =$F$31*Продажи!Q7 -> 13800 | X31: =$F$31*Продажи!R7 -> 13800 | Y31: =$F$31*Продажи!S7 -> 16560 | Z31: =$F$31*Продажи!T7 -> 16560 | AA31: =$F$31*Продажи!U7 -> 20700 | AB31: =$F$31*Продажи!V7 -> 19320 | ... AF31: =$F$31*Продажи!Z7 -> 24840 | AG31: =SUM(U31:AF31) -> 227700 | AH31: =$G$31*Продажи!AB7 -> 31740 | AI31: =$G$31*Продажи!AC7 -> 31740 | AJ31: =$G$31*Продажи!AD7 -> 31740 | AK31: =$G$31*Продажи!AE7 -> 31740 | AL31: =$G$31*Продажи!AF7 -> 36501 | AM31: =$G$31*Продажи!AG7 -> 36501 | AN31: =$G$31*Продажи!AH7 -> 42849 | AO31: =$G$31*Продажи!AI7 -> 39675 | ... AS31: =$G$31*Продажи!AM7 -> 42849 | AT31: =SUM(AH31:AS31) -> 450708
A32: 3.2 | B32: Вышивка (логотип и т.д.) | C32: 0 | D32: 0 | E32: =C32*D32 -> 0 | F32: =E32+E32*'Вводные данные'!$D$4 -> 0 | G32: =F32+F32*'Вводные данные'!$E$4 -> 0 | H32: =$E$32*Продажи!B7 -> 0 | I32: =$E$32*Продажи!C7 -> 0 | J32: =$E$32*Продажи!D7 -> 0 | K32: =$E$32*Продажи!E7 -> 0 | L32: =$E$32*Продажи!F7 -> 0 | M32: =$E$32*Продажи!G7 -> 0 | N32: =$E$32*Продажи!H7 -> 0 | O32: =$E$32*Продажи!I7 -> 0 | ... S32: =$E$32*Продажи!M7 -> 0 | T32: =SUM(H32:S32) -> 0 | U32: =$F$32*Продажи!O7 -> 0 | V32: =$F$32*Продажи!P7 -> 0 | W32: =$F$32*Продажи!Q7 -> 0 | X32: =$F$32*Продажи!R7 -> 0 | Y32: =$F$32*Продажи!S7 -> 0 | Z32: =$F$32*Продажи!T7 -> 0 | AA32: =$F$32*Продажи!U7 -> 0 | AB32: =$F$32*Продажи!V7 -> 0 | ... AF32: =$F$32*Продажи!Z7 -> 0 | AG32: =SUM(U32:AF32) -> 0 | AH32: =$G$32*Продажи!AB7 -> 0 | AI32: =$G$32*Продажи!AC7 -> 0 | AJ32: =$G$32*Продажи!AD7 -> 0 | AK32: =$G$32*Продажи!AE7 -> 0 | AL32: =$G$32*Продажи!AF7 -> 0 | AM32: =$G$32*Продажи!AG7 -> 0 | AN32: =$G$32*Продажи!AH7 -> 0 | AO32: =$G$32*Продажи!AI7 -> 0 | ... AS32: =$G$32*Продажи!AM7 -> 0 | AT32: =SUM(AH32:AS32) -> 0
A33: 3.3 | B33: Доставка до потребителя | C33: 0 | D33: 0 | E33: =C33*D33 -> 0 | F33: =E33+E33*'Вводные данные'!$D$4 -> 0 | G33: =F33+F33*'Вводные данные'!$E$4 -> 0 | H33: =$E$33*Продажи!B7 -> 0 | I33: =$E$33*Продажи!C7 -> 0 | J33: =$E$33*Продажи!D7 -> 0 | K33: =$E$33*Продажи!E7 -> 0 | L33: =$E$33*Продажи!F7 -> 0 | M33: =$E$33*Продажи!G7 -> 0 | N33: =$E$33*Продажи!H7 -> 0 | O33: =$E$33*Продажи!I7 -> 0 | ... S33: =$E$33*Продажи!M7 -> 0 | T33: =SUM(H33:S33) -> 0 | U33: =$F$33*Продажи!O7 -> 0 | V33: =$F$33*Продажи!P7 -> 0 | W33: =$F$33*Продажи!Q7 -> 0 | X33: =$F$33*Продажи!R7 -> 0 | Y33: =$F$33*Продажи!S7 -> 0 | Z33: =$F$33*Продажи!T7 -> 0 | AA33: =$F$33*Продажи!U7 -> 0 | AB33: =$F$33*Продажи!V7 -> 0 | ... AF33: =$F$33*Продажи!Z7 -> 0 | AG33: =SUM(U33:AF33) -> 0 | AH33: =$G$33*Продажи!AB7 -> 0 | AI33: =$G$33*Продажи!AC7 -> 0 | AJ33: =$G$33*Продажи!AD7 -> 0 | AK33: =$G$33*Продажи!AE7 -> 0 | AL33: =$G$33*Продажи!AF7 -> 0 | AM33: =$G$33*Продажи!AG7 -> 0 | AN33: =$G$33*Продажи!AH7 -> 0 | AO33: =$G$33*Продажи!AI7 -> 0 | ... AS33: =$G$33*Продажи!AM7 -> 0 | AT33: =SUM(AH33:AS33) -> 0
A34: 3.4 | B34: Упаковочный пакет | C34: 0 | D34: 0 | E34: =C34*D34 -> 0 | F34: =E34+E34*'Вводные данные'!$D$4 -> 0 | G34: =F34+F34*'Вводные данные'!$E$4 -> 0 | H34: =$E$34*Продажи!B7 -> 0 | I34: =$E$34*Продажи!C7 -> 0 | J34: =$E$34*Продажи!D7 -> 0 | K34: =$E$34*Продажи!E7 -> 0 | L34: =$E$34*Продажи!F7 -> 0 | M34: =$E$34*Продажи!G7 -> 0 | N34: =$E$34*Продажи!H7 -> 0 | O34: =$E$34*Продажи!I7 -> 0 | ... S34: =$E$34*Продажи!M7 -> 0 | T34: =SUM(H34:S34) -> 0 | U34: =$F$34*Продажи!O7 -> 0 | V34: =$F$34*Продажи!P7 -> 0 | W34: =$F$34*Продажи!Q7 -> 0 | X34: =$F$34*Продажи!R7 -> 0 | Y34: =$F$34*Продажи!S7 -> 0 | Z34: =$F$34*Продажи!T7 -> 0 | AA34: =$F$34*Продажи!U7 -> 0 | AB34: =$F$34*Продажи!V7 -> 0 | ... AF34: =$F$34*Продажи!Z7 -> 0 | AG34: =SUM(U34:AF34) -> 0 | AH34: =$G$34*Продажи!AB7 -> 0 | AI34: =$G$34*Продажи!AC7 -> 0 | AJ34: =$G$34*Продажи!AD7 -> 0 | AK34: =$G$34*Продажи!AE7 -> 0 | AL34: =$G$34*Продажи!AF7 -> 0 | AM34: =$G$34*Продажи!AG7 -> 0 | AN34: =$G$34*Продажи!AH7 -> 0 | AO34: =$G$34*Продажи!AI7 -> 0 | ... AS34: =$G$34*Продажи!AM7 -> 0 | AT34: =SUM(AH34:AS34) -> 0
A35: 3.5 | B35: Сырье и материалы 5 | E35: =C35*D35 -> 0 | F35: =E35+E35*'Вводные данные'!$D$4 -> 0 | G35: =F35+F35*'Вводные данные'!$E$4 -> 0 | H35: =$E$35*Продажи!B7 -> 0 | I35: =$E$35*Продажи!C7 -> 0 | J35: =$E$35*Продажи!D7 -> 0 | K35: =$E$35*Продажи!E7 -> 0 | L35: =$E$35*Продажи!F7 -> 0 | M35: =$E$35*Продажи!G7 -> 0 | N35: =$E$35*Продажи!H7 -> 0 | O35: =$E$35*Продажи!I7 -> 0 | ... S35: =$E$35*Продажи!M7 -> 0 | T35: =SUM(H35:S35) -> 0 | U35: =$F$35*Продажи!O7 -> 0 | V35: =$F$35*Продажи!P7 -> 0 | W35: =$F$35*Продажи!Q7 -> 0 | X35: =$F$35*Продажи!R7 -> 0 | Y35: =$F$35*Продажи!S7 -> 0 | Z35: =$F$35*Продажи!T7 -> 0 | AA35: =$F$35*Продажи!U7 -> 0 | AB35: =$F$35*Продажи!V7 -> 0 | ... AF35: =$F$35*Продажи!Z7 -> 0 | AG35: =SUM(U35:AF35) -> 0 | AH35: =$G$35*Продажи!AB7 -> 0 | AI35: =$G$35*Продажи!AC7 -> 0 | AJ35: =$G$35*Продажи!AD7 -> 0 | AK35: =$G$35*Продажи!AE7 -> 0 | AL35: =$G$35*Продажи!AF7 -> 0 | AM35: =$G$35*Продажи!AG7 -> 0 | AN35: =$G$35*Продажи!AH7 -> 0 | AO35: =$G$35*Продажи!AI7 -> 0 | ... AS35: =$G$35*Продажи!AM7 -> 0 | AT35: =SUM(AH35:AS35) -> 0
A36: 3.6 | B36: Сырье и материалы 6 | E36: =C36*D36 -> 0 | F36: =E36+E36*'Вводные данные'!$D$4 -> 0 | G36: =F36+F36*'Вводные данные'!$E$4 -> 0 | H36: =$E$36*Продажи!B7 -> 0 | I36: =$E$36*Продажи!C7 -> 0 | J36: =$E$36*Продажи!D7 -> 0 | K36: =$E$36*Продажи!E7 -> 0 | L36: =$E$36*Продажи!F7 -> 0 | M36: =$E$36*Продажи!G7 -> 0 | N36: =$E$36*Продажи!H7 -> 0 | O36: =$E$36*Продажи!I7 -> 0 | ... S36: =$E$36*Продажи!M7 -> 0 | T36: =SUM(H36:S36) -> 0 | U36: =$F$36*Продажи!O7 -> 0 | V36: =$F$36*Продажи!P7 -> 0 | W36: =$F$36*Продажи!Q7 -> 0 | X36: =$F$36*Продажи!R7 -> 0 | Y36: =$F$36*Продажи!S7 -> 0 | Z36: =$F$36*Продажи!T7 -> 0 | AA36: =$F$36*Продажи!U7 -> 0 | AB36: =$F$36*Продажи!V7 -> 0 | ... AF36: =$F$36*Продажи!Z7 -> 0 | AG36: =SUM(U36:AF36) -> 0 | AH36: =$G$36*Продажи!AB7 -> 0 | AI36: =$G$36*Продажи!AC7 -> 0 | AJ36: =$G$36*Продажи!AD7 -> 0 | AK36: =$G$36*Продажи!AE7 -> 0 | AL36: =$G$36*Продажи!AF7 -> 0 | AM36: =$G$36*Продажи!AG7 -> 0 | AN36: =$G$36*Продажи!AH7 -> 0 | AO36: =$G$36*Продажи!AI7 -> 0 | ... AS36: =$G$36*Продажи!AM7 -> 0 | AT36: =SUM(AH36:AS36) -> 0
A37: 3.7 | B37: Сырье и материалы 7 | E37: =C37*D37 -> 0 | F37: =E37+E37*'Вводные данные'!$D$4 -> 0 | G37: =F37+F37*'Вводные данные'!$E$4 -> 0 | H37: =$E$37*Продажи!B7 -> 0 | I37: =$E$37*Продажи!C7 -> 0 | J37: =$E$37*Продажи!D7 -> 0 | K37: =$E$37*Продажи!E7 -> 0 | L37: =$E$37*Продажи!F7 -> 0 | M37: =$E$37*Продажи!G7 -> 0 | N37: =$E$37*Продажи!H7 -> 0 | O37: =$E$37*Продажи!I7 -> 0 | ... S37: =$E$37*Продажи!M7 -> 0 | T37: =SUM(H37:S37) -> 0 | U37: =$F$37*Продажи!O7 -> 0 | V37: =$F$37*Продажи!P7 -> 0 | W37: =$F$37*Продажи!Q7 -> 0 | X37: =$F$37*Продажи!R7 -> 0 | Y37: =$F$37*Продажи!S7 -> 0 | Z37: =$F$37*Продажи!T7 -> 0 | AA37: =$F$37*Продажи!U7 -> 0 | AB37: =$F$37*Продажи!V7 -> 0 | ... AF37: =$F$37*Продажи!Z7 -> 0 | AG37: =SUM(U37:AF37) -> 0 | AH37: =$G$37*Продажи!AB7 -> 0 | AI37: =$G$37*Продажи!AC7 -> 0 | AJ37: =$G$37*Продажи!AD7 -> 0 | AK37: =$G$37*Продажи!AE7 -> 0 | AL37: =$G$37*Продажи!AF7 -> 0 | AM37: =$G$37*Продажи!AG7 -> 0 | AN37: =$G$37*Продажи!AH7 -> 0 | AO37: =$G$37*Продажи!AI7 -> 0 | ... AS37: =$G$37*Продажи!AM7 -> 0 | AT37: =SUM(AH37:AS37) -> 0
A38: 3.8 | B38: Сырье и материалы 8 | E38: =C38*D38 -> 0 | F38: =E38+E38*'Вводные данные'!$D$4 -> 0 | G38: =F38+F38*'Вводные данные'!$E$4 -> 0 | H38: =$E$38*Продажи!B7 -> 0 | I38: =$E$38*Продажи!C7 -> 0 | J38: =$E$38*Продажи!D7 -> 0 | K38: =$E$38*Продажи!E7 -> 0 | L38: =$E$38*Продажи!F7 -> 0 | M38: =$E$38*Продажи!G7 -> 0 | N38: =$E$38*Продажи!H7 -> 0 | O38: =$E$38*Продажи!I7 -> 0 | ... S38: =$E$38*Продажи!M7 -> 0 | T38: =SUM(H38:S38) -> 0 | U38: =$F$38*Продажи!O7 -> 0 | V38: =$F$38*Продажи!P7 -> 0 | W38: =$F$38*Продажи!Q7 -> 0 | X38: =$F$38*Продажи!R7 -> 0 | Y38: =$F$38*Продажи!S7 -> 0 | Z38: =$F$38*Продажи!T7 -> 0 | AA38: =$F$38*Продажи!U7 -> 0 | AB38: =$F$38*Продажи!V7 -> 0 | ... AF38: =$F$38*Продажи!Z7 -> 0 | AG38: =SUM(U38:AF38) -> 0 | AH38: =$G$38*Продажи!AB7 -> 0 | AI38: =$G$38*Продажи!AC7 -> 0 | AJ38: =$G$38*Продажи!AD7 -> 0 | AK38: =$G$38*Продажи!AE7 -> 0 | AL38: =$G$38*Продажи!AF7 -> 0 | AM38: =$G$38*Продажи!AG7 -> 0 | AN38: =$G$38*Продажи!AH7 -> 0 | AO38: =$G$38*Продажи!AI7 -> 0 | ... AS38: =$G$38*Продажи!AM7 -> 0 | AT38: =SUM(AH38:AS38) -> 0
A39: 3.9 | B39: Сырье и материалы 9 | E39: =C39*D39 -> 0 | F39: =E39+E39*'Вводные данные'!$D$4 -> 0 | G39: =F39+F39*'Вводные данные'!$E$4 -> 0 | H39: =$E$39*Продажи!B7 -> 0 | I39: =$E$39*Продажи!C7 -> 0 | J39: =$E$39*Продажи!D7 -> 0 | K39: =$E$39*Продажи!E7 -> 0 | L39: =$E$39*Продажи!F7 -> 0 | M39: =$E$39*Продажи!G7 -> 0 | N39: =$E$39*Продажи!H7 -> 0 | O39: =$E$39*Продажи!I7 -> 0 | ... S39: =$E$39*Продажи!M7 -> 0 | T39: =SUM(H39:S39) -> 0 | U39: =$F$39*Продажи!O7 -> 0 | V39: =$F$39*Продажи!P7 -> 0 | W39: =$F$39*Продажи!Q7 -> 0 | X39: =$F$39*Продажи!R7 -> 0 | Y39: =$F$39*Продажи!S7 -> 0 | Z39: =$F$39*Продажи!T7 -> 0 | AA39: =$F$39*Продажи!U7 -> 0 | AB39: =$F$39*Продажи!V7 -> 0 | ... AF39: =$F$39*Продажи!Z7 -> 0 | AG39: =SUM(U39:AF39) -> 0 | AH39: =$G$39*Продажи!AB7 -> 0 | AI39: =$G$39*Продажи!AC7 -> 0 | AJ39: =$G$39*Продажи!AD7 -> 0 | AK39: =$G$39*Продажи!AE7 -> 0 | AL39: =$G$39*Продажи!AF7 -> 0 | AM39: =$G$39*Продажи!AG7 -> 0 | AN39: =$G$39*Продажи!AH7 -> 0 | AO39: =$G$39*Продажи!AI7 -> 0 | ... AS39: =$G$39*Продажи!AM7 -> 0 | AT39: =SUM(AH39:AS39) -> 0
A40: 3.10 | B40: Сырье и материалы 10 | E40: =C40*D40 -> 0 | F40: =E40+E40*'Вводные данные'!$D$4 -> 0 | G40: =F40+F40*'Вводные данные'!$E$4 -> 0 | H40: =$E$40*Продажи!B7 -> 0 | I40: =$E$40*Продажи!C7 -> 0 | J40: =$E$40*Продажи!D7 -> 0 | K40: =$E$40*Продажи!E7 -> 0 | L40: =$E$40*Продажи!F7 -> 0 | M40: =$E$40*Продажи!G7 -> 0 | N40: =$E$40*Продажи!H7 -> 0 | O40: =$E$40*Продажи!I7 -> 0 | ... S40: =$E$40*Продажи!M7 -> 0 | T40: =SUM(H40:S40) -> 0 | U40: =$F$40*Продажи!O7 -> 0 | V40: =$F$40*Продажи!P7 -> 0 | W40: =$F$40*Продажи!Q7 -> 0 | X40: =$F$40*Продажи!R7 -> 0 | Y40: =$F$40*Продажи!S7 -> 0 | Z40: =$F$40*Продажи!T7 -> 0 | AA40: =$F$40*Продажи!U7 -> 0 | AB40: =$F$40*Продажи!V7 -> 0 | ... AF40: =$F$40*Продажи!Z7 -> 0 | AG40: =SUM(U40:AF40) -> 0 | AH40: =$G$40*Продажи!AB7 -> 0 | AI40: =$G$40*Продажи!AC7 -> 0 | AJ40: =$G$40*Продажи!AD7 -> 0 | AK40: =$G$40*Продажи!AE7 -> 0 | AL40: =$G$40*Продажи!AF7 -> 0 | AM40: =$G$40*Продажи!AG7 -> 0 | AN40: =$G$40*Продажи!AH7 -> 0 | AO40: =$G$40*Продажи!AI7 -> 0 | ... AS40: =$G$40*Продажи!AM7 -> 0 | AT40: =SUM(AH40:AS40) -> 0
A41: 3.11 | B41: Cправочно стоимость услуги | H41: ='Продукция и цена '!C6 -> 9000 | T41: =H41 -> 9000 | U41: ='Продукция и цена '!D6 -> 10350 | AG41: =SUM(U41:AF41) -> 10350 | AH41: ='Продукция и цена '!E6 -> 11902.5 | AT41: =SUM(AH41:AS41) -> 11902.5
A42: 4 | B42: ='Продукция и цена '!A7 -> Установка и настройка системы, онбординг | C42: - | D42: - | E42: 1 год | F42: 2 год | G42: 3 год | H42: =SUM(H43:H52) -> 45000 | I42: =SUM(I43:I52) -> 0 | J42: =SUM(J43:J52) -> 90000 | K42: =SUM(K43:K52) -> 0 | L42: =SUM(L43:L52) -> 45000 | M42: =SUM(M43:M52) -> 45000 | N42: =SUM(N43:N52) -> 45000 | O42: =SUM(O43:O52) -> 45000 | ... S42: =SUM(S43:S52) -> 45000 | T42: =SUM(H42:S42) -> 495000 | U42: =SUM(U43:U52) -> 103500 | V42: =SUM(V43:V52) -> 155250 | W42: =SUM(W43:W52) -> 103500 | X42: =SUM(X43:X52) -> 207000 | Y42: =SUM(Y43:Y52) -> 103500 | Z42: =SUM(Z43:Z52) -> 155250 | AA42: =SUM(AA43:AA52) -> 103500 | AB42: =SUM(AB43:AB52) -> 207000 | ... AF42: =SUM(AF43:AF52) -> 207000 | AG42: =SUM(U42:AF42) -> 1707750 | AH42: =SUM(AH43:AH52) -> 357075 | AI42: =SUM(AI43:AI52) -> 357075 | AJ42: =SUM(AJ43:AJ52) -> 238050 | AK42: =SUM(AK43:AK52) -> 357075 | AL42: =SUM(AL43:AL52) -> 238050 | AM42: =SUM(AM43:AM52) -> 357075 | AN42: =SUM(AN43:AN52) -> 238050 | AO42: =SUM(AO43:AO52) -> 357075 | ... AS42: =SUM(AS43:AS52) -> 357075 | AT42: =SUM(AH42:AS42) -> 3689775
A43: 4.1 | B43: Менеджер+разработчик+тестировщик | C43: 45000 | D43: 1 | E43: =C43*D43 -> 45000 | F43: =E43+E43*'Вводные данные'!$D$4 -> 51750 | G43: =F43+F43*'Вводные данные'!$E$4 -> 59512.5 | H43: =$E$43*Продажи!B8 -> 45000 | I43: =$E$43*Продажи!C8 -> 0 | J43: =$E$43*Продажи!D8 -> 90000 | K43: =$E$43*Продажи!E8 -> 0 | L43: =$E$43*Продажи!F8 -> 45000 | M43: =$E$43*Продажи!G8 -> 45000 | N43: =$E$43*Продажи!H8 -> 45000 | O43: =$E$43*Продажи!I8 -> 45000 | ... S43: =$E$43*Продажи!M8 -> 45000 | T43: =SUM(H43:S43) -> 495000 | U43: =$F$43*Продажи!O8 -> 103500 | V43: =$F$43*Продажи!P8 -> 155250 | W43: =$F$43*Продажи!Q8 -> 103500 | X43: =$F$43*Продажи!R8 -> 207000 | Y43: =$F$43*Продажи!S8 -> 103500 | Z43: =$F$43*Продажи!T8 -> 155250 | AA43: =$F$43*Продажи!U8 -> 103500 | AB43: =$F$43*Продажи!V8 -> 207000 | ... AF43: =$F$43*Продажи!Z8 -> 207000 | AG43: =SUM(U43:AF43) -> 1707750 | AH43: =$G$43*Продажи!AB8 -> 357075 | AI43: =$G$43*Продажи!AC8 -> 357075 | AJ43: =$G$43*Продажи!AD8 -> 238050 | AK43: =$G$43*Продажи!AE8 -> 357075 | AL43: =$G$43*Продажи!AF8 -> 238050 | AM43: =$G$43*Продажи!AG8 -> 357075 | AN43: =$G$43*Продажи!AH8 -> 238050 | AO43: =$G$43*Продажи!AI8 -> 357075 | ... AS43: =$G$43*Продажи!AM8 -> 357075 | AT43: =SUM(AH43:AS43) -> 3689775
A44: 4.2 | B44: 0 | C44: 0 | D44: 0 | E44: =C44*D44 -> 0 | F44: =E44+E44*'Вводные данные'!$D$4 -> 0 | G44: =F44+F44*'Вводные данные'!$E$4 -> 0 | H44: =$E$44*Продажи!B8 -> 0 | I44: =$E$44*Продажи!C8 -> 0 | J44: =$E$44*Продажи!D8 -> 0 | K44: =$E$44*Продажи!E8 -> 0 | L44: =$E$44*Продажи!F8 -> 0 | M44: =$E$44*Продажи!G8 -> 0 | N44: =$E$44*Продажи!H8 -> 0 | O44: =$E$44*Продажи!I8 -> 0 | ... S44: =$E$44*Продажи!M8 -> 0 | T44: =SUM(H44:S44) -> 0 | U44: =$F$44*Продажи!O8 -> 0 | V44: =$F$44*Продажи!P8 -> 0 | W44: =$F$44*Продажи!Q8 -> 0 | X44: =$F$44*Продажи!R8 -> 0 | Y44: =$F$44*Продажи!S8 -> 0 | Z44: =$F$44*Продажи!T8 -> 0 | AA44: =$F$44*Продажи!U8 -> 0 | AB44: =$F$44*Продажи!V8 -> 0 | ... AF44: =$F$44*Продажи!Z8 -> 0 | AG44: =SUM(U44:AF44) -> 0 | AH44: =$G$44*Продажи!AB8 -> 0 | AI44: =$G$44*Продажи!AC8 -> 0 | AJ44: =$G$44*Продажи!AD8 -> 0 | AK44: =$G$44*Продажи!AE8 -> 0 | AL44: =$G$44*Продажи!AF8 -> 0 | AM44: =$G$44*Продажи!AG8 -> 0 | AN44: =$G$44*Продажи!AH8 -> 0 | AO44: =$G$44*Продажи!AI8 -> 0 | ... AS44: =$G$44*Продажи!AM8 -> 0 | AT44: =SUM(AH44:AS44) -> 0
A45: 4.3 | B45: 0 | C45: 0 | D45: 0 | E45: =C45*D45 -> 0 | F45: =E45+E45*'Вводные данные'!$D$4 -> 0 | G45: =F45+F45*'Вводные данные'!$E$4 -> 0 | H45: =$E$45*Продажи!B8 -> 0 | I45: =$E$45*Продажи!C8 -> 0 | J45: =$E$45*Продажи!D8 -> 0 | K45: =$E$45*Продажи!E8 -> 0 | L45: =$E$45*Продажи!F8 -> 0 | M45: =$E$45*Продажи!G8 -> 0 | N45: =$E$45*Продажи!H8 -> 0 | O45: =$E$45*Продажи!I8 -> 0 | ... S45: =$E$45*Продажи!M8 -> 0 | T45: =SUM(H45:S45) -> 0 | U45: =$F$45*Продажи!O8 -> 0 | V45: =$F$45*Продажи!P8 -> 0 | W45: =$F$45*Продажи!Q8 -> 0 | X45: =$F$45*Продажи!R8 -> 0 | Y45: =$F$45*Продажи!S8 -> 0 | Z45: =$F$45*Продажи!T8 -> 0 | AA45: =$F$45*Продажи!U8 -> 0 | AB45: =$F$45*Продажи!V8 -> 0 | ... AF45: =$F$45*Продажи!Z8 -> 0 | AG45: =SUM(U45:AF45) -> 0 | AH45: =$G$45*Продажи!AB8 -> 0 | AI45: =$G$45*Продажи!AC8 -> 0 | AJ45: =$G$45*Продажи!AD8 -> 0 | AK45: =$G$45*Продажи!AE8 -> 0 | AL45: =$G$45*Продажи!AF8 -> 0 | AM45: =$G$45*Продажи!AG8 -> 0 | AN45: =$G$45*Продажи!AH8 -> 0 | AO45: =$G$45*Продажи!AI8 -> 0 | ... AS45: =$G$45*Продажи!AM8 -> 0 | AT45: =SUM(AH45:AS45) -> 0
A46: 4.4 | B46: 0 | C46: 0 | D46: 0 | E46: =C46*D46 -> 0 | F46: =E46+E46*'Вводные данные'!$D$4 -> 0 | G46: =F46+F46*'Вводные данные'!$E$4 -> 0 | H46: =$E$46*Продажи!B8 -> 0 | I46: =$E$46*Продажи!C8 -> 0 | J46: =$E$46*Продажи!D8 -> 0 | K46: =$E$46*Продажи!E8 -> 0 | L46: =$E$46*Продажи!F8 -> 0 | M46: =$E$46*Продажи!G8 -> 0 | N46: =$E$46*Продажи!H8 -> 0 | O46: =$E$46*Продажи!I8 -> 0 | ... S46: =$E$46*Продажи!M8 -> 0 | T46: =SUM(H46:S46) -> 0 | U46: =$F$46*Продажи!O8 -> 0 | V46: =$F$46*Продажи!P8 -> 0 | W46: =$F$46*Продажи!Q8 -> 0 | X46: =$F$46*Продажи!R8 -> 0 | Y46: =$F$46*Продажи!S8 -> 0 | Z46: =$F$46*Продажи!T8 -> 0 | AA46: =$F$46*Продажи!U8 -> 0 | AB46: =$F$46*Продажи!V8 -> 0 | ... AF46: =$F$46*Продажи!Z8 -> 0 | AG46: =SUM(U46:AF46) -> 0 | AH46: =$G$46*Продажи!AB8 -> 0 | AI46: =$G$46*Продажи!AC8 -> 0 | AJ46: =$G$46*Продажи!AD8 -> 0 | AK46: =$G$46*Продажи!AE8 -> 0 | AL46: =$G$46*Продажи!AF8 -> 0 | AM46: =$G$46*Продажи!AG8 -> 0 | AN46: =$G$46*Продажи!AH8 -> 0 | AO46: =$G$46*Продажи!AI8 -> 0 | ... AS46: =$G$46*Продажи!AM8 -> 0 | AT46: =SUM(AH46:AS46) -> 0
A47: 4.5 | B47: Сырье и материалы 5 | E47: =C47*D47 -> 0 | F47: =E47+E47*'Вводные данные'!$D$4 -> 0 | G47: =F47+F47*'Вводные данные'!$E$4 -> 0 | H47: =$E$47*Продажи!B8 -> 0 | I47: =$E$47*Продажи!C8 -> 0 | J47: =$E$47*Продажи!D8 -> 0 | K47: =$E$47*Продажи!E8 -> 0 | L47: =$E$47*Продажи!F8 -> 0 | M47: =$E$47*Продажи!G8 -> 0 | N47: =$E$47*Продажи!H8 -> 0 | O47: =$E$47*Продажи!I8 -> 0 | ... S47: =$E$47*Продажи!M8 -> 0 | T47: =SUM(H47:S47) -> 0 | U47: =$F$47*Продажи!O8 -> 0 | V47: =$F$47*Продажи!P8 -> 0 | W47: =$F$47*Продажи!Q8 -> 0 | X47: =$F$47*Продажи!R8 -> 0 | Y47: =$F$47*Продажи!S8 -> 0 | Z47: =$F$47*Продажи!T8 -> 0 | AA47: =$F$47*Продажи!U8 -> 0 | AB47: =$F$47*Продажи!V8 -> 0 | ... AF47: =$F$47*Продажи!Z8 -> 0 | AG47: =SUM(U47:AF47) -> 0 | AH47: =$G$47*Продажи!AB8 -> 0 | AI47: =$G$47*Продажи!AC8 -> 0 | AJ47: =$G$47*Продажи!AD8 -> 0 | AK47: =$G$47*Продажи!AE8 -> 0 | AL47: =$G$47*Продажи!AF8 -> 0 | AM47: =$G$47*Продажи!AG8 -> 0 | AN47: =$G$47*Продажи!AH8 -> 0 | AO47: =$G$47*Продажи!AI8 -> 0 | ... AS47: =$G$47*Продажи!AM8 -> 0 | AT47: =SUM(AH47:AS47) -> 0
A48: 4.6 | B48: Сырье и материалы 6 | E48: =C48*D48 -> 0 | F48: =E48+E48*'Вводные данные'!$D$4 -> 0 | G48: =F48+F48*'Вводные данные'!$E$4 -> 0 | H48: =$E$48*Продажи!B8 -> 0 | I48: =$E$48*Продажи!C8 -> 0 | J48: =$E$48*Продажи!D8 -> 0 | K48: =$E$48*Продажи!E8 -> 0 | L48: =$E$48*Продажи!F8 -> 0 | M48: =$E$48*Продажи!G8 -> 0 | N48: =$E$48*Продажи!H8 -> 0 | O48: =$E$48*Продажи!I8 -> 0 | ... S48: =$E$48*Продажи!M8 -> 0 | T48: =SUM(H48:S48) -> 0 | U48: =$F$48*Продажи!O8 -> 0 | V48: =$F$48*Продажи!P8 -> 0 | W48: =$F$48*Продажи!Q8 -> 0 | X48: =$F$48*Продажи!R8 -> 0 | Y48: =$F$48*Продажи!S8 -> 0 | Z48: =$F$48*Продажи!T8 -> 0 | AA48: =$F$48*Продажи!U8 -> 0 | AB48: =$F$48*Продажи!V8 -> 0 | ... AF48: =$F$48*Продажи!Z8 -> 0 | AG48: =SUM(U48:AF48) -> 0 | AH48: =$G$48*Продажи!AB8 -> 0 | AI48: =$G$48*Продажи!AC8 -> 0 | AJ48: =$G$48*Продажи!AD8 -> 0 | AK48: =$G$48*Продажи!AE8 -> 0 | AL48: =$G$48*Продажи!AF8 -> 0 | AM48: =$G$48*Продажи!AG8 -> 0 | AN48: =$G$48*Продажи!AH8 -> 0 | AO48: =$G$48*Продажи!AI8 -> 0 | ... AS48: =$G$48*Продажи!AM8 -> 0 | AT48: =SUM(AH48:AS48) -> 0
A49: 4.7 | B49: Сырье и материалы 7 | E49: =C49*D49 -> 0 | F49: =E49+E49*'Вводные данные'!$D$4 -> 0 | G49: =F49+F49*'Вводные данные'!$E$4 -> 0 | H49: =$E$49*Продажи!B8 -> 0 | I49: =$E$49*Продажи!C8 -> 0 | J49: =$E$49*Продажи!D8 -> 0 | K49: =$E$49*Продажи!E8 -> 0 | L49: =$E$49*Продажи!F8 -> 0 | M49: =$E$49*Продажи!G8 -> 0 | N49: =$E$49*Продажи!H8 -> 0 | O49: =$E$49*Продажи!I8 -> 0 | ... S49: =$E$49*Продажи!M8 -> 0 | T49: =SUM(H49:S49) -> 0 | U49: =$F$49*Продажи!O8 -> 0 | V49: =$F$49*Продажи!P8 -> 0 | W49: =$F$49*Продажи!Q8 -> 0 | X49: =$F$49*Продажи!R8 -> 0 | Y49: =$F$49*Продажи!S8 -> 0 | Z49: =$F$49*Продажи!T8 -> 0 | AA49: =$F$49*Продажи!U8 -> 0 | AB49: =$F$49*Продажи!V8 -> 0 | ... AF49: =$F$49*Продажи!Z8 -> 0 | AG49: =SUM(U49:AF49) -> 0 | AH49: =$G$49*Продажи!AB8 -> 0 | AI49: =$G$49*Продажи!AC8 -> 0 | AJ49: =$G$49*Продажи!AD8 -> 0 | AK49: =$G$49*Продажи!AE8 -> 0 | AL49: =$G$49*Продажи!AF8 -> 0 | AM49: =$G$49*Продажи!AG8 -> 0 | AN49: =$G$49*Продажи!AH8 -> 0 | AO49: =$G$49*Продажи!AI8 -> 0 | ... AS49: =$G$49*Продажи!AM8 -> 0 | AT49: =SUM(AH49:AS49) -> 0
A50: 4.8 | B50: Сырье и материалы 8 | E50: =C50*D50 -> 0 | F50: =E50+E50*'Вводные данные'!$D$4 -> 0 | G50: =F50+F50*'Вводные данные'!$E$4 -> 0 | H50: =$E$50*Продажи!B8 -> 0 | I50: =$E$50*Продажи!C8 -> 0 | J50: =$E$50*Продажи!D8 -> 0 | K50: =$E$50*Продажи!E8 -> 0 | L50: =$E$50*Продажи!F8 -> 0 | M50: =$E$50*Продажи!G8 -> 0 | N50: =$E$50*Продажи!H8 -> 0 | O50: =$E$50*Продажи!I8 -> 0 | ... S50: =$E$50*Продажи!M8 -> 0 | T50: =SUM(H50:S50) -> 0 | U50: =$F$50*Продажи!O8 -> 0 | V50: =$F$50*Продажи!P8 -> 0 | W50: =$F$50*Продажи!Q8 -> 0 | X50: =$F$50*Продажи!R8 -> 0 | Y50: =$F$50*Продажи!S8 -> 0 | Z50: =$F$50*Продажи!T8 -> 0 | AA50: =$F$50*Продажи!U8 -> 0 | AB50: =$F$50*Продажи!V8 -> 0 | ... AF50: =$F$50*Продажи!Z8 -> 0 | AG50: =SUM(U50:AF50) -> 0 | AH50: =$G$50*Продажи!AB8 -> 0 | AI50: =$G$50*Продажи!AC8 -> 0 | AJ50: =$G$50*Продажи!AD8 -> 0 | AK50: =$G$50*Продажи!AE8 -> 0 | AL50: =$G$50*Продажи!AF8 -> 0 | AM50: =$G$50*Продажи!AG8 -> 0 | AN50: =$G$50*Продажи!AH8 -> 0 | AO50: =$G$50*Продажи!AI8 -> 0 | ... AS50: =$G$50*Продажи!AM8 -> 0 | AT50: =SUM(AH50:AS50) -> 0
A51: 4.9 | B51: Сырье и материалы 9 | E51: =C51*D51 -> 0 | F51: =E51+E51*'Вводные данные'!$D$4 -> 0 | G51: =F51+F51*'Вводные данные'!$E$4 -> 0 | H51: =$E$51*Продажи!B8 -> 0 | I51: =$E$51*Продажи!C8 -> 0 | J51: =$E$51*Продажи!D8 -> 0 | K51: =$E$51*Продажи!E8 -> 0 | L51: =$E$51*Продажи!F8 -> 0 | M51: =$E$51*Продажи!G8 -> 0 | N51: =$E$51*Продажи!H8 -> 0 | O51: =$E$51*Продажи!I8 -> 0 | ... S51: =$E$51*Продажи!M8 -> 0 | T51: =SUM(H51:S51) -> 0 | U51: =$F$51*Продажи!O8 -> 0 | V51: =$F$51*Продажи!P8 -> 0 | W51: =$F$51*Продажи!Q8 -> 0 | X51: =$F$51*Продажи!R8 -> 0 | Y51: =$F$51*Продажи!S8 -> 0 | Z51: =$F$51*Продажи!T8 -> 0 | AA51: =$F$51*Продажи!U8 -> 0 | AB51: =$F$51*Продажи!V8 -> 0 | ... AF51: =$F$51*Продажи!Z8 -> 0 | AG51: =SUM(U51:AF51) -> 0 | AH51: =$G$51*Продажи!AB8 -> 0 | AI51: =$G$51*Продажи!AC8 -> 0 | AJ51: =$G$51*Продажи!AD8 -> 0 | AK51: =$G$51*Продажи!AE8 -> 0 | AL51: =$G$51*Продажи!AF8 -> 0 | AM51: =$G$51*Продажи!AG8 -> 0 | AN51: =$G$51*Продажи!AH8 -> 0 | AO51: =$G$51*Продажи!AI8 -> 0 | ... AS51: =$G$51*Продажи!AM8 -> 0 | AT51: =SUM(AH51:AS51) -> 0
A52: 4.10 | B52: Сырье и материалы 10 | E52: =C52*D52 -> 0 | F52: =E52+E52*'Вводные данные'!$D$4 -> 0 | G52: =F52+F52*'Вводные данные'!$E$4 -> 0 | H52: =$E$52*Продажи!B8 -> 0 | I52: =$E$52*Продажи!C8 -> 0 | J52: =$E$52*Продажи!D8 -> 0 | K52: =$E$52*Продажи!E8 -> 0 | L52: =$E$52*Продажи!F8 -> 0 | M52: =$E$52*Продажи!G8 -> 0 | N52: =$E$52*Продажи!H8 -> 0 | O52: =$E$52*Продажи!I8 -> 0 | ... S52: =$E$52*Продажи!M8 -> 0 | T52: =SUM(H52:S52) -> 0 | U52: =$F$52*Продажи!O8 -> 0 | V52: =$F$52*Продажи!P8 -> 0 | W52: =$F$52*Продажи!Q8 -> 0 | X52: =$F$52*Продажи!R8 -> 0 | Y52: =$F$52*Продажи!S8 -> 0 | Z52: =$F$52*Продажи!T8 -> 0 | AA52: =$F$52*Продажи!U8 -> 0 | AB52: =$F$52*Продажи!V8 -> 0 | ... AF52: =$F$52*Продажи!Z8 -> 0 | AG52: =SUM(U52:AF52) -> 0 | AH52: =$G$52*Продажи!AB8 -> 0 | AI52: =$G$52*Продажи!AC8 -> 0 | AJ52: =$G$52*Продажи!AD8 -> 0 | AK52: =$G$52*Продажи!AE8 -> 0 | AL52: =$G$52*Продажи!AF8 -> 0 | AM52: =$G$52*Продажи!AG8 -> 0 | AN52: =$G$52*Продажи!AH8 -> 0 | AO52: =$G$52*Продажи!AI8 -> 0 | ... AS52: =$G$52*Продажи!AM8 -> 0 | AT52: =SUM(AH52:AS52) -> 0
A53: 4.11 | B53: Cправочно стоимость услуги | H53: ='Продукция и цена '!C7 -> 250000 | T53: =H53 -> 250000 | U53: ='Продукция и цена '!D7 -> 287500 | AG53: =SUM(U53:AF53) -> 287500 | AH53: ='Продукция и цена '!E7 -> 330625 | AT53: =SUM(AH53:AS53) -> 330625
A54: 5 | B54: ='Продукция и цена '!A8 -> Реклама/партнёрства | C54: - | D54: - | E54: 1 год | F54: 2 год | G54: 3 год | H54: =SUM(H55:H64) -> 0 | I54: =SUM(I55:I64) -> 0 | J54: =SUM(J55:J64) -> 0 | K54: =SUM(K55:K64) -> 1300 | L54: =SUM(L55:L64) -> 1300 | M54: =SUM(M55:M64) -> 1300 | N54: =SUM(N55:N64) -> 1300 | O54: =SUM(O55:O64) -> 1300 | ... S54: =SUM(S55:S64) -> 1300 | T54: =SUM(H54:S54) -> 11700 | U54: =SUM(U55:U64) -> 1495 | V54: =SUM(V55:V64) -> 1495 | W54: =SUM(W55:W64) -> 1495 | X54: =SUM(X55:X64) -> 1495 | Y54: =SUM(Y55:Y64) -> 1495 | Z54: =SUM(Z55:Z64) -> 1495 | AA54: =SUM(AA55:AA64) -> 2990 | AB54: =SUM(AB55:AB64) -> 2990 | ... AF54: =SUM(AF55:AF64) -> 2990 | AG54: =SUM(U54:AF54) -> 23920 | AH54: =SUM(AH55:AH64) -> 3438.5 | AI54: =SUM(AI55:AI64) -> 3438.5 | AJ54: =SUM(AJ55:AJ64) -> 3438.5 | AK54: =SUM(AK55:AK64) -> 3438.5 | AL54: =SUM(AL55:AL64) -> 3438.5 | AM54: =SUM(AM55:AM64) -> 1719.25 | AN54: =SUM(AN55:AN64) -> 3438.5 | AO54: =SUM(AO55:AO64) -> 3438.5 | ... AS54: =SUM(AS55:AS64) -> 3438.5 | AT54: =SUM(AH54:AS54) -> 37823.5
A55: 5.1 | B55: Дизайн+настройка | C55: 1300 | D55: 1 | E55: =C55*D55 -> 1300 | F55: =E55+E55*'Вводные данные'!$D$4 -> 1495 | G55: =F55+F55*'Вводные данные'!$E$4 -> 1719.25 | H55: =$E$55*Продажи!B9 -> 0 | I55: =$E$55*Продажи!C9 -> 0 | J55: =$E$55*Продажи!D9 -> 0 | K55: =$E$55*Продажи!E9 -> 1300 | L55: =$E$55*Продажи!F9 -> 1300 | M55: =$E$55*Продажи!G9 -> 1300 | N55: =$E$55*Продажи!H9 -> 1300 | O55: =$E$55*Продажи!I9 -> 1300 | ... S55: =$E$55*Продажи!M9 -> 1300 | T55: =SUM(H55:S55) -> 11700 | U55: =$F$55*Продажи!O9 -> 1495 | V55: =$F$55*Продажи!P9 -> 1495 | W55: =$F$55*Продажи!Q9 -> 1495 | X55: =$F$55*Продажи!R9 -> 1495 | Y55: =$F$55*Продажи!S9 -> 1495 | Z55: =$F$55*Продажи!T9 -> 1495 | AA55: =$F$55*Продажи!U9 -> 2990 | AB55: =$F$55*Продажи!V9 -> 2990 | ... AF55: =$F$55*Продажи!Z9 -> 2990 | AG55: =SUM(U55:AF55) -> 23920 | AH55: =$G$55*Продажи!AB9 -> 3438.5 | AI55: =$G$55*Продажи!AC9 -> 3438.5 | AJ55: =$G$55*Продажи!AD9 -> 3438.5 | AK55: =$G$55*Продажи!AE9 -> 3438.5 | AL55: =$G$55*Продажи!AF9 -> 3438.5 | AM55: =$G$55*Продажи!AG9 -> 1719.25 | AN55: =$G$55*Продажи!AH9 -> 3438.5 | AO55: =$G$55*Продажи!AI9 -> 3438.5 | ... AS55: =$G$55*Продажи!AM9 -> 3438.5 | AT55: =SUM(AH55:AS55) -> 37823.5
A56: 5.2 | E56: =C56*D56 -> 0 | F56: =E56+E56*'Вводные данные'!$D$4 -> 0 | G56: =F56+F56*'Вводные данные'!$E$4 -> 0 | H56: =$E$56*Продажи!B9 -> 0 | I56: =$E$56*Продажи!C9 -> 0 | J56: =$E$56*Продажи!D9 -> 0 | K56: =$E$56*Продажи!E9 -> 0 | L56: =$E$56*Продажи!F9 -> 0 | M56: =$E$56*Продажи!G9 -> 0 | N56: =$E$56*Продажи!H9 -> 0 | O56: =$E$56*Продажи!I9 -> 0 | ... S56: =$E$56*Продажи!M9 -> 0 | T56: =SUM(H56:S56) -> 0 | U56: =$F$56*Продажи!O9 -> 0 | V56: =$F$56*Продажи!P9 -> 0 | W56: =$F$56*Продажи!Q9 -> 0 | X56: =$F$56*Продажи!R9 -> 0 | Y56: =$F$56*Продажи!S9 -> 0 | Z56: =$F$56*Продажи!T9 -> 0 | AA56: =$F$56*Продажи!U9 -> 0 | AB56: =$F$56*Продажи!V9 -> 0 | ... AF56: =$F$56*Продажи!Z9 -> 0 | AG56: =SUM(U56:AF56) -> 0 | AH56: =$G$56*Продажи!AB9 -> 0 | AI56: =$G$56*Продажи!AC9 -> 0 | AJ56: =$G$56*Продажи!AD9 -> 0 | AK56: =$G$56*Продажи!AE9 -> 0 | AL56: =$G$56*Продажи!AF9 -> 0 | AM56: =$G$56*Продажи!AG9 -> 0 | AN56: =$G$56*Продажи!AH9 -> 0 | AO56: =$G$56*Продажи!AI9 -> 0 | ... AS56: =$G$56*Продажи!AM9 -> 0 | AT56: =SUM(AH56:AS56) -> 0
A57: 5.3 | E57: =C57*D57 -> 0 | F57: =E57+E57*'Вводные данные'!$D$4 -> 0 | G57: =F57+F57*'Вводные данные'!$E$4 -> 0 | H57: =$E$57*Продажи!B9 -> 0 | I57: =$E$57*Продажи!C9 -> 0 | J57: =$E$57*Продажи!D9 -> 0 | K57: =$E$57*Продажи!E9 -> 0 | L57: =$E$57*Продажи!F9 -> 0 | M57: =$E$57*Продажи!G9 -> 0 | N57: =$E$57*Продажи!H9 -> 0 | O57: =$E$57*Продажи!I9 -> 0 | ... S57: =$E$57*Продажи!M9 -> 0 | T57: =SUM(H57:S57) -> 0 | U57: =$F$57*Продажи!O9 -> 0 | V57: =$F$57*Продажи!P9 -> 0 | W57: =$F$57*Продажи!Q9 -> 0 | X57: =$F$57*Продажи!R9 -> 0 | Y57: =$F$57*Продажи!S9 -> 0 | Z57: =$F$57*Продажи!T9 -> 0 | AA57: =$F$57*Продажи!U9 -> 0 | AB57: =$F$57*Продажи!V9 -> 0 | ... AF57: =$F$57*Продажи!Z9 -> 0 | AG57: =SUM(U57:AF57) -> 0 | AH57: =$G$57*Продажи!AB9 -> 0 | AI57: =$G$57*Продажи!AC9 -> 0 | AJ57: =$G$57*Продажи!AD9 -> 0 | AK57: =$G$57*Продажи!AE9 -> 0 | AL57: =$G$57*Продажи!AF9 -> 0 | AM57: =$G$57*Продажи!AG9 -> 0 | AN57: =$G$57*Продажи!AH9 -> 0 | AO57: =$G$57*Продажи!AI9 -> 0 | ... AS57: =$G$57*Продажи!AM9 -> 0 | AT57: =SUM(AH57:AS57) -> 0
A58: 5.4 | B58: Сырье и материалы 4 | E58: =C58*D58 -> 0 | F58: =E58+E58*'Вводные данные'!$D$4 -> 0 | G58: =F58+F58*'Вводные данные'!$E$4 -> 0 | H58: =$E$58*Продажи!B9 -> 0 | I58: =$E$58*Продажи!C9 -> 0 | J58: =$E$58*Продажи!D9 -> 0 | K58: =$E$58*Продажи!E9 -> 0 | L58: =$E$58*Продажи!F9 -> 0 | M58: =$E$58*Продажи!G9 -> 0 | N58: =$E$58*Продажи!H9 -> 0 | O58: =$E$58*Продажи!I9 -> 0 | ... S58: =$E$58*Продажи!M9 -> 0 | T58: =SUM(H58:S58) -> 0 | U58: =$F$58*Продажи!O9 -> 0 | V58: =$F$58*Продажи!P9 -> 0 | W58: =$F$58*Продажи!Q9 -> 0 | X58: =$F$58*Продажи!R9 -> 0 | Y58: =$F$58*Продажи!S9 -> 0 | Z58: =$F$58*Продажи!T9 -> 0 | AA58: =$F$58*Продажи!U9 -> 0 | AB58: =$F$58*Продажи!V9 -> 0 | ... AF58: =$F$58*Продажи!Z9 -> 0 | AG58: =SUM(U58:AF58) -> 0 | AH58: =$G$58*Продажи!AB9 -> 0 | AI58: =$G$58*Продажи!AC9 -> 0 | AJ58: =$G$58*Продажи!AD9 -> 0 | AK58: =$G$58*Продажи!AE9 -> 0 | AL58: =$G$58*Продажи!AF9 -> 0 | AM58: =$G$58*Продажи!AG9 -> 0 | AN58: =$G$58*Продажи!AH9 -> 0 | AO58: =$G$58*Продажи!AI9 -> 0 | ... AS58: =$G$58*Продажи!AM9 -> 0 | AT58: =SUM(AH58:AS58) -> 0
A59: 5.5 | B59: Сырье и материалы 5 | E59: =C59*D59 -> 0 | F59: =E59+E59*'Вводные данные'!$D$4 -> 0 | G59: =F59+F59*'Вводные данные'!$E$4 -> 0 | H59: =$E$59*Продажи!B9 -> 0 | I59: =$E$59*Продажи!C9 -> 0 | J59: =$E$59*Продажи!D9 -> 0 | K59: =$E$59*Продажи!E9 -> 0 | L59: =$E$59*Продажи!F9 -> 0 | M59: =$E$59*Продажи!G9 -> 0 | N59: =$E$59*Продажи!H9 -> 0 | O59: =$E$59*Продажи!I9 -> 0 | ... S59: =$E$59*Продажи!M9 -> 0 | T59: =SUM(H59:S59) -> 0 | U59: =$F$59*Продажи!O9 -> 0 | V59: =$F$59*Продажи!P9 -> 0 | W59: =$F$59*Продажи!Q9 -> 0 | X59: =$F$59*Продажи!R9 -> 0 | Y59: =$F$59*Продажи!S9 -> 0 | Z59: =$F$59*Продажи!T9 -> 0 | AA59: =$F$59*Продажи!U9 -> 0 | AB59: =$F$59*Продажи!V9 -> 0 | ... AF59: =$F$59*Продажи!Z9 -> 0 | AG59: =SUM(U59:AF59) -> 0 | AH59: =$G$59*Продажи!AB9 -> 0 | AI59: =$G$59*Продажи!AC9 -> 0 | AJ59: =$G$59*Продажи!AD9 -> 0 | AK59: =$G$59*Продажи!AE9 -> 0 | AL59: =$G$59*Продажи!AF9 -> 0 | AM59: =$G$59*Продажи!AG9 -> 0 | AN59: =$G$59*Продажи!AH9 -> 0 | AO59: =$G$59*Продажи!AI9 -> 0 | ... AS59: =$G$59*Продажи!AM9 -> 0 | AT59: =SUM(AH59:AS59) -> 0
A60: 5.6 | B60: Сырье и материалы 6 | E60: =C60*D60 -> 0 | F60: =E60+E60*'Вводные данные'!$D$4 -> 0 | G60: =F60+F60*'Вводные данные'!$E$4 -> 0 | H60: =$E$60*Продажи!B9 -> 0 | I60: =$E$60*Продажи!C9 -> 0 | J60: =$E$60*Продажи!D9 -> 0 | K60: =$E$60*Продажи!E9 -> 0 | L60: =$E$60*Продажи!F9 -> 0 | M60: =$E$60*Продажи!G9 -> 0 | N60: =$E$60*Продажи!H9 -> 0 | O60: =$E$60*Продажи!I9 -> 0 | ... S60: =$E$60*Продажи!M9 -> 0 | T60: =SUM(H60:S60) -> 0 | U60: =$F$60*Продажи!O9 -> 0 | V60: =$F$60*Продажи!P9 -> 0 | W60: =$F$60*Продажи!Q9 -> 0 | X60: =$F$60*Продажи!R9 -> 0 | Y60: =$F$60*Продажи!S9 -> 0 | Z60: =$F$60*Продажи!T9 -> 0 | AA60: =$F$60*Продажи!U9 -> 0 | AB60: =$F$60*Продажи!V9 -> 0 | ... AF60: =$F$60*Продажи!Z9 -> 0 | AG60: =SUM(U60:AF60) -> 0 | AH60: =$G$60*Продажи!AB9 -> 0 | AI60: =$G$60*Продажи!AC9 -> 0 | AJ60: =$G$60*Продажи!AD9 -> 0 | AK60: =$G$60*Продажи!AE9 -> 0 | AL60: =$G$60*Продажи!AF9 -> 0 | AM60: =$G$60*Продажи!AG9 -> 0 | AN60: =$G$60*Продажи!AH9 -> 0 | AO60: =$G$60*Продажи!AI9 -> 0 | ... AS60: =$G$60*Продажи!AM9 -> 0 | AT60: =SUM(AH60:AS60) -> 0
A61: 5.7 | B61: Сырье и материалы 7 | E61: =C61*D61 -> 0 | F61: =E61+E61*'Вводные данные'!$D$4 -> 0 | G61: =F61+F61*'Вводные данные'!$E$4 -> 0 | H61: =$E$61*Продажи!B9 -> 0 | I61: =$E$61*Продажи!C9 -> 0 | J61: =$E$61*Продажи!D9 -> 0 | K61: =$E$61*Продажи!E9 -> 0 | L61: =$E$61*Продажи!F9 -> 0 | M61: =$E$61*Продажи!G9 -> 0 | N61: =$E$61*Продажи!H9 -> 0 | O61: =$E$61*Продажи!I9 -> 0 | ... S61: =$E$61*Продажи!M9 -> 0 | T61: =SUM(H61:S61) -> 0 | U61: =$F$61*Продажи!O9 -> 0 | V61: =$F$61*Продажи!P9 -> 0 | W61: =$F$61*Продажи!Q9 -> 0 | X61: =$F$61*Продажи!R9 -> 0 | Y61: =$F$61*Продажи!S9 -> 0 | Z61: =$F$61*Продажи!T9 -> 0 | AA61: =$F$61*Продажи!U9 -> 0 | AB61: =$F$61*Продажи!V9 -> 0 | ... AF61: =$F$61*Продажи!Z9 -> 0 | AG61: =SUM(U61:AF61) -> 0 | AH61: =$G$61*Продажи!AB9 -> 0 | AI61: =$G$61*Продажи!AC9 -> 0 | AJ61: =$G$61*Продажи!AD9 -> 0 | AK61: =$G$61*Продажи!AE9 -> 0 | AL61: =$G$61*Продажи!AF9 -> 0 | AM61: =$G$61*Продажи!AG9 -> 0 | AN61: =$G$61*Продажи!AH9 -> 0 | AO61: =$G$61*Продажи!AI9 -> 0 | ... AS61: =$G$61*Продажи!AM9 -> 0 | AT61: =SUM(AH61:AS61) -> 0
A62: 5.8 | B62: Сырье и материалы 8 | E62: =C62*D62 -> 0 | F62: =E62+E62*'Вводные данные'!$D$4 -> 0 | G62: =F62+F62*'Вводные данные'!$E$4 -> 0 | H62: =$E$62*Продажи!B9 -> 0 | I62: =$E$62*Продажи!C9 -> 0 | J62: =$E$62*Продажи!D9 -> 0 | K62: =$E$62*Продажи!E9 -> 0 | L62: =$E$62*Продажи!F9 -> 0 | M62: =$E$62*Продажи!G9 -> 0 | N62: =$E$62*Продажи!H9 -> 0 | O62: =$E$62*Продажи!I9 -> 0 | ... S62: =$E$62*Продажи!M9 -> 0 | T62: =SUM(H62:S62) -> 0 | U62: =$F$62*Продажи!O9 -> 0 | V62: =$F$62*Продажи!P9 -> 0 | W62: =$F$62*Продажи!Q9 -> 0 | X62: =$F$62*Продажи!R9 -> 0 | Y62: =$F$62*Продажи!S9 -> 0 | Z62: =$F$62*Продажи!T9 -> 0 | AA62: =$F$62*Продажи!U9 -> 0 | AB62: =$F$62*Продажи!V9 -> 0 | ... AF62: =$F$62*Продажи!Z9 -> 0 | AG62: =SUM(U62:AF62) -> 0 | AH62: =$G$62*Продажи!AB9 -> 0 | AI62: =$G$62*Продажи!AC9 -> 0 | AJ62: =$G$62*Продажи!AD9 -> 0 | AK62: =$G$62*Продажи!AE9 -> 0 | AL62: =$G$62*Продажи!AF9 -> 0 | AM62: =$G$62*Продажи!AG9 -> 0 | AN62: =$G$62*Продажи!AH9 -> 0 | AO62: =$G$62*Продажи!AI9 -> 0 | ... AS62: =$G$62*Продажи!AM9 -> 0 | AT62: =SUM(AH62:AS62) -> 0
A63: 5.9 | B63: Сырье и материалы 9 | E63: =C63*D63 -> 0 | F63: =E63+E63*'Вводные данные'!$D$4 -> 0 | G63: =F63+F63*'Вводные данные'!$E$4 -> 0 | H63: =$E$63*Продажи!B9 -> 0 | I63: =$E$63*Продажи!C9 -> 0 | J63: =$E$63*Продажи!D9 -> 0 | K63: =$E$63*Продажи!E9 -> 0 | L63: =$E$63*Продажи!F9 -> 0 | M63: =$E$63*Продажи!G9 -> 0 | N63: =$E$63*Продажи!H9 -> 0 | O63: =$E$63*Продажи!I9 -> 0 | ... S63: =$E$63*Продажи!M9 -> 0 | T63: =SUM(H63:S63) -> 0 | U63: =$F$63*Продажи!O9 -> 0 | V63: =$F$63*Продажи!P9 -> 0 | W63: =$F$63*Продажи!Q9 -> 0 | X63: =$F$63*Продажи!R9 -> 0 | Y63: =$F$63*Продажи!S9 -> 0 | Z63: =$F$63*Продажи!T9 -> 0 | AA63: =$F$63*Продажи!U9 -> 0 | AB63: =$F$63*Продажи!V9 -> 0 | ... AF63: =$F$63*Продажи!Z9 -> 0 | AG63: =SUM(U63:AF63) -> 0 | AH63: =$G$63*Продажи!AB9 -> 0 | AI63: =$G$63*Продажи!AC9 -> 0 | AJ63: =$G$63*Продажи!AD9 -> 0 | AK63: =$G$63*Продажи!AE9 -> 0 | AL63: =$G$63*Продажи!AF9 -> 0 | AM63: =$G$63*Продажи!AG9 -> 0 | AN63: =$G$63*Продажи!AH9 -> 0 | AO63: =$G$63*Продажи!AI9 -> 0 | ... AS63: =$G$63*Продажи!AM9 -> 0 | AT63: =SUM(AH63:AS63) -> 0
A64: 5.10 | B64: Сырье и материалы 10 | E64: =C64*D64 -> 0 | F64: =E64+E64*'Вводные данные'!$D$4 -> 0 | G64: =F64+F64*'Вводные данные'!$E$4 -> 0 | H64: =$E$64*Продажи!B9 -> 0 | I64: =$E$64*Продажи!C9 -> 0 | J64: =$E$64*Продажи!D9 -> 0 | K64: =$E$64*Продажи!E9 -> 0 | L64: =$E$64*Продажи!F9 -> 0 | M64: =$E$64*Продажи!G9 -> 0 | N64: =$E$64*Продажи!H9 -> 0 | O64: =$E$64*Продажи!I9 -> 0 | ... S64: =$E$64*Продажи!M9 -> 0 | T64: =SUM(H64:S64) -> 0 | U64: =$F$64*Продажи!O9 -> 0 | V64: =$F$64*Продажи!P9 -> 0 | W64: =$F$64*Продажи!Q9 -> 0 | X64: =$F$64*Продажи!R9 -> 0 | Y64: =$F$64*Продажи!S9 -> 0 | Z64: =$F$64*Продажи!T9 -> 0 | AA64: =$F$64*Продажи!U9 -> 0 | AB64: =$F$64*Продажи!V9 -> 0 | ... AF64: =$F$64*Продажи!Z9 -> 0 | AG64: =SUM(U64:AF64) -> 0 | AH64: =$G$64*Продажи!AB9 -> 0 | AI64: =$G$64*Продажи!AC9 -> 0 | AJ64: =$G$64*Продажи!AD9 -> 0 | AK64: =$G$64*Продажи!AE9 -> 0 | AL64: =$G$64*Продажи!AF9 -> 0 | AM64: =$G$64*Продажи!AG9 -> 0 | AN64: =$G$64*Продажи!AH9 -> 0 | AO64: =$G$64*Продажи!AI9 -> 0 | ... AS64: =$G$64*Продажи!AM9 -> 0 | AT64: =SUM(AH64:AS64) -> 0
A65: 5.11 | B65: Cправочно стоимость услуги | H65: ='Продукция и цена '!C8 -> 20000 | T65: =H65 -> 20000 | U65: ='Продукция и цена '!D8 -> 23000 | AG65: =SUM(U65:AF65) -> 23000 | AH65: ='Продукция и цена '!E8 -> 26450 | AT65: =SUM(AH65:AS65) -> 26450
A66: 6 | B66: ='Продукция и цена '!A9 -> 0 | C66: - | D66: - | E66: 1 год | F66: 2 год | G66: 3 год | H66: =SUM(H67:H76) -> 0 | I66: =SUM(I67:I76) -> 0 | J66: =SUM(J67:J76) -> 0 | K66: =SUM(K67:K76) -> 0 | L66: =SUM(L67:L76) -> 0 | M66: =SUM(M67:M76) -> 0 | N66: =SUM(N67:N76) -> 0 | O66: =SUM(O67:O76) -> 0 | ... S66: =SUM(S67:S76) -> 0 | T66: =SUM(H66:S66) -> 0 | U66: =SUM(U67:U76) -> 0 | V66: =SUM(V67:V76) -> 0 | W66: =SUM(W67:W76) -> 0 | X66: =SUM(X67:X76) -> 0 | Y66: =SUM(Y67:Y76) -> 0 | Z66: =SUM(Z67:Z76) -> 0 | AA66: =SUM(AA67:AA76) -> 0 | AB66: =SUM(AB67:AB76) -> 0 | ... AF66: =SUM(AF67:AF76) -> 0 | AG66: =SUM(U66:AF66) -> 0 | AH66: =SUM(AH67:AH76) -> 0 | AI66: =SUM(AI67:AI76) -> 0 | AJ66: =SUM(AJ67:AJ76) -> 0 | AK66: =SUM(AK67:AK76) -> 0 | AL66: =SUM(AL67:AL76) -> 0 | AM66: =SUM(AM67:AM76) -> 0 | AN66: =SUM(AN67:AN76) -> 0 | AO66: =SUM(AO67:AO76) -> 0 | ... AS66: =SUM(AS67:AS76) -> 0 | AT66: =SUM(AH66:AS66) -> 0
A67: 6.1 | B67: Сырье и материалы 1 | E67: =C67*D67 -> 0 | F67: =E67+E67*'Вводные данные'!$D$4 -> 0 | G67: =F67+F67*'Вводные данные'!$E$4 -> 0 | H67: =$E$67*Продажи!B10 -> 0 | I67: =$E$67*Продажи!C10 -> 0 | J67: =$E$67*Продажи!D10 -> 0 | K67: =$E$67*Продажи!E10 -> 0 | L67: =$E$67*Продажи!F10 -> 0 | M67: =$E$67*Продажи!G10 -> 0 | N67: =$E$67*Продажи!H10 -> 0 | O67: =$E$67*Продажи!I10 -> 0 | ... S67: =$E$67*Продажи!M10 -> 0 | T67: =SUM(H67:S67) -> 0 | U67: =$F$67*Продажи!O10 -> 0 | V67: =$F$67*Продажи!P10 -> 0 | W67: =$F$67*Продажи!Q10 -> 0 | X67: =$F$67*Продажи!R10 -> 0 | Y67: =$F$67*Продажи!S10 -> 0 | Z67: =$F$67*Продажи!T10 -> 0 | AA67: =$F$67*Продажи!U10 -> 0 | AB67: =$F$67*Продажи!V10 -> 0 | ... AF67: =$F$67*Продажи!Z10 -> 0 | AG67: =SUM(U67:AF67) -> 0 | AH67: =$G$67*Продажи!AB10 -> 0 | AI67: =$G$67*Продажи!AC10 -> 0 | AJ67: =$G$67*Продажи!AD10 -> 0 | AK67: =$G$67*Продажи!AE10 -> 0 | AL67: =$G$67*Продажи!AF10 -> 0 | AM67: =$G$67*Продажи!AG10 -> 0 | AN67: =$G$67*Продажи!AH10 -> 0 | AO67: =$G$67*Продажи!AI10 -> 0 | ... AS67: =$G$67*Продажи!AM10 -> 0 | AT67: =SUM(AH67:AS67) -> 0
A68: 6.2 | B68: Сырье и материалы 2 | E68: =C68*D68 -> 0 | F68: =E68+E68*'Вводные данные'!$D$4 -> 0 | G68: =F68+F68*'Вводные данные'!$E$4 -> 0 | H68: =$E$68*Продажи!B10 -> 0 | I68: =$E$68*Продажи!C10 -> 0 | J68: =$E$68*Продажи!D10 -> 0 | K68: =$E$68*Продажи!E10 -> 0 | L68: =$E$68*Продажи!F10 -> 0 | M68: =$E$68*Продажи!G10 -> 0 | N68: =$E$68*Продажи!H10 -> 0 | O68: =$E$68*Продажи!I10 -> 0 | ... S68: =$E$68*Продажи!M10 -> 0 | T68: =SUM(H68:S68) -> 0 | U68: =$F$68*Продажи!O10 -> 0 | V68: =$F$68*Продажи!P10 -> 0 | W68: =$F$68*Продажи!Q10 -> 0 | X68: =$F$68*Продажи!R10 -> 0 | Y68: =$F$68*Продажи!S10 -> 0 | Z68: =$F$68*Продажи!T10 -> 0 | AA68: =$F$68*Продажи!U10 -> 0 | AB68: =$F$68*Продажи!V10 -> 0 | ... AF68: =$F$68*Продажи!Z10 -> 0 | AG68: =SUM(U68:AF68) -> 0 | AH68: =$G$68*Продажи!AB10 -> 0 | AI68: =$G$68*Продажи!AC10 -> 0 | AJ68: =$G$68*Продажи!AD10 -> 0 | AK68: =$G$68*Продажи!AE10 -> 0 | AL68: =$G$68*Продажи!AF10 -> 0 | AM68: =$G$68*Продажи!AG10 -> 0 | AN68: =$G$68*Продажи!AH10 -> 0 | AO68: =$G$68*Продажи!AI10 -> 0 | ... AS68: =$G$68*Продажи!AM10 -> 0 | AT68: =SUM(AH68:AS68) -> 0
A69: 6.3 | B69: Сырье и материалы 3 | E69: =C69*D69 -> 0 | F69: =E69+E69*'Вводные данные'!$D$4 -> 0 | G69: =F69+F69*'Вводные данные'!$E$4 -> 0 | H69: =$E$69*Продажи!B10 -> 0 | I69: =$E$69*Продажи!C10 -> 0 | J69: =$E$69*Продажи!D10 -> 0 | K69: =$E$69*Продажи!E10 -> 0 | L69: =$E$69*Продажи!F10 -> 0 | M69: =$E$69*Продажи!G10 -> 0 | N69: =$E$69*Продажи!H10 -> 0 | O69: =$E$69*Продажи!I10 -> 0 | ... S69: =$E$69*Продажи!M10 -> 0 | T69: =SUM(H69:S69) -> 0 | U69: =$F$69*Продажи!O10 -> 0 | V69: =$F$69*Продажи!P10 -> 0 | W69: =$F$69*Продажи!Q10 -> 0 | X69: =$F$69*Продажи!R10 -> 0 | Y69: =$F$69*Продажи!S10 -> 0 | Z69: =$F$69*Продажи!T10 -> 0 | AA69: =$F$69*Продажи!U10 -> 0 | AB69: =$F$69*Продажи!V10 -> 0 | ... AF69: =$F$69*Продажи!Z10 -> 0 | AG69: =SUM(U69:AF69) -> 0 | AH69: =$G$69*Продажи!AB10 -> 0 | AI69: =$G$69*Продажи!AC10 -> 0 | AJ69: =$G$69*Продажи!AD10 -> 0 | AK69: =$G$69*Продажи!AE10 -> 0 | AL69: =$G$69*Продажи!AF10 -> 0 | AM69: =$G$69*Продажи!AG10 -> 0 | AN69: =$G$69*Продажи!AH10 -> 0 | AO69: =$G$69*Продажи!AI10 -> 0 | ... AS69: =$G$69*Продажи!AM10 -> 0 | AT69: =SUM(AH69:AS69) -> 0
A70: 6.4 | B70: Сырье и материалы 4 | E70: =C70*D70 -> 0 | F70: =E70+E70*'Вводные данные'!$D$4 -> 0 | G70: =F70+F70*'Вводные данные'!$E$4 -> 0 | H70: =$E$70*Продажи!B10 -> 0 | I70: =$E$70*Продажи!C10 -> 0 | J70: =$E$70*Продажи!D10 -> 0 | K70: =$E$70*Продажи!E10 -> 0 | L70: =$E$70*Продажи!F10 -> 0 | M70: =$E$70*Продажи!G10 -> 0 | N70: =$E$70*Продажи!H10 -> 0 | O70: =$E$70*Продажи!I10 -> 0 | ... S70: =$E$70*Продажи!M10 -> 0 | T70: =SUM(H70:S70) -> 0 | U70: =$F$70*Продажи!O10 -> 0 | V70: =$F$70*Продажи!P10 -> 0 | W70: =$F$70*Продажи!Q10 -> 0 | X70: =$F$70*Продажи!R10 -> 0 | Y70: =$F$70*Продажи!S10 -> 0 | Z70: =$F$70*Продажи!T10 -> 0 | AA70: =$F$70*Продажи!U10 -> 0 | AB70: =$F$70*Продажи!V10 -> 0 | ... AF70: =$F$70*Продажи!Z10 -> 0 | AG70: =SUM(U70:AF70) -> 0 | AH70: =$G$70*Продажи!AB10 -> 0 | AI70: =$G$70*Продажи!AC10 -> 0 | AJ70: =$G$70*Продажи!AD10 -> 0 | AK70: =$G$70*Продажи!AE10 -> 0 | AL70: =$G$70*Продажи!AF10 -> 0 | AM70: =$G$70*Продажи!AG10 -> 0 | AN70: =$G$70*Продажи!AH10 -> 0 | AO70: =$G$70*Продажи!AI10 -> 0 | ... AS70: =$G$70*Продажи!AM10 -> 0 | AT70: =SUM(AH70:AS70) -> 0
A71: 6.5 | B71: Сырье и материалы 5 | E71: =C71*D71 -> 0 | F71: =E71+E71*'Вводные данные'!$D$4 -> 0 | G71: =F71+F71*'Вводные данные'!$E$4 -> 0 | H71: =$E$71*Продажи!B10 -> 0 | I71: =$E$71*Продажи!C10 -> 0 | J71: =$E$71*Продажи!D10 -> 0 | K71: =$E$71*Продажи!E10 -> 0 | L71: =$E$71*Продажи!F10 -> 0 | M71: =$E$71*Продажи!G10 -> 0 | N71: =$E$71*Продажи!H10 -> 0 | O71: =$E$71*Продажи!I10 -> 0 | ... S71: =$E$71*Продажи!M10 -> 0 | T71: =SUM(H71:S71) -> 0 | U71: =$F$71*Продажи!O10 -> 0 | V71: =$F$71*Продажи!P10 -> 0 | W71: =$F$71*Продажи!Q10 -> 0 | X71: =$F$71*Продажи!R10 -> 0 | Y71: =$F$71*Продажи!S10 -> 0 | Z71: =$F$71*Продажи!T10 -> 0 | AA71: =$F$71*Продажи!U10 -> 0 | AB71: =$F$71*Продажи!V10 -> 0 | ... AF71: =$F$71*Продажи!Z10 -> 0 | AG71: =SUM(U71:AF71) -> 0 | AH71: =$G$71*Продажи!AB10 -> 0 | AI71: =$G$71*Продажи!AC10 -> 0 | AJ71: =$G$71*Продажи!AD10 -> 0 | AK71: =$G$71*Продажи!AE10 -> 0 | AL71: =$G$71*Продажи!AF10 -> 0 | AM71: =$G$71*Продажи!AG10 -> 0 | AN71: =$G$71*Продажи!AH10 -> 0 | AO71: =$G$71*Продажи!AI10 -> 0 | ... AS71: =$G$71*Продажи!AM10 -> 0 | AT71: =SUM(AH71:AS71) -> 0
A72: 6.6 | B72: Сырье и материалы 6 | E72: =C72*D72 -> 0 | F72: =E72+E72*'Вводные данные'!$D$4 -> 0 | G72: =F72+F72*'Вводные данные'!$E$4 -> 0 | H72: =$E$72*Продажи!B10 -> 0 | I72: =$E$72*Продажи!C10 -> 0 | J72: =$E$72*Продажи!D10 -> 0 | K72: =$E$72*Продажи!E10 -> 0 | L72: =$E$72*Продажи!F10 -> 0 | M72: =$E$72*Продажи!G10 -> 0 | N72: =$E$72*Продажи!H10 -> 0 | O72: =$E$72*Продажи!I10 -> 0 | ... S72: =$E$72*Продажи!M10 -> 0 | T72: =SUM(H72:S72) -> 0 | U72: =$F$72*Продажи!O10 -> 0 | V72: =$F$72*Продажи!P10 -> 0 | W72: =$F$72*Продажи!Q10 -> 0 | X72: =$F$72*Продажи!R10 -> 0 | Y72: =$F$72*Продажи!S10 -> 0 | Z72: =$F$72*Продажи!T10 -> 0 | AA72: =$F$72*Продажи!U10 -> 0 | AB72: =$F$72*Продажи!V10 -> 0 | ... AF72: =$F$72*Продажи!Z10 -> 0 | AG72: =SUM(U72:AF72) -> 0 | AH72: =$G$72*Продажи!AB10 -> 0 | AI72: =$G$72*Продажи!AC10 -> 0 | AJ72: =$G$72*Продажи!AD10 -> 0 | AK72: =$G$72*Продажи!AE10 -> 0 | AL72: =$G$72*Продажи!AF10 -> 0 | AM72: =$G$72*Продажи!AG10 -> 0 | AN72: =$G$72*Продажи!AH10 -> 0 | AO72: =$G$72*Продажи!AI10 -> 0 | ... AS72: =$G$72*Продажи!AM10 -> 0 | AT72: =SUM(AH72:AS72) -> 0
A73: 6.7 | B73: Сырье и материалы 7 | E73: =C73*D73 -> 0 | F73: =E73+E73*'Вводные данные'!$D$4 -> 0 | G73: =F73+F73*'Вводные данные'!$E$4 -> 0 | H73: =$E$73*Продажи!B10 -> 0 | I73: =$E$73*Продажи!C10 -> 0 | J73: =$E$73*Продажи!D10 -> 0 | K73: =$E$73*Продажи!E10 -> 0 | L73: =$E$73*Продажи!F10 -> 0 | M73: =$E$73*Продажи!G10 -> 0 | N73: =$E$73*Продажи!H10 -> 0 | O73: =$E$73*Продажи!I10 -> 0 | ... S73: =$E$73*Продажи!M10 -> 0 | T73: =SUM(H73:S73) -> 0 | U73: =$F$73*Продажи!O10 -> 0 | V73: =$F$73*Продажи!P10 -> 0 | W73: =$F$73*Продажи!Q10 -> 0 | X73: =$F$73*Продажи!R10 -> 0 | Y73: =$F$73*Продажи!S10 -> 0 | Z73: =$F$73*Продажи!T10 -> 0 | AA73: =$F$73*Продажи!U10 -> 0 | AB73: =$F$73*Продажи!V10 -> 0 | ... AF73: =$F$73*Продажи!Z10 -> 0 | AG73: =SUM(U73:AF73) -> 0 | AH73: =$G$73*Продажи!AB10 -> 0 | AI73: =$G$73*Продажи!AC10 -> 0 | AJ73: =$G$73*Продажи!AD10 -> 0 | AK73: =$G$73*Продажи!AE10 -> 0 | AL73: =$G$73*Продажи!AF10 -> 0 | AM73: =$G$73*Продажи!AG10 -> 0 | AN73: =$G$73*Продажи!AH10 -> 0 | AO73: =$G$73*Продажи!AI10 -> 0 | ... AS73: =$G$73*Продажи!AM10 -> 0 | AT73: =SUM(AH73:AS73) -> 0
A74: 6.8 | B74: Сырье и материалы 8 | E74: =C74*D74 -> 0 | F74: =E74+E74*'Вводные данные'!$D$4 -> 0 | G74: =F74+F74*'Вводные данные'!$E$4 -> 0 | H74: =$E$74*Продажи!B10 -> 0 | I74: =$E$74*Продажи!C10 -> 0 | J74: =$E$74*Продажи!D10 -> 0 | K74: =$E$74*Продажи!E10 -> 0 | L74: =$E$74*Продажи!F10 -> 0 | M74: =$E$74*Продажи!G10 -> 0 | N74: =$E$74*Продажи!H10 -> 0 | O74: =$E$74*Продажи!I10 -> 0 | ... S74: =$E$74*Продажи!M10 -> 0 | T74: =SUM(H74:S74) -> 0 | U74: =$F$74*Продажи!O10 -> 0 | V74: =$F$74*Продажи!P10 -> 0 | W74: =$F$74*Продажи!Q10 -> 0 | X74: =$F$74*Продажи!R10 -> 0 | Y74: =$F$74*Продажи!S10 -> 0 | Z74: =$F$74*Продажи!T10 -> 0 | AA74: =$F$74*Продажи!U10 -> 0 | AB74: =$F$74*Продажи!V10 -> 0 | ... AF74: =$F$74*Продажи!Z10 -> 0 | AG74: =SUM(U74:AF74) -> 0 | AH74: =$G$74*Продажи!AB10 -> 0 | AI74: =$G$74*Продажи!AC10 -> 0 | AJ74: =$G$74*Продажи!AD10 -> 0 | AK74: =$G$74*Продажи!AE10 -> 0 | AL74: =$G$74*Продажи!AF10 -> 0 | AM74: =$G$74*Продажи!AG10 -> 0 | AN74: =$G$74*Продажи!AH10 -> 0 | AO74: =$G$74*Продажи!AI10 -> 0 | ... AS74: =$G$74*Продажи!AM10 -> 0 | AT74: =SUM(AH74:AS74) -> 0
A75: 6.9 | B75: Сырье и материалы 9 | E75: =C75*D75 -> 0 | F75: =E75+E75*'Вводные данные'!$D$4 -> 0 | G75: =F75+F75*'Вводные данные'!$E$4 -> 0 | H75: =$E$75*Продажи!B10 -> 0 | I75: =$E$75*Продажи!C10 -> 0 | J75: =$E$75*Продажи!D10 -> 0 | K75: =$E$75*Продажи!E10 -> 0 | L75: =$E$75*Продажи!F10 -> 0 | M75: =$E$75*Продажи!G10 -> 0 | N75: =$E$75*Продажи!H10 -> 0 | O75: =$E$75*Продажи!I10 -> 0 | ... S75: =$E$75*Продажи!M10 -> 0 | T75: =SUM(H75:S75) -> 0 | U75: =$F$75*Продажи!O10 -> 0 | V75: =$F$75*Продажи!P10 -> 0 | W75: =$F$75*Продажи!Q10 -> 0 | X75: =$F$75*Продажи!R10 -> 0 | Y75: =$F$75*Продажи!S10 -> 0 | Z75: =$F$75*Продажи!T10 -> 0 | AA75: =$F$75*Продажи!U10 -> 0 | AB75: =$F$75*Продажи!V10 -> 0 | ... AF75: =$F$75*Продажи!Z10 -> 0 | AG75: =SUM(U75:AF75) -> 0 | AH75: =$G$75*Продажи!AB10 -> 0 | AI75: =$G$75*Продажи!AC10 -> 0 | AJ75: =$G$75*Продажи!AD10 -> 0 | AK75: =$G$75*Продажи!AE10 -> 0 | AL75: =$G$75*Продажи!AF10 -> 0 | AM75: =$G$75*Продажи!AG10 -> 0 | AN75: =$G$75*Продажи!AH10 -> 0 | AO75: =$G$75*Продажи!AI10 -> 0 | ... AS75: =$G$75*Продажи!AM10 -> 0 | AT75: =SUM(AH75:AS75) -> 0
A76: 6.10 | B76: Сырье и материалы 10 | E76: =C76*D76 -> 0 | F76: =E76+E76*'Вводные данные'!$D$4 -> 0 | G76: =F76+F76*'Вводные данные'!$E$4 -> 0 | H76: =$E$76*Продажи!B10 -> 0 | I76: =$E$76*Продажи!C10 -> 0 | J76: =$E$76*Продажи!D10 -> 0 | K76: =$E$76*Продажи!E10 -> 0 | L76: =$E$76*Продажи!F10 -> 0 | M76: =$E$76*Продажи!G10 -> 0 | N76: =$E$76*Продажи!H10 -> 0 | O76: =$E$76*Продажи!I10 -> 0 | ... S76: =$E$76*Продажи!M10 -> 0 | T76: =SUM(H76:S76) -> 0 | U76: =$F$76*Продажи!O10 -> 0 | V76: =$F$76*Продажи!P10 -> 0 | W76: =$F$76*Продажи!Q10 -> 0 | X76: =$F$76*Продажи!R10 -> 0 | Y76: =$F$76*Продажи!S10 -> 0 | Z76: =$F$76*Продажи!T10 -> 0 | AA76: =$F$76*Продажи!U10 -> 0 | AB76: =$F$76*Продажи!V10 -> 0 | ... AF76: =$F$76*Продажи!Z10 -> 0 | AG76: =SUM(U76:AF76) -> 0 | AH76: =$G$76*Продажи!AB10 -> 0 | AI76: =$G$76*Продажи!AC10 -> 0 | AJ76: =$G$76*Продажи!AD10 -> 0 | AK76: =$G$76*Продажи!AE10 -> 0 | AL76: =$G$76*Продажи!AF10 -> 0 | AM76: =$G$76*Продажи!AG10 -> 0 | AN76: =$G$76*Продажи!AH10 -> 0 | AO76: =$G$76*Продажи!AI10 -> 0 | ... AS76: =$G$76*Продажи!AM10 -> 0 | AT76: =SUM(AH76:AS76) -> 0
A77: 6.11 | B77: Cправочно стоимость услуги | H77: ='Продукция и цена '!C9 -> 0 | T77: =H77 -> 0 | U77: ='Продукция и цена '!D9 -> 0 | AG77: =SUM(U77:AF77) -> 0 | AH77: ='Продукция и цена '!E9 -> 0 | AT77: =SUM(AH77:AS77) -> 0
A78: 7 | B78: ='Продукция и цена '!A10 -> 0 | C78: - | D78: - | E78: 1 год | F78: 2 год | G78: 3 год | H78: =SUM(H79:H88) -> 0 | I78: =SUM(I79:I88) -> 0 | J78: =SUM(J79:J88) -> 0 | K78: =SUM(K79:K88) -> 0 | L78: =SUM(L79:L88) -> 0 | M78: =SUM(M79:M88) -> 0 | N78: =SUM(N79:N88) -> 0 | O78: =SUM(O79:O88) -> 0 | ... S78: =SUM(S79:S88) -> 0 | T78: =SUM(H78:S78) -> 0 | U78: =SUM(U79:U88) -> 0 | V78: =SUM(V79:V88) -> 0 | W78: =SUM(W79:W88) -> 0 | X78: =SUM(X79:X88) -> 0 | Y78: =SUM(Y79:Y88) -> 0 | Z78: =SUM(Z79:Z88) -> 0 | AA78: =SUM(AA79:AA88) -> 0 | AB78: =SUM(AB79:AB88) -> 0 | ... AF78: =SUM(AF79:AF88) -> 0 | AG78: =SUM(U78:AF78) -> 0 | AH78: =SUM(AH79:AH88) -> 0 | AI78: =SUM(AI79:AI88) -> 0 | AJ78: =SUM(AJ79:AJ88) -> 0 | AK78: =SUM(AK79:AK88) -> 0 | AL78: =SUM(AL79:AL88) -> 0 | AM78: =SUM(AM79:AM88) -> 0 | AN78: =SUM(AN79:AN88) -> 0 | AO78: =SUM(AO79:AO88) -> 0 | ... AS78: =SUM(AS79:AS88) -> 0 | AT78: =SUM(AH78:AS78) -> 0
A79: 7.1 | B79: Сырье и материалы 1 | E79: =C79*D79 -> 0 | F79: =E79+E79*'Вводные данные'!$D$4 -> 0 | G79: =F79+F79*'Вводные данные'!$E$4 -> 0 | H79: =$E$79*Продажи!B11 -> 0 | I79: =$E$79*Продажи!C11 -> 0 | J79: =$E$79*Продажи!D11 -> 0 | K79: =$E$79*Продажи!E11 -> 0 | L79: =$E$79*Продажи!F11 -> 0 | M79: =$E$79*Продажи!G11 -> 0 | N79: =$E$79*Продажи!H11 -> 0 | O79: =$E$79*Продажи!I11 -> 0 | ... S79: =$E$79*Продажи!M11 -> 0 | T79: =SUM(H79:S79) -> 0 | U79: =$F$79*Продажи!O11 -> 0 | V79: =$F$79*Продажи!P11 -> 0 | W79: =$F$79*Продажи!Q11 -> 0 | X79: =$F$79*Продажи!R11 -> 0 | Y79: =$F$79*Продажи!S11 -> 0 | Z79: =$F$79*Продажи!T11 -> 0 | AA79: =$F$79*Продажи!U11 -> 0 | AB79: =$F$79*Продажи!V11 -> 0 | ... AF79: =$F$79*Продажи!Z11 -> 0 | AG79: =SUM(U79:AF79) -> 0 | AH79: =$G$79*Продажи!AB11 -> 0 | AI79: =$G$79*Продажи!AC11 -> 0 | AJ79: =$G$79*Продажи!AD11 -> 0 | AK79: =$G$79*Продажи!AE11 -> 0 | AL79: =$G$79*Продажи!AF11 -> 0 | AM79: =$G$79*Продажи!AG11 -> 0 | AN79: =$G$79*Продажи!AH11 -> 0 | AO79: =$G$79*Продажи!AI11 -> 0 | ... AS79: =$G$79*Продажи!AM11 -> 0 | AT79: =SUM(AH79:AS79) -> 0
